Workbook
Name Actividade: '[1]Listas para formulário'!$G$2:$G$9
Name Ambito: [2]Tabelas!$AG$1:$AG$5
Name Bolsas_de_Iniciação_Científica__BIC: 'Valores bolsas e 57_2016'!$A$1:$B$9
Name Classificação_das_despesas: '[1]Listas para formulário'!$A$2:$A$15
Name Estabelecimento: '[1]Listas para formulário'!$E$2:$E$4
Name GeneroList: [3]dados_aux!$B$42:$B$45
Name lista: 'Valores bolsas e 57_2016'!$A$1:$A$9
Name Lista2: 'Valores bolsas e 57_2016'!#REF!
Name Lista2: 'Valores bolsas e 57_2016'!#REF!
Name Lista2: 'Valores bolsas e 57_2016'!#REF!
Name listaB: 'Valores bolsas e 57_2016'!$A$1:$B$9
Name Listas: [4]Folha1!$A$18:$A$90
Name LISTAZ: [5]Folha1!$A$18:$A$90
Name RespostaList: [3]dados_aux!$B$48:$B$50
Name RHExistNivelQualificList: [3]dados_aux!$B$100:$B$108
Name S_N: [2]Tabelas!$AF$1:$AF$2
Name SituacaoActual: [2]Tabelas!$AH$1:$AH$3
Name SNC: '[1]Listas para formulário'!$C$2:$C$23
Name Tipo_de_RH: [3]dados_aux!$B$82:$B$97
Name TipodeProteccao: [2]Tabelas!$AC$1:$AC$6

Sheet 2.Equipa de Investigação
G10: Montante associado à OCS | H10: 4320 | I10: 1ETI/MÊS
B11: 2. DETALHE DE EQUIPA POR ANO
F12: FTE
B13: Beneficiário | C13: Afetação para o Cálculo de Financiamento | D13: NOME | E13: Vínculo | F13: 2024 | G13: 2025 | H13: 2026 | I13: 2027 | J13: Total
B14: Universidade do Algarve | C14: Sim | D14: José Paulo Monteiro | E14: Contrato trabalho com o beneficiário | F14: 0 | G14: =SUMIF(CRONOGRAMA!#REF!,D14,CRONOGRAMA!#REF!) -> #REF! | H14: =SUMIF(CRONOGRAMA!#REF!,D14,CRONOGRAMA!#REF!) -> #REF! | I14: =SUMIF(CRONOGRAMA!#REF!,D14,CRONOGRAMA!#REF!) -> #REF! | J14: =SUM(F14:I14) -> #REF!
B15: Universidade do Algarve | C15: Sim | D15: Maria Conceição Neves | E15: Contrato trabalho com o beneficiário | F15: 0 | G15: =SUMIF(CRONOGRAMA!#REF!,D15,CRONOGRAMA!#REF!) -> #REF! | H15: =SUMIF(CRONOGRAMA!#REF!,D15,CRONOGRAMA!#REF!) -> #REF! | I15: =SUMIF(CRONOGRAMA!#REF!,D15,CRONOGRAMA!#REF!) -> #REF! | J15: =SUM(F15:I15) -> #REF!
F16: 0 | G16: =SUMIF(CRONOGRAMA!#REF!,D16,CRONOGRAMA!#REF!) -> #REF! | H16: =SUMIF(CRONOGRAMA!#REF!,D16,CRONOGRAMA!#REF!) -> #REF! | I16: =SUMIF(CRONOGRAMA!#REF!,D16,CRONOGRAMA!#REF!) -> #REF! | J16: =SUM(F16:I16) -> #REF! | K16: -
F17: 0 | G17: =SUMIF(CRONOGRAMA!#REF!,D17,CRONOGRAMA!#REF!) -> #REF! | H17: =SUMIF(CRONOGRAMA!#REF!,D17,CRONOGRAMA!#REF!) -> #REF! | I17: =SUMIF(CRONOGRAMA!#REF!,D17,CRONOGRAMA!#REF!) -> #REF! | J17: =SUM(F17:I17) -> #REF!
F18: 0 | G18: =SUMIF(CRONOGRAMA!#REF!,D18,CRONOGRAMA!#REF!) -> #REF! | H18: =SUMIF(CRONOGRAMA!#REF!,D18,CRONOGRAMA!#REF!) -> #REF! | I18: =SUMIF(CRONOGRAMA!#REF!,D18,CRONOGRAMA!#REF!) -> #REF! | J18: =SUM(F18:I18) -> #REF!
F19: 0 | G19: =SUMIF(CRONOGRAMA!#REF!,D19,CRONOGRAMA!#REF!) -> #REF! | H19: =SUMIF(CRONOGRAMA!#REF!,D19,CRONOGRAMA!#REF!) -> #REF! | I19: =SUMIF(CRONOGRAMA!#REF!,D19,CRONOGRAMA!#REF!) -> #REF! | J19: =SUM(F19:I19) -> #REF!
F20: 0 | G20: =SUMIF(CRONOGRAMA!#REF!,D20,CRONOGRAMA!#REF!) -> #REF! | H20: =SUMIF(CRONOGRAMA!#REF!,D20,CRONOGRAMA!#REF!) -> #REF! | I20: =SUMIF(CRONOGRAMA!#REF!,D20,CRONOGRAMA!#REF!) -> #REF! | J20: =SUM(F20:I20) -> #REF!
F21: 0 | G21: =SUMIF(CRONOGRAMA!#REF!,D21,CRONOGRAMA!#REF!) -> #REF! | H21: =SUMIF(CRONOGRAMA!#REF!,D21,CRONOGRAMA!#REF!) -> #REF! | I21: =SUMIF(CRONOGRAMA!#REF!,D21,CRONOGRAMA!#REF!) -> #REF! | J21: =SUM(F21:I21) -> #REF! | K21: -
F22: 0 | G22: =SUMIF(CRONOGRAMA!#REF!,D22,CRONOGRAMA!#REF!) -> #REF! | H22: =SUMIF(CRONOGRAMA!#REF!,D22,CRONOGRAMA!#REF!) -> #REF! | I22: =SUMIF(CRONOGRAMA!#REF!,D22,CRONOGRAMA!#REF!) -> #REF! | J22: =SUM(F22:I22) -> #REF!
F23: 0 | G23: =SUMIF(CRONOGRAMA!#REF!,D23,CRONOGRAMA!#REF!) -> #REF! | H23: =SUMIF(CRONOGRAMA!#REF!,D23,CRONOGRAMA!#REF!) -> #REF! | I23: =SUMIF(CRONOGRAMA!#REF!,D23,CRONOGRAMA!#REF!) -> #REF! | J23: =SUM(F23:I23) -> #REF!
F24: 0 | G24: =SUMIF(CRONOGRAMA!#REF!,D24,CRONOGRAMA!#REF!) -> #REF! | H24: =SUMIF(CRONOGRAMA!#REF!,D24,CRONOGRAMA!#REF!) -> #REF! | I24: =SUMIF(CRONOGRAMA!#REF!,D24,CRONOGRAMA!#REF!) -> #REF! | J24: =SUM(F24:I24) -> #REF!
F25: 0 | G25: =SUMIF(CRONOGRAMA!#REF!,D25,CRONOGRAMA!#REF!) -> #REF! | H25: =SUMIF(CRONOGRAMA!#REF!,D25,CRONOGRAMA!#REF!) -> #REF! | I25: =SUMIF(CRONOGRAMA!#REF!,D25,CRONOGRAMA!#REF!) -> #REF! | J25: =SUM(F25:I25) -> #REF!
F26: 0 | G26: =SUMIF(CRONOGRAMA!#REF!,D26,CRONOGRAMA!#REF!) -> #REF! | H26: =SUMIF(CRONOGRAMA!#REF!,D26,CRONOGRAMA!#REF!) -> #REF! | I26: =SUMIF(CRONOGRAMA!#REF!,D26,CRONOGRAMA!#REF!) -> #REF! | J26: =SUM(F26:I26) -> #REF!
F27: 0 | G27: =SUMIF(CRONOGRAMA!#REF!,D27,CRONOGRAMA!#REF!) -> #REF! | H27: =SUMIF(CRONOGRAMA!#REF!,D27,CRONOGRAMA!#REF!) -> #REF! | I27: =SUMIF(CRONOGRAMA!#REF!,D27,CRONOGRAMA!#REF!) -> #REF! | J27: =SUM(F27:I27) -> #REF!
E28: TOTAL | F28: 0 | G28: =SUM(G14:G27) -> #REF! | H28: =SUM(H14:H27) -> #REF! | I28: =SUM(I14:I27) -> #REF! | J28: =SUM(J14:J27) -> #REF! | K28: =J28-J16-J21 -> #REF!
E29: TOTAL FINANCEIRO
B31: 2. QUADRO FINANCEIRO
B33: Beneficiário | D33: FTE | E33: CUSTO TOTAL
B34: =+CRONOGRAMA!#REF! -> #REF! | D34: =SUMIFS($J$14:$J$27,$B$14:$B$27,B34,$C$14:$C$27,"Sim") -> 0 | E34: =+D34*H10 -> 0 | F34: (Valor a ser distribuído da Universidade do Algarve)
B35: =+CRONOGRAMA!#REF! -> #REF! | D35: =SUMIFS($J$14:$J$27,$B$14:$B$27,B35,$C$14:$C$27,"Sim") -> 0 | E35: =+D35*$H$10 -> 0
B36: =+CRONOGRAMA!#REF! -> #REF! | D36: =SUMIFS($J$14:$J$27,$B$14:$B$27,B36,$C$14:$C$27,"Sim") -> 0 | E36: =+D36*$H$10 -> 0
B37: TOTAL | D37: =SUM(D34:D35) -> 0 | E37: =SUM(E34:E35) -> 0

Sheet RESUMO
C10: Informações: Formulário elaborado para uso interno de docentes e investigadores da Universidade do Algarve, destinado a auxilar na elaboração de orçamentos de candidaturas a submeter ao concurso MPr-2023-7: SIID – I&D Empresarial - Operações em Copromoção - Outros territórios , promovido pelo Algarve 2030 . As células assinaladas a cor azul correspondem campos de preenchimento obrigatório. O projeto tem que que ser validado pela Divisão de Informação e Estatística (DIE) juntamente com a folha de cálculo deve ser enviado o overview do projeto.
C14: A. Programa Financiador: ALGARVE 2030 B. Para as ENESII: A taxa máxima de financiamento FEDER das operações elegíveis para o ALGARVE 2030 é de 75%. Todavia a taxa pode ser de 80% nos termos do nº10 do 133º do REITD em caso de superação das metas contratualizadas em todos os indicadores de resultado. C. Duração máxima dos projetos: 36 meses, exceto em casos devidamente justificados. D. Custos elegíveis: os custos das operações serão exclusivamente financiados através da metodologia de custos simplificados, na modalidade de custos unitários (custo unitário por FTE/ ETI – full time equivalent/ equivalente a tempo integral). O custo por FTE/ETI é de 4.320Euros E. Orçamento total: o projeto deve integrar um investimento elegível mínimo de 150.000 €. O montante do investimento é atingido pelos FTEs/ ETIs do projeto.
C17: PROJETO
C19: Aviso | E19: SACCT- Projetos de investigação Científica e Desenvolvim ento Tecnológico
C21: Beneficiário principal | E21: Universidade do Algarve | N21: NIF:
C23: Acrónimo e Título | E23: OAKHIMEDES - Adaptações dos sobreiros face às alterações climáticas e como as mesmas promovem a sustentabilidade do ecossistema
C25: Referência
C27: IR na UAlg | E27: Ana Cristina Coelho
C29: Unid. Orgânica | G29: Unidade I&D
C32: Data início | E32: 46296 | F32: (Campo Obrigatório)
C33: Duração Nº Meses | E33: 36 | F33: (Campo Obrigatório)
C34: Data de fim | E34: =IF(E33=0,"",EDATE(E32,E33)-1) -> 47391
C37: ORÇAMENTO
C39: Orçamento elegível | F39: =+BUDGET!G34 -> 580219.2
C40: Taxa de overheads | F40: 0.25
C41: Overheads | F41: =+BUDGET!G33 -> 116043.84
C51: 46387 | E51: =+E32 -> 46296 | F51: =IF(YEAR(C51)=YEAR(E51),MONTH(C51-E51),MONTH(E32-C52)) -> 3
C52: 46387 | E52: =IF(E34=1-1-2026,E34,"01-01-2026") -> 01-01-2026 | F52: =MONTH(C52-E52) -> 12
C53: 46752 | E53: =IF(E34=1-1-2027,E34,"01-01-2027") -> 01-01-2027 | F53: =MONTH(C53-E53) -> 12
C54: 47118 | E54: =IF(E34<=1-1-2028,E34,"01-01-2028") -> 01-01-2028 | F54: =MONTH(C54-E54) -> 12
C55: 47483 | E55: =E34 -> 47391 | F55: =IF(E55="","",MONTH(E55)) -> 9

Sheet ATIVIDADES
P3: Investigação Industrial
P4: Desenvolvimento Experimental
P5: Divulgação e Promoção
P6: Gestão Projeto
C10: Informações: Formulário elaborado para uso interno de docentes e investigadores da Universidade do Algarve, destinado a auxilar na elaboração de orçamentos de candidaturas a submeter ao concurso MPr-2023-7: SIID – I&D Empresarial - Operações em Copromoção - Outros territórios , promovido pelo Algarve 2030 . As células assinaladas a cor azul correspondem campos de preenchimento obrigatório. O projeto tem que que ser validado pela Divisão de Informação e Estatística (DIE) juntamente com a folha de cálculo deve ser enviado o overview do projeto.
C15: ATIVIDADES
C17: Número | D17: Designação | E17: Data de Início | F17: Duração | G17: Data de Fim | H17: Classificação
C18: A1 | D18: Gestão e Coordenação | E18: 46296 | F18: 36 | G18: =IF(OR(E18="",F18="",F18=0),"",EDATE(E18,F18)-1) -> 47391 | H18: Gestão Projeto
C19: A2 | D19: Avaliação da vitalidade das árvores | E19: 46388 | F19: 25 | G19: =IF(OR(E19="",F19="",F19=0),"",EDATE(E19,F19)-1) -> 47149 | H19: Desenvolvimento Experimental
C20: A3 | D20: Ambiente | E20: 46388 | F20: 25 | G20: =IF(OR(E20="",F20="",F20=0),"",EDATE(E20,F20)-1) -> 47149 | H20: Desenvolvimento Experimental
C21: A4 | D21: Homeostasia e genética | E21: 46388 | F21: 25 | G21: =IF(OR(E21="",F21="",F21=0),"",EDATE(E21,F21)-1) -> 47149 | H21: Desenvolvimento Experimental
C22: A5 | D22: Análise e interpretação dos dados | E22: 46753 | F22: 19 | G22: =IF(OR(E22="",F22="",F22=0),"",EDATE(E22,F22)-1) -> 47330 | H22: Desenvolvimento Experimental
C23: A6 | D23: Partilha de conhecimento | E23: 46753 | F23: 21 | G23: =IF(OR(E23="",F23="",F23=0),"",EDATE(E23,F23)-1) -> 47391 | H23: Divulgação e Promoção
C24: A7
C25: A8 | G25: =IF(OR(E25="",F25="",F25=0),"",EDATE(E25,F25)-1)
C26: A9 | G26: =IF(OR(E26="",F26="",F26=0),"",EDATE(E26,F26)-1)
C27: A10 | G27: =IF(OR(E27="",F27="",F27=0),"",EDATE(E27,F27)-1)
C28: A11 | G28: =IF(OR(E28="",F28="",F28=0),"",EDATE(E28,F28)-1)

Sheet CRONOGRAMA
B11: 1.DISTRIBUIÇÂO DA EQUIPA POR ATIVIDADES E POR EQUIPA DE INVESTIGAÇÂO
B13: Atividade | C13: Início (dd-mm-aaaaa) | D13: Duração (meses) | E13: Fim (dd-mm-aaaaa) | F13: =IF(F14<>"",IF(RESUMO!$E$32="","",DATE(YEAR(RESUMO!$E$32),MONTH(RESUMO!$E$32),DAY(RESUMO!$E$32))),"") -> 46296 | G13: =IF(G14<>"",IF(RESUMO!$E$32="","",DATE(YEAR(RESUMO!$E$32),MONTH(RESUMO!$E$32)+F14,DAY(RESUMO!$E$32))),"") -> 46327 | H13: =IF(H14<>"",IF(RESUMO!$E$32="","",DATE(YEAR(RESUMO!$E$32),MONTH(RESUMO!$E$32)+G14,DAY(RESUMO!$E$32))),"") -> 46357 | I13: =IF(I14<>"",IF(RESUMO!$E$32="","",DATE(YEAR(RESUMO!$E$32),MONTH(RESUMO!$E$32)+H14,DAY(RESUMO!$E$32))),"") -> 46388 | J13: =IF(J14<>"",IF(RESUMO!$E$32="","",DATE(YEAR(RESUMO!$E$32),MONTH(RESUMO!$E$32)+I14,DAY(RESUMO!$E$32))),"") -> 46419 | K13: =IF(K14<>"",IF(RESUMO!$E$32="","",DATE(YEAR(RESUMO!$E$32),MONTH(RESUMO!$E$32)+J14,DAY(RESUMO!$E$32))),"") -> 46447 | L13: =IF(L14<>"",IF(RESUMO!$E$32="","",DATE(YEAR(RESUMO!$E$32),MONTH(RESUMO!$E$32)+K14,DAY(RESUMO!$E$32))),"") -> 46478 | M13: =IF(M14<>"",IF(RESUMO!$E$32="","",DATE(YEAR(RESUMO!$E$32),MONTH(RESUMO!$E$32)+L14,DAY(RESUMO!$E$32))),"") -> 46508 | N13: =IF(N14<>"",IF(RESUMO!$E$32="","",DATE(YEAR(RESUMO!$E$32),MONTH(RESUMO!$E$32)+M14,DAY(RESUMO!$E$32))),"") -> 46539 | ... AO13: =IF(AO14<>"",IF(RESUMO!$E$32="","",DATE(YEAR(RESUMO!$E$32),MONTH(RESUMO!$E$32)+AN14,DAY(RESUMO!$E$32))),"") -> 47362
F14: =IF(RESUMO!$E$33>0,1,"") -> 1 | G14: =IF(RESUMO!$E$33>0,F14+1,"") -> 2 | H14: =IF(RESUMO!$E$33>0,G14+1,"") -> 3 | I14: =IF(RESUMO!$E$33>0,H14+1,"") -> 4 | J14: =IF(RESUMO!$E$33>0,I14+1,"") -> 5 | K14: =IF(RESUMO!$E$33>0,J14+1,"") -> 6 | L14: =IF(RESUMO!$E$33>0,K14+1,"") -> 7 | M14: =IF(RESUMO!$E$33>0,L14+1,"") -> 8 | N14: =IF(RESUMO!$E$33>0,M14+1,"") -> 9 | ... AO14: =IF(RESUMO!$E$33>0,AN14+1,"") -> 36
B16: =IF(ATIVIDADES!D18>0,ATIVIDADES!D18,"") -> Gestão e Coordenação | C16: =IF(B16="","",VLOOKUP(B16,ATIVIDADES!$D$17:$F$23,2,FALSE)) -> 46296 | D16: =IF(B16="","",VLOOKUP(B16,ATIVIDADES!$D$18:$F$23,3,FALSE)) -> 36 | E16: =IF(OR(C16="",D16="",D16=0),"",EDATE(C16,D16)-1) -> 47391 | F16: =IF(OR($C16="",$D16=""),0,IF(AND($C16<=F$13,$E16>=F$13),1,0)) -> 1 | G16: =IF(OR($C16="",$D16=""),0,IF(AND($C16<=G$13,$E16>=G$13),F16+1,0)) -> 2 | H16: =IF(OR($C16="",$D16=""),0,IF(AND($C16<=H$13,$E16>=H$13),G16+1,0)) -> 3 | I16: =IF(OR($C16="",$D16=""),0,IF(AND($C16<=I$13,$E16>=I$13),H16+1,0)) -> 4 | J16: =IF(OR($C16="",$D16=""),0,IF(AND($C16<=J$13,$E16>=J$13),I16+1,0)) -> 5 | K16: =IF(OR($C16="",$D16=""),0,IF(AND($C16<=K$13,$E16>=K$13),J16+1,0)) -> 6 | L16: =IF(OR($C16="",$D16=""),0,IF(AND($C16<=L$13,$E16>=L$13),K16+1,0)) -> 7 | M16: =IF(OR($C16="",$D16=""),0,IF(AND($C16<=M$13,$E16>=M$13),L16+1,0)) -> 8 | N16: =IF(OR($C16="",$D16=""),0,IF(AND($C16<=N$13,$E16>=N$13),M16+1,0)) -> 9 | ... AO16: =IF(OR($C16="",$D16=""),0,IF(AND($C16<=AO$13,$E16>=AO$13),AN16+1,0)) -> 36
B17: =IF(ATIVIDADES!D19>0,ATIVIDADES!D19,"") -> Avaliação da vitalidade das árvores | C17: =IF(B17="","",VLOOKUP(B17,ATIVIDADES!$D$17:$F$23,2,FALSE)) -> 46388 | D17: =IF(B17="","",VLOOKUP(B17,ATIVIDADES!$D$18:$F$23,3,FALSE)) -> 25 | E17: =IF(OR(C17="",D17="",D17=0),"",EDATE(C17,D17)-1) -> 47149 | F17: =IF(OR($C17="",$D17=""),0,IF(AND($C17<=F$13,$E17>=F$13),1,0)) -> 0 | G17: =IF(OR($C17="",$D17=""),0,IF(AND($C17<=G$13,$E17>=G$13),F17+1,0)) -> 0 | H17: =IF(OR($C17="",$D17=""),0,IF(AND($C17<=H$13,$E17>=H$13),G17+1,0)) -> 0 | I17: =IF(OR($C17="",$D17=""),0,IF(AND($C17<=I$13,$E17>=I$13),H17+1,0)) -> 1 | J17: =IF(OR($C17="",$D17=""),0,IF(AND($C17<=J$13,$E17>=J$13),I17+1,0)) -> 2 | K17: =IF(OR($C17="",$D17=""),0,IF(AND($C17<=K$13,$E17>=K$13),J17+1,0)) -> 3 | L17: =IF(OR($C17="",$D17=""),0,IF(AND($C17<=L$13,$E17>=L$13),K17+1,0)) -> 4 | M17: =IF(OR($C17="",$D17=""),0,IF(AND($C17<=M$13,$E17>=M$13),L17+1,0)) -> 5 | N17: =IF(OR($C17="",$D17=""),0,IF(AND($C17<=N$13,$E17>=N$13),M17+1,0)) -> 6 | ... AO17: =IF(OR($C17="",$D17=""),0,IF(AND($C17<=AO$13,$E17>=AO$13),AN17+1,0)) -> 0
B18: =IF(ATIVIDADES!D20>0,ATIVIDADES!D20,"") -> Ambiente | C18: =IF(B18="","",VLOOKUP(B18,ATIVIDADES!$D$17:$F$23,2,FALSE)) -> 46388 | D18: =IF(B18="","",VLOOKUP(B18,ATIVIDADES!$D$18:$F$23,3,FALSE)) -> 25 | E18: =IF(OR(C18="",D18="",D18=0),"",EDATE(C18,D18)-1) -> 47149 | F18: =IF(OR($C18="",$D18=""),0,IF(AND($C18<=F$13,$E18>=F$13),1,0)) -> 0 | G18: =IF(OR($C18="",$D18=""),0,IF(AND($C18<=G$13,$E18>=G$13),F18+1,0)) -> 0 | H18: =IF(OR($C18="",$D18=""),0,IF(AND($C18<=H$13,$E18>=H$13),G18+1,0)) -> 0 | I18: =IF(OR($C18="",$D18=""),0,IF(AND($C18<=I$13,$E18>=I$13),H18+1,0)) -> 1 | J18: =IF(OR($C18="",$D18=""),0,IF(AND($C18<=J$13,$E18>=J$13),I18+1,0)) -> 2 | K18: =IF(OR($C18="",$D18=""),0,IF(AND($C18<=K$13,$E18>=K$13),J18+1,0)) -> 3 | L18: =IF(OR($C18="",$D18=""),0,IF(AND($C18<=L$13,$E18>=L$13),K18+1,0)) -> 4 | M18: =IF(OR($C18="",$D18=""),0,IF(AND($C18<=M$13,$E18>=M$13),L18+1,0)) -> 5 | N18: =IF(OR($C18="",$D18=""),0,IF(AND($C18<=N$13,$E18>=N$13),M18+1,0)) -> 6 | ... AO18: =IF(OR($C18="",$D18=""),0,IF(AND($C18<=AO$13,$E18>=AO$13),AN18+1,0)) -> 0
B19: =IF(ATIVIDADES!D21>0,ATIVIDADES!D21,"") -> Homeostasia e genética | C19: =IF(B19="","",VLOOKUP(B19,ATIVIDADES!$D$17:$F$23,2,FALSE)) -> 46388 | D19: =IF(B19="","",VLOOKUP(B19,ATIVIDADES!$D$18:$F$23,3,FALSE)) -> 25 | E19: =IF(OR(C19="",D19="",D19=0),"",EDATE(C19,D19)-1) -> 47149 | F19: =IF(OR($C19="",$D19=""),0,IF(AND($C19<=F$13,$E19>=F$13),1,0)) -> 0 | G19: =IF(OR($C19="",$D19=""),0,IF(AND($C19<=G$13,$E19>=G$13),F19+1,0)) -> 0 | H19: =IF(OR($C19="",$D19=""),0,IF(AND($C19<=H$13,$E19>=H$13),G19+1,0)) -> 0 | I19: =IF(OR($C19="",$D19=""),0,IF(AND($C19<=I$13,$E19>=I$13),H19+1,0)) -> 1 | J19: =IF(OR($C19="",$D19=""),0,IF(AND($C19<=J$13,$E19>=J$13),I19+1,0)) -> 2 | K19: =IF(OR($C19="",$D19=""),0,IF(AND($C19<=K$13,$E19>=K$13),J19+1,0)) -> 3 | L19: =IF(OR($C19="",$D19=""),0,IF(AND($C19<=L$13,$E19>=L$13),K19+1,0)) -> 4 | M19: =IF(OR($C19="",$D19=""),0,IF(AND($C19<=M$13,$E19>=M$13),L19+1,0)) -> 5 | N19: =IF(OR($C19="",$D19=""),0,IF(AND($C19<=N$13,$E19>=N$13),M19+1,0)) -> 6 | ... AO19: =IF(OR($C19="",$D19=""),0,IF(AND($C19<=AO$13,$E19>=AO$13),AN19+1,0)) -> 0
B20: =IF(ATIVIDADES!D22>0,ATIVIDADES!D22,"") -> Análise e interpretação dos dados | C20: =IF(B20="","",VLOOKUP(B20,ATIVIDADES!$D$17:$F$23,2,FALSE)) -> 46753 | D20: =IF(B20="","",VLOOKUP(B20,ATIVIDADES!$D$18:$F$23,3,FALSE)) -> 19 | E20: =IF(OR(C20="",D20="",D20=0),"",EDATE(C20,D20)-1) -> 47330 | F20: =IF(OR($C20="",$D20=""),0,IF(AND($C20<=F$13,$E20>=F$13),1,0)) -> 0 | G20: =IF(OR($C20="",$D20=""),0,IF(AND($C20<=G$13,$E20>=G$13),F20+1,0)) -> 0 | H20: =IF(OR($C20="",$D20=""),0,IF(AND($C20<=H$13,$E20>=H$13),G20+1,0)) -> 0 | I20: =IF(OR($C20="",$D20=""),0,IF(AND($C20<=I$13,$E20>=I$13),H20+1,0)) -> 0 | J20: =IF(OR($C20="",$D20=""),0,IF(AND($C20<=J$13,$E20>=J$13),I20+1,0)) -> 0 | K20: =IF(OR($C20="",$D20=""),0,IF(AND($C20<=K$13,$E20>=K$13),J20+1,0)) -> 0 | L20: =IF(OR($C20="",$D20=""),0,IF(AND($C20<=L$13,$E20>=L$13),K20+1,0)) -> 0 | M20: =IF(OR($C20="",$D20=""),0,IF(AND($C20<=M$13,$E20>=M$13),L20+1,0)) -> 0 | N20: =IF(OR($C20="",$D20=""),0,IF(AND($C20<=N$13,$E20>=N$13),M20+1,0)) -> 0 | ... AO20: =IF(OR($C20="",$D20=""),0,IF(AND($C20<=AO$13,$E20>=AO$13),AN20+1,0)) -> 0
B21: =IF(ATIVIDADES!D23>0,ATIVIDADES!D23,"") -> Partilha de conhecimento | C21: =IF(B21="","",VLOOKUP(B21,ATIVIDADES!$D$17:$F$23,2,FALSE)) -> 46753 | D21: =IF(B21="","",VLOOKUP(B21,ATIVIDADES!$D$18:$F$23,3,FALSE)) -> 21 | E21: =IF(OR(C21="",D21="",D21=0),"",EDATE(C21,D21)-1) -> 47391 | F21: =IF(OR($C21="",$D21=""),0,IF(AND($C21<=F$13,$E21>=F$13),1,0)) -> 0 | G21: =IF(OR($C21="",$D21=""),0,IF(AND($C21<=G$13,$E21>=G$13),F21+1,0)) -> 0 | H21: =IF(OR($C21="",$D21=""),0,IF(AND($C21<=H$13,$E21>=H$13),G21+1,0)) -> 0 | I21: =IF(OR($C21="",$D21=""),0,IF(AND($C21<=I$13,$E21>=I$13),H21+1,0)) -> 0 | J21: =IF(OR($C21="",$D21=""),0,IF(AND($C21<=J$13,$E21>=J$13),I21+1,0)) -> 0 | K21: =IF(OR($C21="",$D21=""),0,IF(AND($C21<=K$13,$E21>=K$13),J21+1,0)) -> 0 | L21: =IF(OR($C21="",$D21=""),0,IF(AND($C21<=L$13,$E21>=L$13),K21+1,0)) -> 0 | M21: =IF(OR($C21="",$D21=""),0,IF(AND($C21<=M$13,$E21>=M$13),L21+1,0)) -> 0 | N21: =IF(OR($C21="",$D21=""),0,IF(AND($C21<=N$13,$E21>=N$13),M21+1,0)) -> 0 | ... AO21: =IF(OR($C21="",$D21=""),0,IF(AND($C21<=AO$13,$E21>=AO$13),AN21+1,0)) -> 21
B22: =IF(ATIVIDADES!D24>0,ATIVIDADES!D24,"") | C22: =IF(B22="","",VLOOKUP(B22,ATIVIDADES!$D$17:$F$23,2,FALSE)) | D22: =IF(B22="","",VLOOKUP(B22,ATIVIDADES!$D$18:$F$23,3,FALSE)) | E22: =IF(OR(C22="",D22="",D22=0),"",EDATE(C22,D22)-1) | F22: =IF(OR($C22="",$D22=""),0,IF(AND($C22<=F$13,$E22>=F$13),1,0)) -> 0 | G22: =IF(OR($C22="",$D22=""),0,IF(AND($C22<=G$13,$E22>=G$13),F22+1,0)) -> 0 | H22: =IF(OR($C22="",$D22=""),0,IF(AND($C22<=H$13,$E22>=H$13),G22+1,0)) -> 0 | I22: =IF(OR($C22="",$D22=""),0,IF(AND($C22<=I$13,$E22>=I$13),H22+1,0)) -> 0 | J22: =IF(OR($C22="",$D22=""),0,IF(AND($C22<=J$13,$E22>=J$13),I22+1,0)) -> 0 | K22: =IF(OR($C22="",$D22=""),0,IF(AND($C22<=K$13,$E22>=K$13),J22+1,0)) -> 0 | L22: =IF(OR($C22="",$D22=""),0,IF(AND($C22<=L$13,$E22>=L$13),K22+1,0)) -> 0 | M22: =IF(OR($C22="",$D22=""),0,IF(AND($C22<=M$13,$E22>=M$13),L22+1,0)) -> 0 | N22: =IF(OR($C22="",$D22=""),0,IF(AND($C22<=N$13,$E22>=N$13),M22+1,0)) -> 0 | ... AO22: =IF(OR($C22="",$D22=""),0,IF(AND($C22<=AO$13,$E22>=AO$13),AN22+1,0)) -> 0
B23: =IF(ATIVIDADES!D25>0,ATIVIDADES!D25,"") | C23: =IF(B23="","",VLOOKUP(B23,ATIVIDADES!$D$17:$F$23,2,FALSE)) | D23: =IF(B23="","",VLOOKUP(B23,ATIVIDADES!$D$18:$F$23,3,FALSE)) | E23: =IF(OR(C23="",D23="",D23=0),"",EDATE(C23,D23)-1) | F23: =IF(OR($C23="",$D23=""),0,IF(AND($C23<=F$13,$E23>=F$13),1,0)) -> 0 | G23: =IF(OR($C23="",$D23=""),0,IF(AND($C23<=G$13,$E23>=G$13),F23+1,0)) -> 0 | H23: =IF(OR($C23="",$D23=""),0,IF(AND($C23<=H$13,$E23>=H$13),G23+1,0)) -> 0 | I23: =IF(OR($C23="",$D23=""),0,IF(AND($C23<=I$13,$E23>=I$13),H23+1,0)) -> 0 | J23: =IF(OR($C23="",$D23=""),0,IF(AND($C23<=J$13,$E23>=J$13),I23+1,0)) -> 0 | K23: =IF(OR($C23="",$D23=""),0,IF(AND($C23<=K$13,$E23>=K$13),J23+1,0)) -> 0 | L23: =IF(OR($C23="",$D23=""),0,IF(AND($C23<=L$13,$E23>=L$13),K23+1,0)) -> 0 | M23: =IF(OR($C23="",$D23=""),0,IF(AND($C23<=M$13,$E23>=M$13),L23+1,0)) -> 0 | N23: =IF(OR($C23="",$D23=""),0,IF(AND($C23<=N$13,$E23>=N$13),M23+1,0)) -> 0 | ... AO23: =IF(OR($C23="",$D23=""),0,IF(AND($C23<=AO$13,$E23>=AO$13),AN23+1,0)) -> 0
B24: =IF(ATIVIDADES!D26>0,ATIVIDADES!D26,"") | C24: =IF(B24="","",VLOOKUP(B24,ATIVIDADES!$D$17:$F$23,2,FALSE)) | D24: =IF(B24="","",VLOOKUP(B24,ATIVIDADES!$D$18:$F$23,3,FALSE)) | E24: =IF(OR(C24="",D24="",D24=0),"",EDATE(C24,D24)-1) | F24: =IF(OR($C24="",$D24=""),0,IF(AND($C24<=F$13,$E24>=F$13),1,0)) -> 0 | G24: =IF(OR($C24="",$D24=""),0,IF(AND($C24<=G$13,$E24>=G$13),F24+1,0)) -> 0 | H24: =IF(OR($C24="",$D24=""),0,IF(AND($C24<=H$13,$E24>=H$13),G24+1,0)) -> 0 | I24: =IF(OR($C24="",$D24=""),0,IF(AND($C24<=I$13,$E24>=I$13),H24+1,0)) -> 0 | J24: =IF(OR($C24="",$D24=""),0,IF(AND($C24<=J$13,$E24>=J$13),I24+1,0)) -> 0 | K24: =IF(OR($C24="",$D24=""),0,IF(AND($C24<=K$13,$E24>=K$13),J24+1,0)) -> 0 | L24: =IF(OR($C24="",$D24=""),0,IF(AND($C24<=L$13,$E24>=L$13),K24+1,0)) -> 0 | M24: =IF(OR($C24="",$D24=""),0,IF(AND($C24<=M$13,$E24>=M$13),L24+1,0)) -> 0 | N24: =IF(OR($C24="",$D24=""),0,IF(AND($C24<=N$13,$E24>=N$13),M24+1,0)) -> 0 | ... AO24: =IF(OR($C24="",$D24=""),0,IF(AND($C24<=AO$13,$E24>=AO$13),AN24+1,0)) -> 0
B25: =IF(ATIVIDADES!D27>0,ATIVIDADES!D27,"") | C25: =IF(B25="","",VLOOKUP(B25,ATIVIDADES!$D$17:$F$23,2,FALSE)) | D25: =IF(B25="","",VLOOKUP(B25,ATIVIDADES!$D$18:$F$23,3,FALSE)) | E25: =IF(OR(C25="",D25="",D25=0),"",EDATE(C25,D25)-1) | F25: =IF(OR($C25="",$D25=""),0,IF(AND($C25<=F$13,$E25>=F$13),1,0)) -> 0 | G25: =IF(OR($C25="",$D25=""),0,IF(AND($C25<=G$13,$E25>=G$13),F25+1,0)) -> 0 | H25: =IF(OR($C25="",$D25=""),0,IF(AND($C25<=H$13,$E25>=H$13),G25+1,0)) -> 0 | I25: =IF(OR($C25="",$D25=""),0,IF(AND($C25<=I$13,$E25>=I$13),H25+1,0)) -> 0 | J25: =IF(OR($C25="",$D25=""),0,IF(AND($C25<=J$13,$E25>=J$13),I25+1,0)) -> 0 | K25: =IF(OR($C25="",$D25=""),0,IF(AND($C25<=K$13,$E25>=K$13),J25+1,0)) -> 0 | L25: =IF(OR($C25="",$D25=""),0,IF(AND($C25<=L$13,$E25>=L$13),K25+1,0)) -> 0 | M25: =IF(OR($C25="",$D25=""),0,IF(AND($C25<=M$13,$E25>=M$13),L25+1,0)) -> 0 | N25: =IF(OR($C25="",$D25=""),0,IF(AND($C25<=N$13,$E25>=N$13),M25+1,0)) -> 0 | ... AO25: =IF(OR($C25="",$D25=""),0,IF(AND($C25<=AO$13,$E25>=AO$13),AN25+1,0)) -> 0
B26: =IF(ATIVIDADES!D28>0,ATIVIDADES!D28,"") | C26: =IF(B26="","",VLOOKUP(B26,ATIVIDADES!$D$17:$F$23,2,FALSE)) | D26: =IF(B26="","",VLOOKUP(B26,ATIVIDADES!$D$18:$F$23,3,FALSE)) | E26: =IF(OR(C26="",D26="",D26=0),"",EDATE(C26,D26)-1) | F26: =IF(OR($C26="",$D26=""),0,IF(AND($C26<=F$13,$E26>=F$13),1,0)) -> 0 | G26: =IF(OR($C26="",$D26=""),0,IF(AND($C26<=G$13,$E26>=G$13),F26+1,0)) -> 0 | H26: =IF(OR($C26="",$D26=""),0,IF(AND($C26<=H$13,$E26>=H$13),G26+1,0)) -> 0 | I26: =IF(OR($C26="",$D26=""),0,IF(AND($C26<=I$13,$E26>=I$13),H26+1,0)) -> 0 | J26: =IF(OR($C26="",$D26=""),0,IF(AND($C26<=J$13,$E26>=J$13),I26+1,0)) -> 0 | K26: =IF(OR($C26="",$D26=""),0,IF(AND($C26<=K$13,$E26>=K$13),J26+1,0)) -> 0 | L26: =IF(OR($C26="",$D26=""),0,IF(AND($C26<=L$13,$E26>=L$13),K26+1,0)) -> 0 | M26: =IF(OR($C26="",$D26=""),0,IF(AND($C26<=M$13,$E26>=M$13),L26+1,0)) -> 0 | N26: =IF(OR($C26="",$D26=""),0,IF(AND($C26<=N$13,$E26>=N$13),M26+1,0)) -> 0 | ... AO26: =IF(OR($C26="",$D26=""),0,IF(AND($C26<=AO$13,$E26>=AO$13),AN26+1,0)) -> 0

Sheet RH_BOLSEIROS
V2: SIM
V3: NÃO
B9: SACCT-Projetos de Investigação Científica e Desenvolvimento Tecnológico (IC&DT)
B12: Pessoal técnico do beneficiário
B14: O PROJETO IRÁ TER BOLSEIROS DE INVESTIGAÇÃO | E14: SIM | F14: (preenchimento Obrigatório)
B16: Bolsas de Investigação
B18: Tipo de bolsa | C18: Valor mensal | D18: 2026 | H18: 2027 | L18: 2028 | P18: 2029 | T18: 2030 | X18: Total | Y18: Person-Month_FTE
D19: N.º Meses | E19: Seg. Social Voluntário | F19: Valor | G19: 2024 Total | H19: N.º Meses | I19: Seg. Social Voluntário | J19: Valor | K19: 2025 Total | L19: N.º Meses | M19: Seg. Social Voluntário | N19: Valor | O19: 2026 Total | P19: N.º Meses | Q19: Seg. Social Voluntário | R19: Valor | S19: 2027 Total | T19: N.º Meses | U19: Seg. Social Voluntário | V19: Valor | W19: 2028 Total
B20: Bolsas de Investigação (BI)- estudantes de doutoramento | C20: =VLOOKUP(B20,'Valores bolsas e 57_2016'!$A$1:$B$9,2,FALSE) -> 1309.64 | D20: 0 | E20: =D20*$AC$25 -> 0 | F20: =+C20*D20 -> 0 | G20: =E20+F20 -> 0 | H20: 12 | I20: =H20*$AC$25 -> 1855.92 | J20: =H20*$C$20 -> 15715.68 | K20: =I20+J20 -> 17571.6 | L20: 12 | M20: =L20*$AC$25 -> 1855.92 | N20: =L20*$C$20 -> 15715.68 | O20: =M20+N20 -> 17571.6 | P20: 6 | Q20: =P20*$AC$25 -> 927.96 | R20: =P20*$C$20 -> 7857.84 | S20: =Q20+R20 -> 8785.8 | T20: 0 | U20: =T20*$AC$25 -> 0 | V20: =T20*$C$20 -> 0 | W20: =U20+V20 -> 0 | X20: =+G20+K20+O20+S20 -> 43929 | Y20: =+T20+P20+L20+H20+D20 -> 30
B21: Bolsas de Investigação (BI)- estudantes de doutoramento | C21: =VLOOKUP(B21,'Valores bolsas e 57_2016'!$A$1:$B$9,2,FALSE) -> 1309.64 | D21: 0 | E21: =D21*$AC$25 -> 0 | F21: =+C21*D21 -> 0 | G21: =E21+F21 -> 0 | H21: 12 | I21: =H21*$AC$25 -> 1855.92 | J21: =H21*$C$21 -> 15715.68 | K21: =I21+J21 -> 17571.6 | L21: 12 | M21: =L21*$AC$25 -> 1855.92 | N21: =L21*$C$21 -> 15715.68 | O21: =M21+N21 -> 17571.6 | P21: 6 | Q21: =P21*$AC$25 -> 927.96 | R21: =P21*$C$21 -> 7857.84 | S21: =Q21+R21 -> 8785.8 | T21: 0 | U21: =T21*$AC$25 -> 0 | V21: =T21*$C$21 -> 0 | W21: =U21+V21 -> 0 | X21: =+G21+K21+O21+S21 -> 43929 | Y21: =+T21+P21+L21+H21+D21 -> 30
B22: Bolsas de investigação pós doutoral | C22: =VLOOKUP(B22,'Valores bolsas e 57_2016'!$A$1:$B$9,2,FALSE) -> 1851 | D22: 0 | E22: =D22*$AC$25 -> 0 | F22: =+C22*D22 -> 0 | G22: =E22+F22 -> 0 | H22: 12 | I22: =H22*$AC$25 -> 1855.92 | J22: =H22*$C$22 -> 22212 | K22: =I22+J22 -> 24067.92 | L22: 12 | M22: =L22*$AC$25 -> 1855.92 | N22: =L22*$C$22 -> 22212 | O22: =M22+N22 -> 24067.92 | P22: 6 | Q22: =P22*$AC$25 -> 927.96 | R22: =P22*$C$22 -> 11106 | S22: =Q22+R22 -> 12033.96 | T22: 0 | U22: =T22*$AC$25 -> 0 | V22: =T22*$C$22 -> 0 | W22: =U22+V22 -> 0 | X22: =+G22+K22+O22+S22 -> 60169.8 | Y22: =+T22+P22+L22+H22+D22 -> 30
B23: Sem bolsa | C23: =VLOOKUP(B23,'Valores bolsas e 57_2016'!$A$1:$B$9,2,FALSE) -> 0 | D23: 0 | E23: =D23*$AC$25 -> 0 | F23: =+C23*D23 -> 0 | G23: =E23+F23 -> 0 | H23: 0 | I23: =H23*$AC$25 -> 0 | J23: =H23*$C$23 -> 0 | K23: =I23+J23 -> 0 | M23: =L23*$AC$25 -> 0 | N23: =L23*$C$23 -> 0 | O23: =M23+N23 -> 0 | P23: 0 | Q23: =P23*$AC$25 -> 0 | R23: =P23*$C$23 -> 0 | S23: =Q23+R23 -> 0 | T23: 0 | U23: =T23*$AC$25 -> 0 | V23: =T23*$C$23 -> 0 | W23: =U23+V23 -> 0 | X23: =+G23+K23+O23+S23 -> 0 | Y23: =+T23+P23+L23+H23+D23 -> 0
B24: Total | E24: =SUM(E20:E23) -> 0 | F24: =SUM(F20:F23) -> 0 | G24: =SUM(G20:G23) -> 0 | I24: =SUM(I20:I23) -> 5567.76 | J24: =SUM(J20:J23) -> 53643.36 | K24: =SUM(K20:K23) -> 59211.12 | M24: =SUM(M20:M23) -> 5567.76 | N24: =SUM(N20:N23) -> 53643.36 | O24: =SUM(O20:O23) -> 59211.12 | Q24: =SUM(Q20:Q23) -> 2783.88 | R24: =SUM(R20:R23) -> 26821.68 | S24: =SUM(S20:S23) -> 29605.56 | U24: =SUM(U20:U23) -> 0 | V24: =SUM(V20:V23) -> 0 | W24: =SUM(W20:W23) -> 0 | X24: =SUM(X20:X23) -> 148027.8 | Z24: Seguro Social Voluntário
Y25: =SUM(Y20:Y23) -> 90 | Z25: 2025 | AA25: 0 | AC25: 154.66
B26: Regulamento das Bolsas

Sheet RH_CONTRATOS
B9: SACCT-Projetos de Investigação Científica e Desenvolvimento Tecnológico (IC&DT) | V9: SIM
V10: NÃO
B12: Pessoal técnico do beneficiário
B14: O PROJETO IRÁ CONTRATAR INVESTIGADORES | E14: NÃO | F14: (preenchimento Obrigatório)
B16: Pessoal a contratar Emprego Científico (DL n.º 57/2016 de 29-08)
B18: Emprego Científico - Contratos de Trabalho | C18: Remuneração Bruta | D18: 2025 | J18: 2026 | P18: 2027 | V18: 2028 | AB18: TOTAL
D19: Meses | E19: RbM | F19: Segurança Social | G19: Subsidio férias e Natal | H19: Subsidio Alimentação | I19: Custo total 2024 | J19: Meses | K19: RbM | L19: Segurança Social | M19: Subsidio férias e Natal | N19: Subsidio Alimentação | O19: Custo total 2025 | P19: Meses | Q19: RbM | R19: Segurança Social | S19: Subsidio férias e Natal | T19: Subsidio Alimentação | U19: Custo total 2026 | V19: Meses | W19: RbM | X19: Segurança Social | Y19: Subsidio férias e Natal | Z19: Subsidio Alimentação | AA19: Custo total 2027 | AB19: Meses | AC19: Valor
B20: Sem Contrato | C20: =VLOOKUP(B20,'Valores bolsas e 57_2016'!$A$7:$B$12,2,FALSE) -> 0 | D20: 0 | E20: =+C20*D20 -> 0 | F20: =(+E20*$C$26)+(G20*$C$26) -> 0 | G20: =+((D20/12)*2)*C20 -> 0 | H20: =IF(D20=0,0, $C$27*(D20-1)*22) -> 0 | I20: =+E20+F20+G20+H20 -> 0 | J20: 0 | K20: =+C20*J20 -> 0 | L20: =(+K20*$C$26)+(M20*$C$26) -> 0 | M20: =+((J20/12)*2)*C20 -> 0 | N20: =IF(J20=0,0, $C$27*(J20-1)*22) -> 0 | O20: =+K20+L20+M20+N20 -> 0 | P20: 0 | Q20: =+C20*P20 -> 0 | R20: =(+Q20*$C$26)+(S20*$C$26) -> 0 | S20: =+((P20/12)*2)*C20 -> 0 | T20: =IF(P20=0,0, $C$27*(P20-1)*22) -> 0 | U20: =+Q20+R20+S20+T20 -> 0 | V20: 0 | W20: =+C20*V20 -> 0 | X20: =(+W20*$C$26)+(Y20*$C$26) -> 0 | Y20: =+((V20/12)*2)*C20 -> 0 | Z20: =IF(V20=0,0, $C$27*(V20-1)*22) -> 0 | AA20: =+W20+X20+Y20+Z20 -> 0 | AB20: =+V20+P20+J20+D20 -> 0 | AC20: =+AA20+U20+O20+I20 -> 0
B21: Sem Contrato | C21: =VLOOKUP(B21,'Valores bolsas e 57_2016'!$A$7:$B$12,2,FALSE) -> 0 | D21: 0 | E21: =+C21*D21 -> 0 | F21: =(+E21*$C$26)+(G21*$C$26) -> 0 | G21: =+((D21/12)*2)*C21 -> 0 | H21: =IF(D21=0,0, $C$27*(D21-1)*22) -> 0 | I21: =+E21+F21+G21+H21 -> 0 | J21: 0 | K21: =+C21*J21 -> 0 | L21: =(+K21*$C$26)+(M21*$C$26) -> 0 | M21: =+((J21/12)*2)*C21 -> 0 | N21: =IF(J21=0,0, $C$27*(J21-1)*22) -> 0 | O21: =+K21+L21+M21+N21 -> 0 | P21: 0 | Q21: =+C21*P21 -> 0 | R21: =(+Q21*$C$26)+(S21*$C$26) -> 0 | S21: =+((P21/12)*2)*C21 -> 0 | T21: =IF(P21=0,0, $C$27*(P21-1)*22) -> 0 | U21: =+Q21+R21+S21+T21 -> 0 | V21: 0 | W21: =+C21*V21 -> 0 | X21: =(+W21*$C$26)+(Y21*$C$26) -> 0 | Y21: =+((V21/12)*2)*C21 -> 0 | Z21: =IF(V21=0,0, $C$27*(V21-1)*22) -> 0 | AA21: =+W21+X21+Y21+Z21 -> 0 | AB21: =+V21+P21+J21+D21 -> 0 | AC21: =+AA21+U21+O21+I21 -> 0
B22: Sem Contrato | C22: =VLOOKUP(B22,'Valores bolsas e 57_2016'!$A$7:$B$12,2,FALSE) -> 0 | D22: 0 | E22: =+C22*D22 -> 0 | F22: =(+E22*$C$26)+(G22*$C$26) -> 0 | G22: =+((D22/12)*2)*C22 -> 0 | H22: =IF(D22=0,0, $C$27*(D22-1)*22) -> 0 | I22: =+E22+F22+G22+H22 -> 0 | J22: 0 | K22: =+C22*J22 -> 0 | L22: =(+K22*$C$26)+(M22*$C$26) -> 0 | M22: =+((J22/12)*2)*C22 -> 0 | N22: =IF(J22=0,0, $C$27*(J22-1)*22) -> 0 | O22: =+K22+L22+M22+N22 -> 0 | P22: 0 | Q22: =+C22*P22 -> 0 | R22: =(+Q22*$C$26)+(S22*$C$26) -> 0 | S22: =+((P22/12)*2)*C22 -> 0 | T22: =IF(P22=0,0, $C$27*(P22-1)*22) -> 0 | U22: =+Q22+R22+S22+T22 -> 0 | V22: 0 | W22: =+C22*V22 -> 0 | X22: =(+W22*$C$26)+(Y22*$C$26) -> 0 | Y22: =+((V22/12)*2)*C22 -> 0 | Z22: =IF(V22=0,0, $C$27*(V22-1)*22) -> 0 | AA22: =+W22+X22+Y22+Z22 -> 0 | AB22: =+V22+P22+J22+D22 -> 0 | AC22: =+AA22+U22+O22+I22 -> 0
B23: Sem Contrato | C23: =VLOOKUP(B23,'Valores bolsas e 57_2016'!$A$7:$B$12,2,FALSE) -> 0 | D23: 0 | E23: =+C23*D23 -> 0 | F23: =(+E23*$C$26)+(G23*$C$26) -> 0 | G23: =+((D23/12)*2)*C23 -> 0 | H23: =IF(D23=0,0, $C$27*(D23-1)*22) -> 0 | I23: =+E23+F23+G23+H23 -> 0 | J23: 0 | K23: =+C23*J23 -> 0 | L23: =(+K23*$C$26)+(M23*$C$26) -> 0 | M23: =+((J23/12)*2)*C23 -> 0 | N23: =IF(J23=0,0, $C$27*(J23-1)*22) -> 0 | O23: =+K23+L23+M23+N23 -> 0 | P23: 0 | Q23: =+C23*P23 -> 0 | R23: =(+Q23*$C$26)+(S23*$C$26) -> 0 | S23: =+((P23/12)*2)*C23 -> 0 | T23: =IF(P23=0,0, $C$27*(P23-1)*22) -> 0 | U23: =+Q23+R23+S23+T23 -> 0 | V23: 0 | W23: =+C23*V23 -> 0 | X23: =(+W23*$C$26)+(Y23*$C$26) -> 0 | Y23: =+((V23/12)*2)*C23 -> 0 | Z23: =IF(V23=0,0, $C$27*(V23-1)*22) -> 0 | AA23: =+W23+X23+Y23+Z23 -> 0 | AB23: =+V23+P23+J23+D23 -> 0 | AC23: =+AA23+U23+O23+I23 -> 0
B24: Total | I24: =SUM(I20:I23) -> 0 | O24: =SUM(O20:O23) -> 0 | U24: =SUM(U20:U23) -> 0 | AA24: =SUM(AA20:AA23) -> 0 | AB24: =SUM(AB20:AB23) -> 0 | AC24: =SUM(AC20:AC23) -> 0
B26: Taxa de segurança Social | C26: 0.2375 | D26: =C20*C26 -> 0 | AB26: Custo total 36 Meses
B27: Subsídio refeição (dia) | C27: 6 | D27: =C27*22 -> 132

Sheet RH_EQUIPA
W3: SIM
W4: NÃO
B9: SACCT-Projetos de Investigação Científica e Desenvolvimento Tecnológico (IC&DT)
B12: Pessoal técnico do beneficiário da Universidade do Algarve
B14: Atenção: Nos termos do aviso do concurso o número máximo de FTEs/ ETIs imputável por ano, equivalente a uma pessoa dedicada ao projeto por 12 meses em full time (100%), é 11 (= 11 meses de trabalho). Exemplos: a) Um contrato em full time por 24 meses 100% dedicado ao projeto corresponde a uma afetação de 22 FTEs/ ETIs (24 meses x 11 / 12 = 22 FTEs/ ETIs); b) Um contrato em full time por 15 meses 100% dedicado ao projeto corresponde a uma afetação de 13,75 FTEs/ ETIs (15 meses x 11 / 12 = 13,75 FTEs/ ETIs); c) Um contrato em full time por 6 meses 100% dedicado ao projeto corresponde a uma afetação de 5,5 FTEs/ ETIs (6 meses x 11 / 12 = 5,5 FTEs/ ETIs). Perfis/ modalidades de contrato que podem ser incluídos como nova contratação: a) Investigador Doutorado DL57/2016 (afetação fixa de 27,50 FTEs/ ETIs por contrato; = 30 meses de contrato); b) Bolsa de Iniciação à Investigação (BII); c) Bolsa de Investigação - Licenciado (BI_L); d) Bolsa de Investigação - Mestre (BI_M); e) Bolsa de Investigação Pós-Doutoral (BIPD).
B16: N.º | C16: EQUIPA UALG | D16: Nova contratação? | E16: % afetação ao projeto | F16: N.º de FTEs/ ETIs
F17: =YEAR(RESUMO!E32) -> 2026 | G17: =F17+1 -> 2027 | H17: =G17+1 -> 2028 | I17: =H17+1 -> 2029 | J17: =I17+1 -> 2030 | K17: =J17+1 -> 2031 | L17: Total
F18: =IF(YEAR(RESUMO!E51)=F17,RESUMO!F51*0.916666666666667,"") -> 2.75 | G18: =+RESUMO!F52*11/12 -> 11 | H18: =+RESUMO!F53*11/12 -> 11 | I18: =IF(YEAR(RESUMO!E55)=I17,RESUMO!F55*11/12,"") -> 8.25 | J18: =IF(YEAR(RESUMO!F55)=J17,RESUMO!G55*11/12,"") | K18: =IF(YEAR(RESUMO!G55)=K17,RESUMO!H55*11/12,"")
B19: =IF(C19>0,1,"") -> 1 | C19: Ana Cristina Coelho | D19: NÃO | E19: 0.35 | F19: =IF($F$18="",0,$E19*$F$18) -> 0.9625 | G19: =+$E19*$G$18 -> 3.85 | H19: =+$E19*$H$18 -> 3.85 | I19: =IF($I$18="",0,$E19*$I$18) -> 2.8875 | L19: =SUM(F19:K19) -> 11.55
B20: =IF(C20>0,B19+1,"") -> 2 | C20: Ana Maria Costa | D20: NÃO | E20: 0.15 | F20: =IF($F$18="",0,$E20*$F$18) -> 0.4125 | G20: =+$E20*$G$18 -> 1.65 | H20: =+$E20*$H$18 -> 1.65 | I20: =IF($I$18="",0,$E20*$I$18) -> 1.2375 | L20: =SUM(F20:K20) -> 4.95
B21: =IF(C21>0,B20+1,"") -> 3 | C21: Cristina Veiga-Pires | D21: NÃO | E21: 0.15 | F21: =IF($F$18="",0,$E21*$F$18) -> 0.4125 | G21: =+$E21*$G$18 -> 1.65 | H21: =+$E21*$H$18 -> 1.65 | I21: =IF($I$18="",0,$E21*$I$18) -> 1.2375 | L21: =SUM(F21:K21) -> 4.95
B22: =IF(C22>0,B21+1,"") -> 4 | C22: Jorge Semião | D22: NÃO | E22: 0.05 | F22: =IF($F$18="",0,$E22*$F$18) -> 0.1375 | G22: =+$E22*$G$18 -> 0.55 | H22: =+$E22*$H$18 -> 0.55 | I22: =IF($I$18="",0,$E22*$I$18) -> 0.4125 | L22: =SUM(F22:K22) -> 1.65
B23: =IF(C23>0,B22+1,"") -> 5 | C23: Jânio Monteiro | D23: NÃO | E23: 0.05 | F23: =IF($F$18="",0,$E23*$F$18) -> 0.1375 | G23: =+$E23*$G$18 -> 0.55 | H23: =+$E23*$H$18 -> 0.55 | I23: =IF($I$18="",0,$E23*$I$18) -> 0.4125 | L23: =SUM(F23:K23) -> 1.65
B24: =IF(C24>0,B23+1,"") -> 6 | C24: Pedro cardoso | D24: NÃO | E24: 0.05 | F24: =IF($F$18="",0,$E24*$F$18) -> 0.1375 | G24: =+$E24*$G$18 -> 0.55 | H24: =+$E24*$H$18 -> 0.55 | I24: =IF($I$18="",0,$E24*$I$18) -> 0.4125 | L24: =SUM(F24:K24) -> 1.65
B25: =IF(C25>0,B24+1,"") -> 7 | C25: Roberto Lam | D25: NÃO | E25: 0.05 | F25: =IF($F$18="",0,$E25*$F$18) -> 0.1375 | G25: =+$E25*$G$18 -> 0.55 | H25: =+$E25*$H$18 -> 0.55 | I25: =IF($I$18="",0,$E25*$I$18) -> 0.4125 | L25: =SUM(F25:K25) -> 1.65
B26: =IF(C26>0,B25+1,"") -> 8 | C26: Cristiano Cabrita | D26: NÃO | E26: 0.05 | F26: =IF($F$18="",0,$E26*$F$18) -> 0.1375 | G26: =+$E26*$G$18 -> 0.55 | H26: =+$E26*$H$18 -> 0.55 | I26: =IF($I$18="",0,$E26*$I$18) -> 0.4125 | L26: =SUM(F26:K26) -> 1.65
B27: =IF(C27>0,B26+1,"") -> 9 | C27: Jaime Martins | D27: NÃO | E27: 0.05 | F27: =IF($F$18="",0,$E27*$F$18) -> 0.1375 | G27: =+$E27*$G$18 -> 0.55 | H27: =+$E27*$H$18 -> 0.55 | I27: =IF($I$18="",0,$E27*$I$18) -> 0.4125 | L27: =SUM(F27:K27) -> 1.65
B28: =IF(C28>0,B27+1,"") -> 10 | C28: Paulo Silva | D28: NÃO | E28: 0.15 | F28: =IF($F$18="",0,$E28*$F$18) -> 0.4125 | G28: =+$E28*$G$18 -> 1.65 | H28: =+$E28*$H$18 -> 1.65 | I28: =IF($I$18="",0,$E28*$I$18) -> 1.2375 | L28: =SUM(F28:K28) -> 4.95
B29: =IF(C29>0,B28+1,"") -> 11 | C29: João Rodrigues | D29: NÃO | E29: 0.02 | F29: =IF($F$18="",0,$E29*$F$18) -> 0.055 | G29: =+$E29*$G$18 -> 0.22 | H29: =+$E29*$H$18 -> 0.22 | I29: =IF($I$18="",0,$E29*$I$18) -> 0.165 | L29: =SUM(F29:K29) -> 0.66
B30: =IF(C30>0,B29+1,"") -> 12 | C30: Joana Lessa | D30: NÃO | E30: 0.2 | F30: =IF($F$18="",0,$E30*$F$18) -> 0.55 | G30: =+$E30*$G$18 -> 2.2 | H30: =+$E30*$H$18 -> 2.2 | I30: =IF($I$18="",0,$E30*$I$18) -> 1.65 | L30: =SUM(F30:K30) -> 6.6
B31: 13 | C31: José Moreira | D31: NÃO | E31: 0.15 | F31: =IF($F$18="",0,$E31*$F$18) -> 0.4125 | G31: =+$E31*$G$18 -> 1.65 | H31: =+$E31*$H$18 -> 1.65 | I31: =IF($I$18="",0,$E31*$I$18) -> 1.2375 | L31: =SUM(F31:K31) -> 4.95
B32: 14 | C32: Joel Guerreiro | D32: NÃO | E32: 0.1 | F32: =IF($F$18="",0,$E32*$F$18) -> 0.275 | G32: =+$E32*$G$18 -> 1.1 | H32: =+$E32*$H$18 -> 1.1 | I32: =IF($I$18="",0,$E32*$I$18) -> 0.825 | L32: =SUM(F32:K32) -> 3.3
C33: BOLSEIROS DE INVESTIGAÇÃO
B34: B1 | C34: =IF(RH_BOLSEIROS!$E$14="SIM",RH_BOLSEIROS!B20,"") -> Bolsas de Investigação (BI)- estudantes de doutoramento | D34: SIM | E34: =IF(C34="",0%,100%) -> 1 | F34: =11*RH_BOLSEIROS!D20/12 -> 0 | G34: =+RH_BOLSEIROS!H20*0.916666666666667 -> 11 | H34: =+RH_BOLSEIROS!L20*0.916666666666667 -> 11 | I34: =+RH_BOLSEIROS!P20*0.916666666666667 -> 5.5 | J34: =+RH_BOLSEIROS!T20*11/12 -> 0 | L34: =SUM(F34:K34) -> 27.5
B35: B2 | C35: =IF(RH_BOLSEIROS!$E$14="SIM",RH_BOLSEIROS!B21,"") -> Bolsas de Investigação (BI)- estudantes de doutoramento | D35: SIM | E35: =IF(C35="",0%,100%) -> 1 | F35: =11*RH_BOLSEIROS!D21/12 -> 0 | G35: =+RH_BOLSEIROS!H21*0.916666666666667 -> 11 | H35: =+RH_BOLSEIROS!L21*0.916666666666667 -> 11 | I35: =+RH_BOLSEIROS!P21*0.916666666666667 -> 5.5 | J35: =+RH_BOLSEIROS!T21*11/12 -> 0 | L35: =SUM(F35:K35) -> 27.5
B36: B3 | C36: =IF(RH_BOLSEIROS!$E$14="SIM",RH_BOLSEIROS!B22,"") -> Bolsas de investigação pós doutoral | D36: SIM | E36: =IF(C36="",0%,100%) -> 1 | F36: =11*RH_BOLSEIROS!D22/12 -> 0 | G36: =+RH_BOLSEIROS!H22*0.916666666666667 -> 11 | H36: =+RH_BOLSEIROS!L22*0.916666666666667 -> 11 | I36: =+RH_BOLSEIROS!P22*0.916666666666667 -> 5.5 | J36: =+RH_BOLSEIROS!T22*11/12 -> 0 | L36: =SUM(F36:K36) -> 27.5
B37: B4 | C37: =IF(RH_BOLSEIROS!$E$14="SIM",RH_BOLSEIROS!B23,"") -> Sem bolsa | D37: SIM | E37: 1 | F37: =11*RH_BOLSEIROS!D23/12 -> 0 | G37: =+RH_BOLSEIROS!H23*0.916666666666667 -> 0 | H37: =+RH_BOLSEIROS!L23*0.916666666666667 -> 0 | I37: =+RH_BOLSEIROS!P23*0.916666666666667 -> 0 | J37: =+RH_BOLSEIROS!T23*11/12 -> 0 | L37: =SUM(F37:K37) -> 0
C38: CONTRATOS DE INVESTIGAÇÃO
C39: =IF(RH_CONTRATOS!$E$14="SIM",RH_CONTRATOS!B20,"") | D39: SIM | E39: =IF(C39="",0%,100%) -> 0 | F39: =11*RH_CONTRATOS!D20/12 -> 0 | G39: =+RH_CONTRATOS!J20*0.916666666666667 -> 0 | H39: =+RH_CONTRATOS!P20*0.916666666666667 -> 0 | I39: =+RH_CONTRATOS!V20*0.916666666666667 -> 0 | L39: =SUM(F39:J39) -> 0
C40: =IF(RH_CONTRATOS!$E$14="SIM",RH_CONTRATOS!B21,"") | D40: SIM | E40: =IF(C40="",0%,100%) -> 0 | F40: =11*RH_CONTRATOS!D21/12 -> 0 | G40: =+RH_CONTRATOS!J21*0.916666666666667 -> 0 | H40: =+RH_CONTRATOS!P21*0.916666666666667 -> 0 | I40: =+RH_CONTRATOS!V21*0.916666666666667 -> 0 | L40: =SUM(F40:J40) -> 0

Sheet RH_ETI_Atividade
B11: DISTRIBUIÇÂO DA EQUIPA POR ATIVIDADES
D13: =YEAR(CRONOGRAMA!F13) -> 2026 | E13: =YEAR(CRONOGRAMA!G13) -> 2026 | F13: =YEAR(CRONOGRAMA!H13) -> 2026 | G13: =YEAR(CRONOGRAMA!I13) -> 2027 | H13: =YEAR(CRONOGRAMA!J13) -> 2027 | I13: =YEAR(CRONOGRAMA!K13) -> 2027 | J13: =YEAR(CRONOGRAMA!L13) -> 2027 | K13: =YEAR(CRONOGRAMA!M13) -> 2027 | ... AM13: =YEAR(CRONOGRAMA!AO13) -> 2029 | AN13: TOTAL | AO13: =YEAR(RESUMO!E32) -> 2026 | AP13: =AO13+1 -> 2027 | AQ13: =AP13+1 -> 2028 | AR13: =AQ13+1 -> 2029
B14: Membro da Equipa de Investigação | C14: ATIVIDADE | D14: =IF(RESUMO!$E$33>0,1,"") -> 1 | E14: =IF(RESUMO!$E$33>0,D14+1,"") -> 2 | F14: =IF(RESUMO!$E$33>0,E14+1,"") -> 3 | G14: =IF(RESUMO!$E$33>0,F14+1,"") -> 4 | H14: =IF(RESUMO!$E$33>0,G14+1,"") -> 5 | I14: =IF(RESUMO!$E$33>0,H14+1,"") -> 6 | J14: =IF(RESUMO!$E$33>0,I14+1,"") -> 7 | K14: =IF(RESUMO!$E$33>0,J14+1,"") -> 8 | L14: =IF(RESUMO!$E$33>0,K14+1,"") -> 9 | ... AM14: =IF(RESUMO!$E$33>0,AL14+1,"") -> 36 | AO14: 2024
B15: Ana Cristina Coelho | C15: A1 | D15: 0.65 | I15: 0.5 | L15: 0.5 | U15: 0.5 | AG15: 0.5 | AJ15: 0.5 | AM15: 0.5 | AN15: =SUM(D15:AM15) -> 3.65 | AO15: =SUMIF($D$13:$AM$13,$AO$13,D15:AM15) -> 0.65 | AP15: =SUMIF($D$13:$AM$13,$AP$13,D15:AM15) -> 1 | AQ15: =SUMIF($D$13:$AM$13,$AQ$13,D15:AM15) -> 0.5 | AR15: =SUMIF($D$13:$AM$13,$AR$13,D15:AM15) -> 1.5
B16: Ana Cristina Coelho | C16: A2 | G16: 0.5 | S16: 0.5 | Z16: 0.3 | AN16: =SUM(D16:AM16) -> 1.3 | AO16: =SUMIF($D$13:$AM$13,$AO$13,D16:AM16) -> 0 | AP16: =SUMIF($D$13:$AM$13,$AP$13,D16:AM16) -> 0.5 | AQ16: =SUMIF($D$13:$AM$13,$AQ$13,D16:AM16) -> 0.8 | AR16: =SUMIF($D$13:$AM$13,$AR$13,D16:AM16) -> 0
B17: Ana Cristina Coelho | C17: A3 | H17: 0.5 | T17: 0.5 | AA17: 0.5 | AN17: =SUM(D17:AM17) -> 1.5 | AO17: =SUMIF($D$13:$AM$13,$AO$13,D17:AM17) -> 0 | AP17: =SUMIF($D$13:$AM$13,$AP$13,D17:AM17) -> 0.5 | AQ17: =SUMIF($D$13:$AM$13,$AQ$13,D17:AM17) -> 1 | AR17: =SUMIF($D$13:$AM$13,$AR$13,D17:AM17) -> 0
B18: Ana Cristina Coelho | C18: A4 | I18: 0.5 | N18: 0.5 | W18: 0.5 | Y18: 0.5 | AN18: =SUM(D18:AM18) -> 2 | AO18: =SUMIF($D$13:$AM$13,$AO$13,D18:AM18) -> 0 | AP18: =SUMIF($D$13:$AM$13,$AP$13,D18:AM18) -> 1 | AQ18: =SUMIF($D$13:$AM$13,$AQ$13,D18:AM18) -> 1 | AR18: =SUMIF($D$13:$AM$13,$AR$13,D18:AM18) -> 0
B19: Ana Cristina Coelho | C19: A5 | Z19: 0.5 | AC19: 0.5 | AF19: 0.5 | AH19: 0.5 | AN19: =SUM(D19:AM19) -> 2 | AO19: =SUMIF($D$13:$AM$13,$AO$13,D19:AM19) -> 0 | AP19: =SUMIF($D$13:$AM$13,$AP$13,D19:AM19) -> 0 | AQ19: =SUMIF($D$13:$AM$13,$AQ$13,D19:AM19) -> 1 | AR19: =SUMIF($D$13:$AM$13,$AR$13,D19:AM19) -> 1
B20: Ana Cristina Coelho | C20: A6 | X20: 0.5 | AK20: 0.6 | AN20: =SUM(D20:AM20) -> 1.1 | AO20: =SUMIF($D$13:$AM$13,$AO$13,D20:AM20) -> 0 | AP20: =SUMIF($D$13:$AM$13,$AP$13,D20:AM20) -> 0 | AQ20: =SUMIF($D$13:$AM$13,$AQ$13,D20:AM20) -> 0.5 | AR20: =SUMIF($D$13:$AM$13,$AR$13,D20:AM20) -> 0.6
B21: Ana Maria Costa | C21: A1 | E21: 0.5 | AF21: 0.5 | AN21: =SUM(D21:AM21) -> 1 | AO21: =SUMIF($D$13:$AM$13,$AO$13,D21:AM21) -> 0.5 | AP21: =SUMIF($D$13:$AM$13,$AP$13,D21:AM21) -> 0 | AQ21: =SUMIF($D$13:$AM$13,$AQ$13,D21:AM21) -> 0 | AR21: =SUMIF($D$13:$AM$13,$AR$13,D21:AM21) -> 0.5
B22: Ana Maria Costa | C22: A4 | G22: 0.5 | Q22: 0.5 | S22: 0.5 | AE22: 0.5 | AN22: =SUM(D22:AM22) -> 2 | AO22: =SUMIF($D$13:$AM$13,$AO$13,D22:AM22) -> 0 | AP22: =SUMIF($D$13:$AM$13,$AP$13,D22:AM22) -> 1 | AQ22: =SUMIF($D$13:$AM$13,$AQ$13,D22:AM22) -> 0.5 | AR22: =SUMIF($D$13:$AM$13,$AR$13,D22:AM22) -> 0.5
B23: Ana Maria Costa | C23: A5 | X23: 0.5 | AG23: 0.5 | AN23: =SUM(D23:AM23) -> 1 | AO23: =SUMIF($D$13:$AM$13,$AO$13,D23:AM23) -> 0 | AP23: =SUMIF($D$13:$AM$13,$AP$13,D23:AM23) -> 0 | AQ23: =SUMIF($D$13:$AM$13,$AQ$13,D23:AM23) -> 0.5 | AR23: =SUMIF($D$13:$AM$13,$AR$13,D23:AM23) -> 0.5
B24: Ana Maria Costa | C24: A6 | V24: 0.5 | AK24: 0.45 | AN24: =SUM(D24:AM24) -> 0.95 | AO24: =SUMIF($D$13:$AM$13,$AO$13,D24:AM24) -> 0 | AP24: =SUMIF($D$13:$AM$13,$AP$13,D24:AM24) -> 0 | AQ24: =SUMIF($D$13:$AM$13,$AQ$13,D24:AM24) -> 0.5 | AR24: =SUMIF($D$13:$AM$13,$AR$13,D24:AM24) -> 0.45
B25: Cristina Veiga-Pires | C25: A1 | F25: 0.5 | W25: 0.5 | AN25: =SUM(D25:AM25) -> 1 | AO25: =SUMIF($D$13:$AM$13,$AO$13,D25:AM25) -> 0.5 | AP25: =SUMIF($D$13:$AM$13,$AP$13,D25:AM25) -> 0 | AQ25: =SUMIF($D$13:$AM$13,$AQ$13,D25:AM25) -> 0.5 | AR25: =SUMIF($D$13:$AM$13,$AR$13,D25:AM25) -> 0
B26: Cristina Veiga-Pires | C26: A3 | G26: 0.5 | Q26: 0.5 | S26: 0.5 | AE26: 0.5 | AN26: =SUM(D26:AM26) -> 2 | AO26: =SUMIF($D$13:$AM$13,$AO$13,D26:AM26) -> 0 | AP26: =SUMIF($D$13:$AM$13,$AP$13,D26:AM26) -> 1 | AQ26: =SUMIF($D$13:$AM$13,$AQ$13,D26:AM26) -> 0.5 | AR26: =SUMIF($D$13:$AM$13,$AR$13,D26:AM26) -> 0.5
B27: Cristina Veiga-Pires | C27: A5 | U27: 0.5 | AG27: 0.5 | AN27: =SUM(D27:AM27) -> 1 | AO27: =SUMIF($D$13:$AM$13,$AO$13,D27:AM27) -> 0 | AP27: =SUMIF($D$13:$AM$13,$AP$13,D27:AM27) -> 0 | AQ27: =SUMIF($D$13:$AM$13,$AQ$13,D27:AM27) -> 0.5 | AR27: =SUMIF($D$13:$AM$13,$AR$13,D27:AM27) -> 0.5
B28: Cristina Veiga-Pires | C28: A6 | V28: 0.5 | AM28: 0.45 | AN28: =SUM(D28:AM28) -> 0.95 | AO28: =SUMIF($D$13:$AM$13,$AO$13,D28:AM28) -> 0 | AP28: =SUMIF($D$13:$AM$13,$AP$13,D28:AM28) -> 0 | AQ28: =SUMIF($D$13:$AM$13,$AQ$13,D28:AM28) -> 0.5 | AR28: =SUMIF($D$13:$AM$13,$AR$13,D28:AM28) -> 0.45
B29: Joana Lessa | C29: A1 | K29: 0.6 | Y29: 0.5 | AN29: =SUM(D29:AM29) -> 1.1 | AO29: =SUMIF($D$13:$AM$13,$AO$13,D29:AM29) -> 0 | AP29: =SUMIF($D$13:$AM$13,$AP$13,D29:AM29) -> 0.6 | AQ29: =SUMIF($D$13:$AM$13,$AQ$13,D29:AM29) -> 0.5 | AR29: =SUMIF($D$13:$AM$13,$AR$13,D29:AM29) -> 0
B30: Joana Lessa | C30: A6 | T30: 1 | W30: 1 | AA30: 0.5 | AC30: 0.5 | AF30: 0.5 | AI30: 1 | AK30: 0.5 | AM30: 0.5 | AN30: =SUM(D30:AM30) -> 5.5 | AO30: =SUMIF($D$13:$AM$13,$AO$13,D30:AM30) -> 0 | AP30: =SUMIF($D$13:$AM$13,$AP$13,D30:AM30) -> 0 | AQ30: =SUMIF($D$13:$AM$13,$AQ$13,D30:AM30) -> 3 | AR30: =SUMIF($D$13:$AM$13,$AR$13,D30:AM30) -> 2.5
B31: Jorge Semião | C31: A2 | H31: 0.5 | T31: 0.5 | AN31: =SUM(D31:AM31) -> 1 | AO31: =SUMIF($D$13:$AM$13,$AO$13,D31:AM31) -> 0 | AP31: =SUMIF($D$13:$AM$13,$AP$13,D31:AM31) -> 0.5 | AQ31: =SUMIF($D$13:$AM$13,$AQ$13,D31:AM31) -> 0.5 | AR31: =SUMIF($D$13:$AM$13,$AR$13,D31:AM31) -> 0
B32: Jorge Semião | C32: A5 | AA32: 0.35 | AE32: 0.3 | AN32: =SUM(D32:AM32) -> 0.65 | AO32: =SUMIF($D$13:$AM$13,$AO$13,D32:AM32) -> 0 | AP32: =SUMIF($D$13:$AM$13,$AP$13,D32:AM32) -> 0 | AQ32: =SUMIF($D$13:$AM$13,$AQ$13,D32:AM32) -> 0.35 | AR32: =SUMIF($D$13:$AM$13,$AR$13,D32:AM32) -> 0.3
B33: Jânio Monteiro | C33: A3 | H33: 0.5 | T33: 0.5 | AN33: =SUM(D33:AM33) -> 1 | AO33: =SUMIF($D$13:$AM$13,$AO$13,D33:AM33) -> 0 | AP33: =SUMIF($D$13:$AM$13,$AP$13,D33:AM33) -> 0.5 | AQ33: =SUMIF($D$13:$AM$13,$AQ$13,D33:AM33) -> 0.5 | AR33: =SUMIF($D$13:$AM$13,$AR$13,D33:AM33) -> 0
B34: Jânio Monteiro | C34: A5 | AF34: 0.65 | AN34: =SUM(D34:AM34) -> 0.65 | AO34: =SUMIF($D$13:$AM$13,$AO$13,D34:AM34) -> 0 | AP34: =SUMIF($D$13:$AM$13,$AP$13,D34:AM34) -> 0 | AQ34: =SUMIF($D$13:$AM$13,$AQ$13,D34:AM34) -> 0 | AR34: =SUMIF($D$13:$AM$13,$AR$13,D34:AM34) -> 0.65
B35: Pedro cardoso | C35: A5 | X35: 0.65 | AB35: 0.5 | AI35: 0.5 | AN35: =SUM(D35:AM35) -> 1.65 | AO35: =SUMIF($D$13:$AM$13,$AO$13,D35:AM35) -> 0 | AP35: =SUMIF($D$13:$AM$13,$AP$13,D35:AM35) -> 0 | AQ35: =SUMIF($D$13:$AM$13,$AQ$13,D35:AM35) -> 1.15 | AR35: =SUMIF($D$13:$AM$13,$AR$13,D35:AM35) -> 0.5
B36: Roberto Lam | C36: A2 | J36: 0.5 | U36: 0.5 | AN36: =SUM(D36:AM36) -> 1 | AO36: =SUMIF($D$13:$AM$13,$AO$13,D36:AM36) -> 0 | AP36: =SUMIF($D$13:$AM$13,$AP$13,D36:AM36) -> 0.5 | AQ36: =SUMIF($D$13:$AM$13,$AQ$13,D36:AM36) -> 0.5 | AR36: =SUMIF($D$13:$AM$13,$AR$13,D36:AM36) -> 0
B37: Roberto Lam | C37: A5 | AC37: 0.65 | AN37: =SUM(D37:AM37) -> 0.65 | AO37: =SUMIF($D$13:$AM$13,$AO$13,D37:AM37) -> 0 | AP37: =SUMIF($D$13:$AM$13,$AP$13,D37:AM37) -> 0 | AQ37: =SUMIF($D$13:$AM$13,$AQ$13,D37:AM37) -> 0.65 | AR37: =SUMIF($D$13:$AM$13,$AR$13,D37:AM37) -> 0
B38: Cristiano Cabrita | C38: A2 | J38: 0.5 | U38: 0.5 | AN38: =SUM(D38:AM38) -> 1 | AO38: =SUMIF($D$13:$AM$13,$AO$13,D38:AM38) -> 0 | AP38: =SUMIF($D$13:$AM$13,$AP$13,D38:AM38) -> 0.5 | AQ38: =SUMIF($D$13:$AM$13,$AQ$13,D38:AM38) -> 0.5 | AR38: =SUMIF($D$13:$AM$13,$AR$13,D38:AM38) -> 0
B39: Cristiano Cabrita | C39: A5 | AC39: 0.65 | AN39: =SUM(D39:AM39) -> 0.65 | AO39: =SUMIF($D$13:$AM$13,$AO$13,D39:AM39) -> 0 | AP39: =SUMIF($D$13:$AM$13,$AP$13,D39:AM39) -> 0 | AQ39: =SUMIF($D$13:$AM$13,$AQ$13,D39:AM39) -> 0.65 | AR39: =SUMIF($D$13:$AM$13,$AR$13,D39:AM39) -> 0
B40: Jaime Martins | C40: A5 | T40: 0.5 | X40: 0.65 | AF40: 0.5 | AN40: =SUM(D40:AM40) -> 1.65 | AO40: =SUMIF($D$13:$AM$13,$AO$13,D40:AM40) -> 0 | AP40: =SUMIF($D$13:$AM$13,$AP$13,D40:AM40) -> 0 | AQ40: =SUMIF($D$13:$AM$13,$AQ$13,D40:AM40) -> 1.15 | AR40: =SUMIF($D$13:$AM$13,$AR$13,D40:AM40) -> 0.5
B41: Paulo Silva | C41: A2 | G41: 0.5 | M41: 0.5 | T41: 0.5 | AD41: 0.5 | AN41: =SUM(D41:AM41) -> 2 | AO41: =SUMIF($D$13:$AM$13,$AO$13,D41:AM41) -> 0 | AP41: =SUMIF($D$13:$AM$13,$AP$13,D41:AM41) -> 1 | AQ41: =SUMIF($D$13:$AM$13,$AQ$13,D41:AM41) -> 1 | AR41: =SUMIF($D$13:$AM$13,$AR$13,D41:AM41) -> 0
B42: Paulo Silva | C42: A3 | H42: 0.5 | O42: 0.5 | S42: 0.5 | AE42: 0.5 | AN42: =SUM(D42:AM42) -> 2 | AO42: =SUMIF($D$13:$AM$13,$AO$13,D42:AM42) -> 0 | AP42: =SUMIF($D$13:$AM$13,$AP$13,D42:AM42) -> 1 | AQ42: =SUMIF($D$13:$AM$13,$AQ$13,D42:AM42) -> 0.5 | AR42: =SUMIF($D$13:$AM$13,$AR$13,D42:AM42) -> 0.5
B43: Paulo Silva | C43: A5 | V43: 0.5 | AG43: 0.45 | AN43: =SUM(D43:AM43) -> 0.95 | AO43: =SUMIF($D$13:$AM$13,$AO$13,D43:AM43) -> 0 | AP43: =SUMIF($D$13:$AM$13,$AP$13,D43:AM43) -> 0 | AQ43: =SUMIF($D$13:$AM$13,$AQ$13,D43:AM43) -> 0.5 | AR43: =SUMIF($D$13:$AM$13,$AR$13,D43:AM43) -> 0.45
B44: José Moreira | C44: A4 | K44: 1 | V44: 0.5 | AN44: =SUM(D44:AM44) -> 1.5 | AO44: =SUMIF($D$13:$AM$13,$AO$13,D44:AM44) -> 0 | AP44: =SUMIF($D$13:$AM$13,$AP$13,D44:AM44) -> 1 | AQ44: =SUMIF($D$13:$AM$13,$AQ$13,D44:AM44) -> 0.5 | AR44: =SUMIF($D$13:$AM$13,$AR$13,D44:AM44) -> 0
B45: José Moreira | C45: A5 | T45: 1 | AE45: 0.5 | AN45: =SUM(D45:AM45) -> 1.5 | AO45: =SUMIF($D$13:$AM$13,$AO$13,D45:AM45) -> 0 | AP45: =SUMIF($D$13:$AM$13,$AP$13,D45:AM45) -> 0 | AQ45: =SUMIF($D$13:$AM$13,$AQ$13,D45:AM45) -> 1 | AR45: =SUMIF($D$13:$AM$13,$AR$13,D45:AM45) -> 0.5
B46: José Moreira | C46: A6 | X46: 1 | AJ46: 0.95 | AN46: =SUM(D46:AM46) -> 1.95 | AO46: =SUMIF($D$13:$AM$13,$AO$13,D46:AM46) -> 0 | AP46: =SUMIF($D$13:$AM$13,$AP$13,D46:AM46) -> 0 | AQ46: =SUMIF($D$13:$AM$13,$AQ$13,D46:AM46) -> 1 | AR46: =SUMIF($D$13:$AM$13,$AR$13,D46:AM46) -> 0.95
B47: João Rodrigues | C47: A5 | AB47: 0.3 | AG47: 0.36 | AN47: =SUM(D47:AM47) -> 0.66 | AO47: =SUMIF($D$13:$AM$13,$AO$13,D47:AM47) -> 0 | AP47: =SUMIF($D$13:$AM$13,$AP$13,D47:AM47) -> 0 | AQ47: =SUMIF($D$13:$AM$13,$AQ$13,D47:AM47) -> 0.3 | AR47: =SUMIF($D$13:$AM$13,$AR$13,D47:AM47) -> 0.36
B48: Joel Guerreiro | C48: A2 | J48: 1 | U48: 0.5 | AN48: =SUM(D48:AM48) -> 1.5 | AO48: =SUMIF($D$13:$AM$13,$AO$13,D48:AM48) -> 0 | AP48: =SUMIF($D$13:$AM$13,$AP$13,D48:AM48) -> 1 | AQ48: =SUMIF($D$13:$AM$13,$AQ$13,D48:AM48) -> 0.5 | AR48: =SUMIF($D$13:$AM$13,$AR$13,D48:AM48) -> 0
B49: Joel Guerreiro | C49: A5 | AC49: 1 | AG49: 0.8 | AN49: =SUM(D49:AM49) -> 1.8 | AO49: =SUMIF($D$13:$AM$13,$AO$13,D49:AM49) -> 0 | AP49: =SUMIF($D$13:$AM$13,$AP$13,D49:AM49) -> 0 | AQ49: =SUMIF($D$13:$AM$13,$AQ$13,D49:AM49) -> 1 | AR49: =SUMIF($D$13:$AM$13,$AR$13,D49:AM49) -> 0.8
B50: B1 | C50: A2 | G50: 1 | J50: 1 | M50: 1 | P50: 1 | S50: 1 | AB50: 1 | AN50: =SUM(D50:AM50) -> 6 | AO50: =SUMIF($D$13:$AM$13,$AO$13,D50:AM50) -> 0 | AP50: =SUMIF($D$13:$AM$13,$AP$13,D50:AM50) -> 4 | AQ50: =SUMIF($D$13:$AM$13,$AQ$13,D50:AM50) -> 2 | AR50: =SUMIF($D$13:$AM$13,$AR$13,D50:AM50) -> 0
B51: B1 | C51: A3 | H51: 1 | K51: 1 | L51: 1 | M51: 1 | Q51: 1 | T51: 1 | AA51: 1 | AC51: 1 | AN51: =SUM(D51:AM51) -> 8 | AO51: =SUMIF($D$13:$AM$13,$AO$13,D51:AM51) -> 0 | AP51: 5 | AQ51: 3 | AR51: =SUMIF($D$13:$AM$13,$AR$13,D51:AM51) -> 0
B52: B1 | C52: A4 | I52: 1 | L52: 1 | O52: 1 | AN52: =SUM(D52:AM52) -> 3 | AO52: =SUMIF($D$13:$AM$13,$AO$13,D52:AM52) -> 0 | AP52: 2 | AQ52: 1 | AR52: =SUMIF($D$13:$AM$13,$AR$13,D52:AM52) -> 0
B53: B1 | C53: A5 | V53: 0.5 | W53: 1 | X53: 0.5 | Y53: 0.5 | AE53: 1 | AG53: 1 | AH53: 1 | AN53: =SUM(D53:AM53) -> 5.5 | AO53: =SUMIF($D$13:$AM$13,$AO$13,D53:AM53) -> 0 | AP53: =SUMIF($D$13:$AM$13,$AP$13,D53:AM53) -> 0 | AQ53: =SUMIF($D$13:$AM$13,$AQ$13,D53:AM53) -> 2.5 | AR53: =SUMIF($D$13:$AM$13,$AR$13,D53:AM53) -> 3
B54: B1 | C54: A6 | V54: 0.5 | X54: 0.5 | Y54: 0.5 | AA54: 1 | AF54: 1 | AI54: 1 | AJ54: 0.5 | AN54: =SUM(D54:AM54) -> 5 | AO54: =SUMIF($D$13:$AM$13,$AO$13,D54:AM54) -> 0 | AP54: =SUMIF($D$13:$AM$13,$AP$13,D54:AM54) -> 0 | AQ54: =SUMIF($D$13:$AM$13,$AQ$13,D54:AM54) -> 2.5 | AR54: =SUMIF($D$13:$AM$13,$AR$13,D54:AM54) -> 2.5
B55: B2 | C55: A2 | G55: 1 | J55: 1 | P55: 1 | S55: 1 | W55: 1 | AA55: 1 | AN55: =SUM(D55:AM55) -> 6 | AO55: =SUMIF($D$13:$AM$13,$AO$13,D55:AM55) -> 0 | AP55: 3 | AQ55: =SUMIF($D$13:$AM$13,$AQ$13,D55:AM55) -> 3 | AR55: =SUMIF($D$13:$AM$13,$AR$13,D55:AM55) -> 0
B56: B2 | C56: A3 | H56: 1 | K56: 1 | Q56: 1 | T56: 1 | W56: 0.5 | AB56: 0.5 | AC56: 1 | AN56: =SUM(D56:AM56) -> 6 | AO56: =SUMIF($D$13:$AM$13,$AO$13,D56:AM56) -> 0 | AP56: 4 | AQ56: 2 | AR56: =SUMIF($D$13:$AM$13,$AR$13,D56:AM56) -> 0
B57: B2 | C57: A4 | I57: 1 | L57: 1 | M57: 1 | AN57: =SUM(D57:AM57) -> 3 | AO57: =SUMIF($D$13:$AM$13,$AO$13,D57:AM57) -> 0 | AP57: 2 | AQ57: 1 | AR57: =SUMIF($D$13:$AM$13,$AR$13,D57:AM57) -> 0
B58: B2 | C58: A5 | V58: 0.5 | W58: 0.5 | X58: 0.5 | Y58: 0.5 | AA58: 0.5 | AB58: 0.5 | AC58: 0.5 | AD58: 1 | AE58: 0.5 | AF58: 0.5 | AG58: 0.5 | AH58: 0.5 | AI58: 0.5 | AN58: =SUM(D58:AM58) -> 7 | AO58: =SUMIF($D$13:$AM$13,$AO$13,D58:AM58) -> 0 | AP58: =SUMIF($D$13:$AM$13,$AP$13,D58:AM58) -> 0 | AQ58: =SUMIF($D$13:$AM$13,$AQ$13,D58:AM58) -> 4.5 | AR58: =SUMIF($D$13:$AM$13,$AR$13,D58:AM58) -> 2.5
B59: B2 | C59: A6 | V59: 0.5 | W59: 0.5 | X59: 0.5 | Y59: 0.5 | AA59: 0.5 | AE59: 0.5 | AF59: 0.5 | AG59: 0.5 | AH59: 0.5 | AI59: 0.5 | AJ59: 0.5 | AN59: =SUM(D59:AM59) -> 5.5 | AO59: =SUMIF($D$13:$AM$13,$AO$13,D59:AM59) -> 0 | AP59: =SUMIF($D$13:$AM$13,$AP$13,D59:AM59) -> 0 | AQ59: =SUMIF($D$13:$AM$13,$AQ$13,D59:AM59) -> 2.5 | AR59: =SUMIF($D$13:$AM$13,$AR$13,D59:AM59) -> 3
B60: B3 | C60: A2 | G60: 1 | J60: 1 | P60: 1 | S60: 1 | V60: 1 | X60: 1 | Y60: 1 | AN60: =SUM(D60:AM60) -> 7 | AO60: =SUMIF($D$13:$AM$13,$AO$13,D60:AM60) -> 0 | AP60: =SUMIF($D$13:$AM$13,$AP$13,D60:AM60) -> 3 | AQ60: 4 | AR60: =SUMIF($D$13:$AM$13,$AR$13,D60:AM60) -> 0
B61: B3 | C61: A3 | H61: 1 | K61: 1 | Q61: 1 | T61: 1 | AA61: 1 | AB61: 1 | AN61: =SUM(D61:AM61) -> 6 | AO61: =SUMIF($D$13:$AM$13,$AO$13,D61:AM61) -> 0 | AP61: =SUMIF($D$13:$AM$13,$AP$13,D61:AM61) -> 3 | AQ61: 3 | AR61: =SUMIF($D$13:$AM$13,$AR$13,D61:AM61) -> 0
B62: B3 | C62: A4 | I62: 1 | L62: 1 | AN62: =SUM(D62:AM62) -> 2 | AO62: =SUMIF($D$13:$AM$13,$AO$13,D62:AM62) -> 0 | AP62: 1 | AQ62: 1 | AR62: =SUMIF($D$13:$AM$13,$AR$13,D62:AM62) -> 0
B63: B3 | C63: A5 | V63: 0.5 | W63: 0.5 | X63: 0.5 | Y63: 0.5 | AA63: 0.5 | AB63: 0.5 | AC63: 0.5 | AD63: 1 | AE63: 0.5 | AF63: 0.5 | AG63: 0.5 | AH63: 0.5 | AI63: 0.5 | AN63: =SUM(D63:AM63) -> 7 | AO63: =SUMIF($D$13:$AM$13,$AO$13,D63:AM63) -> 0 | AP63: =SUMIF($D$13:$AM$13,$AP$13,D63:AM63) -> 0 | AQ63: =SUMIF($D$13:$AM$13,$AQ$13,D63:AM63) -> 4.5 | AR63: =SUMIF($D$13:$AM$13,$AR$13,D63:AM63) -> 2.5
B64: B3 | C64: A6 | V64: 0.5 | W64: 0.5 | X64: 0.5 | Y64: 0.5 | AA64: 0.5 | AE64: 0.5 | AF64: 0.5 | AG64: 0.5 | AH64: 0.5 | AI64: 0.5 | AJ64: 0.5 | AN64: =SUM(D64:AM64) -> 5.5 | AO64: =SUMIF($D$13:$AM$13,$AO$13,D64:AM64) -> 0 | AP64: =SUMIF($D$13:$AM$13,$AP$13,D64:AM64) -> 0 | AQ64: =SUMIF($D$13:$AM$13,$AQ$13,D64:AM64) -> 2.5 | AR64: =SUMIF($D$13:$AM$13,$AR$13,D64:AM64) -> 3
AN65: =SUM(D65:AM65) -> 0 | AO65: =SUMIF($D$13:$AM$13,$AO$13,D65:AM65) -> 0 | AP65: =SUMIF($D$13:$AM$13,$AP$13,D65:AM65) -> 0 | AQ65: =SUMIF($D$13:$AM$13,$AQ$13,D65:AM65) -> 0 | AR65: =SUMIF($D$13:$AM$13,$AR$13,D65:AM65) -> 0
AN66: =SUM(D66:AM66) -> 0 | AO66: =SUMIF($D$13:$AM$13,$AO$13,D66:AM66) -> 0 | AP66: =SUMIF($D$13:$AM$13,$AP$13,D66:AM66) -> 0 | AQ66: =SUMIF($D$13:$AM$13,$AQ$13,D66:AM66) -> 0 | AR66: =SUMIF($D$13:$AM$13,$AR$13,D66:AM66) -> 0
AN67: =SUM(D67:AM67) -> 0 | AO67: =SUMIF($D$13:$AM$13,$AO$13,D67:AM67) -> 0 | AP67: =SUMIF($D$13:$AM$13,$AP$13,D67:AM67) -> 0 | AQ67: =SUMIF($D$13:$AM$13,$AQ$13,D67:AM67) -> 0 | AR67: =SUMIF($D$13:$AM$13,$AR$13,D67:AM67) -> 0
AN68: =SUM(D68:AM68) -> 0 | AO68: =SUMIF($D$13:$AM$13,$AO$13,D68:AM68) -> 0 | AP68: =SUMIF($D$13:$AM$13,$AP$13,D68:AM68) -> 0 | AQ68: =SUMIF($D$13:$AM$13,$AQ$13,D68:AM68) -> 0 | AR68: =SUMIF($D$13:$AM$13,$AR$13,D68:AM68) -> 0
AN69: =SUM(D69:AM69) -> 0 | AO69: =SUMIF($D$13:$AM$13,$AO$13,D69:AM69) -> 0 | AP69: =SUMIF($D$13:$AM$13,$AP$13,D69:AM69) -> 0 | AQ69: =SUMIF($D$13:$AM$13,$AQ$13,D69:AM69) -> 0 | AR69: =SUMIF($D$13:$AM$13,$AR$13,D69:AM69) -> 0
AN70: =SUM(D70:AM70) -> 0 | AO70: =SUMIF($D$13:$AM$13,$AO$13,D70:AM70) -> 0 | AP70: =SUMIF($D$13:$AM$13,$AP$13,D70:AM70) -> 0 | AQ70: =SUMIF($D$13:$AM$13,$AQ$13,D70:AM70) -> 0 | AR70: =SUMIF($D$13:$AM$13,$AR$13,D70:AM70) -> 0
AN71: =SUM(D71:AM71) -> 0 | AO71: =SUMIF($D$13:$AM$13,$AO$13,D71:AM71) -> 0 | AP71: =SUMIF($D$13:$AM$13,$AP$13,D71:AM71) -> 0 | AQ71: =SUMIF($D$13:$AM$13,$AQ$13,D71:AM71) -> 0 | AR71: =SUMIF($D$13:$AM$13,$AR$13,D71:AM71) -> 0
AN72: =SUM(D72:AM72) -> 0 | AO72: =SUMIF($D$13:$AM$13,$AO$13,D72:AM72) -> 0 | AP72: =SUMIF($D$13:$AM$13,$AP$13,D72:AM72) -> 0 | AQ72: =SUMIF($D$13:$AM$13,$AQ$13,D72:AM72) -> 0 | AR72: =SUMIF($D$13:$AM$13,$AR$13,D72:AM72) -> 0
AN73: =SUM(D73:AM73) -> 0 | AO73: =SUMIF($D$13:$AM$13,$AO$13,D73:AM73) -> 0 | AP73: =SUMIF($D$13:$AM$13,$AP$13,D73:AM73) -> 0 | AQ73: =SUMIF($D$13:$AM$13,$AQ$13,D73:AM73) -> 0 | AR73: =SUMIF($D$13:$AM$13,$AR$13,D73:AM73) -> 0
AN74: =SUM(D74:AM74) -> 0 | AO74: =SUMIF($D$13:$AM$13,$AO$13,D74:AM74) -> 0 | AP74: =SUMIF($D$13:$AM$13,$AP$13,D74:AM74) -> 0 | AQ74: =SUMIF($D$13:$AM$13,$AQ$13,D74:AM74) -> 0 | AR74: =SUMIF($D$13:$AM$13,$AR$13,D74:AM74) -> 0
AN75: =SUM(D75:AM75) -> 0 | AO75: =SUMIF($D$13:$AM$13,$AO$13,D75:AM75) -> 0 | AP75: =SUMIF($D$13:$AM$13,$AP$13,D75:AM75) -> 0 | AQ75: =SUMIF($D$13:$AM$13,$AQ$13,D75:AM75) -> 0 | AR75: =SUMIF($D$13:$AM$13,$AR$13,D75:AM75) -> 0
AN76: =SUM(D76:AM76) -> 0 | AO76: =SUMIF($D$13:$AM$13,$AO$13,D76:AM76) -> 0 | AP76: =SUMIF($D$13:$AM$13,$AP$13,D76:AM76) -> 0 | AQ76: =SUMIF($D$13:$AM$13,$AQ$13,D76:AM76) -> 0 | AR76: =SUMIF($D$13:$AM$13,$AR$13,D76:AM76) -> 0
... AN121: =SUM(D121:AM121) -> 0 | AO121: =SUMIF($D$13:$AM$13,$AO$13,D121:AM121) -> 0 | AP121: =SUMIF($D$13:$AM$13,$AP$13,D121:AM121) -> 0 | AQ121: =SUMIF($D$13:$AM$13,$AQ$13,D121:AM121) -> 0 | AR121: =SUMIF($D$13:$AM$13,$AR$13,D121:AM121) -> 0
B122: TOTAL | AN122: =SUM(AN15:AN121) -> 134.31 | AO122: =SUM(AO15:AO121) -> 1.65 | AP122: =SUM(AP15:AP121) -> 38.6 | AQ122: =SUM(AQ15:AQ121) -> 63.05 | AR122: =SUM(AR15:AR121) -> 31.01
D123: =SUM(D122:O122) -> 0 | P123: =SUM(P122:AA122) -> 0 | AB123: =SUM(AB122:AM122) -> 0

Sheet RH_ETI_QUADROS
B11: Identificação da Atividade por FTE | ORÇAMENTO UAlg | J11: (ESTES QUADROS SÃO DE PREENCHIMENTO AUTOMÁTICO)
B14: 94.0.0 OCS -Custo Unitário | D14: 4320
C16: FTE/ETI
B17: ATIVIDADE | C17: =RH_ETI_Atividade!AO13 -> 2026 | D17: =RH_ETI_Atividade!AP13 -> 2027 | E17: =RH_ETI_Atividade!AQ13 -> 2028 | F17: =RH_ETI_Atividade!AR13 -> 2029 | G17: TOTAL | H17: VALOR POR ATIVIDADE | I17: CLASSIFICAÇÃO
B18: =ATIVIDADES!C18 -> A1 | C18: =SUMIF(RH_ETI_Atividade!$C$15:$C$121,B18,RH_ETI_Atividade!$AO$15:$AO$121) -> 1.65 | D18: =SUMIF(RH_ETI_Atividade!$C$15:$C$121,B18,RH_ETI_Atividade!$AP$15:$AP$121) -> 1.6 | E18: =SUMIF(RH_ETI_Atividade!$C$15:$C$121,B18,RH_ETI_Atividade!$AQ$15:$AQ$121) -> 1.5 | F18: =SUMIF(RH_ETI_Atividade!$C$15:$C$121,B18,RH_ETI_Atividade!$AR$15:$AR$121) -> 2 | G18: =SUM(C18:F18) -> 6.75 | H18: =+G18*$D$14 -> 29160 | I18: =IF(ATIVIDADES!D18>0,VLOOKUP(B18,ATIVIDADES!C17:H28,6,FALSE),"") -> Gestão Projeto
B19: =ATIVIDADES!C19 -> A2 | C19: =SUMIF(RH_ETI_Atividade!$C$15:$C$121,B19,RH_ETI_Atividade!$AO$15:$AO$121) -> 0 | D19: =SUMIF(RH_ETI_Atividade!$C$15:$C$121,B19,RH_ETI_Atividade!$AP$15:$AP$121) -> 14 | E19: =SUMIF(RH_ETI_Atividade!$C$15:$C$121,B19,RH_ETI_Atividade!$AQ$15:$AQ$121) -> 12.8 | F19: =SUMIF(RH_ETI_Atividade!$C$15:$C$121,B19,RH_ETI_Atividade!$AR$15:$AR$121) -> 0 | G19: =SUM(C19:F19) -> 26.8 | H19: =+G19*$D$14 -> 115776 | I19: =IF(ATIVIDADES!D19>0,VLOOKUP(B19,ATIVIDADES!C18:H29,6,FALSE),"") -> Desenvolvimento Experimental
B20: =ATIVIDADES!C20 -> A3 | C20: =SUMIF(RH_ETI_Atividade!$C$15:$C$121,B20,RH_ETI_Atividade!$AO$15:$AO$121) -> 0 | D20: =SUMIF(RH_ETI_Atividade!$C$15:$C$121,B20,RH_ETI_Atividade!$AP$15:$AP$121) -> 15 | E20: =SUMIF(RH_ETI_Atividade!$C$15:$C$121,B20,RH_ETI_Atividade!$AQ$15:$AQ$121) -> 10.5 | F20: =SUMIF(RH_ETI_Atividade!$C$15:$C$121,B20,RH_ETI_Atividade!$AR$15:$AR$121) -> 1 | G20: =SUM(C20:F20) -> 26.5 | H20: =+G20*$D$14 -> 114480 | I20: =IF(ATIVIDADES!D20>0,VLOOKUP(B20,ATIVIDADES!C19:H30,6,FALSE),"") -> Desenvolvimento Experimental
B21: =ATIVIDADES!C21 -> A4 | C21: =SUMIF(RH_ETI_Atividade!$C$15:$C$121,B21,RH_ETI_Atividade!$AO$15:$AO$121) -> 0 | D21: =SUMIF(RH_ETI_Atividade!$C$15:$C$121,B21,RH_ETI_Atividade!$AP$15:$AP$121) -> 8 | E21: =SUMIF(RH_ETI_Atividade!$C$15:$C$121,B21,RH_ETI_Atividade!$AQ$15:$AQ$121) -> 5 | F21: =SUMIF(RH_ETI_Atividade!$C$15:$C$121,B21,RH_ETI_Atividade!$AR$15:$AR$121) -> 0.5 | G21: =SUM(C21:F21) -> 13.5 | H21: =+G21*$D$14 -> 58320 | I21: Fundamental
B22: =ATIVIDADES!C22 -> A5 | C22: =SUMIF(RH_ETI_Atividade!$C$15:$C$121,B22,RH_ETI_Atividade!$AO$15:$AO$121) -> 0 | D22: =SUMIF(RH_ETI_Atividade!$C$15:$C$121,B22,RH_ETI_Atividade!$AP$15:$AP$121) -> 0 | E22: =SUMIF(RH_ETI_Atividade!$C$15:$C$121,B22,RH_ETI_Atividade!$AQ$15:$AQ$121) -> 20.25 | F22: =SUMIF(RH_ETI_Atividade!$C$15:$C$121,B22,RH_ETI_Atividade!$AR$15:$AR$121) -> 14.06 | G22: =SUM(C22:F22) -> 34.31 | H22: =+G22*$D$14 -> 148219.2 | I22: =IF(ATIVIDADES!D22>0,VLOOKUP(B22,ATIVIDADES!C21:H32,6,FALSE),"") -> Desenvolvimento Experimental
B23: =ATIVIDADES!C23 -> A6 | C23: =SUMIF(RH_ETI_Atividade!$C$15:$C$121,B23,RH_ETI_Atividade!$AO$15:$AO$121) -> 0 | D23: =SUMIF(RH_ETI_Atividade!$C$15:$C$121,B23,RH_ETI_Atividade!$AP$15:$AP$121) -> 0 | E23: =SUMIF(RH_ETI_Atividade!$C$15:$C$121,B23,RH_ETI_Atividade!$AQ$15:$AQ$121) -> 13 | F23: =SUMIF(RH_ETI_Atividade!$C$15:$C$121,B23,RH_ETI_Atividade!$AR$15:$AR$121) -> 13.45 | G23: =SUM(C23:F23) -> 26.45 | H23: =+G23*$D$14 -> 114264 | I23: =IF(ATIVIDADES!D23>0,VLOOKUP(B23,ATIVIDADES!C22:H33,6,FALSE),"") -> Divulgação e Promoção
B24: =ATIVIDADES!C24 -> A7 | C24: =SUMIF(RH_ETI_Atividade!$C$15:$C$121,B24,RH_ETI_Atividade!$AO$15:$AO$121) -> 0 | D24: =SUMIF(RH_ETI_Atividade!$C$15:$C$121,B24,RH_ETI_Atividade!$AP$15:$AP$121) -> 0 | E24: =SUMIF(RH_ETI_Atividade!$C$15:$C$121,B24,RH_ETI_Atividade!$AQ$15:$AQ$121) -> 0 | F24: =SUMIF(RH_ETI_Atividade!$C$15:$C$121,B24,RH_ETI_Atividade!$AR$15:$AR$121) -> 0 | G24: =SUM(C24:F24) -> 0 | H24: =+G24*$D$14 -> 0 | I24: =IF(ATIVIDADES!D24>0,VLOOKUP(B24,ATIVIDADES!C23:H34,6,FALSE),"")
B25: =ATIVIDADES!C25 -> A8 | C25: =SUMIF(RH_ETI_Atividade!$C$15:$C$121,B25,RH_ETI_Atividade!$AO$15:$AO$121) -> 0 | D25: =SUMIF(RH_ETI_Atividade!$C$15:$C$121,B25,RH_ETI_Atividade!$AP$15:$AP$121) -> 0 | E25: =SUMIF(RH_ETI_Atividade!$C$15:$C$121,B25,RH_ETI_Atividade!$AQ$15:$AQ$121) -> 0 | F25: =SUMIF(RH_ETI_Atividade!$C$15:$C$121,B25,RH_ETI_Atividade!$AR$15:$AR$121) -> 0 | G25: =SUM(C25:F25) -> 0 | H25: =+G25*$D$14 -> 0 | I25: =IF(ATIVIDADES!D25>0,VLOOKUP(B25,ATIVIDADES!C24:H35,6,FALSE),"")
B26: =ATIVIDADES!C26 -> A9 | C26: =SUMIF(RH_ETI_Atividade!$C$15:$C$121,B26,RH_ETI_Atividade!$AO$15:$AO$121) -> 0 | D26: =SUMIF(RH_ETI_Atividade!$C$15:$C$121,B26,RH_ETI_Atividade!$AP$15:$AP$121) -> 0 | E26: =SUMIF(RH_ETI_Atividade!$C$15:$C$121,B26,RH_ETI_Atividade!$AQ$15:$AQ$121) -> 0 | F26: =SUMIF(RH_ETI_Atividade!$C$15:$C$121,B26,RH_ETI_Atividade!$AR$15:$AR$121) -> 0 | G26: =SUM(C26:F26) -> 0 | H26: =+G26*$D$14 -> 0 | I26: =IF(ATIVIDADES!D26>0,VLOOKUP(B26,ATIVIDADES!C25:H36,6,FALSE),"")
B27: =ATIVIDADES!C27 -> A10 | C27: =SUMIF(RH_ETI_Atividade!$C$15:$C$121,B27,RH_ETI_Atividade!$AO$15:$AO$121) -> 0 | D27: =SUMIF(RH_ETI_Atividade!$C$15:$C$121,B27,RH_ETI_Atividade!$AP$15:$AP$121) -> 0 | E27: =SUMIF(RH_ETI_Atividade!$C$15:$C$121,B27,RH_ETI_Atividade!$AQ$15:$AQ$121) -> 0 | F27: =SUMIF(RH_ETI_Atividade!$C$15:$C$121,B27,RH_ETI_Atividade!$AR$15:$AR$121) -> 0 | G27: =SUM(C27:F27) -> 0 | H27: =+G27*$D$14 -> 0 | I27: =IF(ATIVIDADES!D27>0,VLOOKUP(B27,ATIVIDADES!C26:H37,6,FALSE),"")
B28: =ATIVIDADES!C28 -> A11 | C28: =SUMIF(RH_ETI_Atividade!$C$15:$C$121,B28,RH_ETI_Atividade!$AO$15:$AO$121) -> 0 | D28: =SUMIF(RH_ETI_Atividade!$C$15:$C$121,B28,RH_ETI_Atividade!$AP$15:$AP$121) -> 0 | E28: =SUMIF(RH_ETI_Atividade!$C$15:$C$121,B28,RH_ETI_Atividade!$AQ$15:$AQ$121) -> 0 | F28: =SUMIF(RH_ETI_Atividade!$C$15:$C$121,B28,RH_ETI_Atividade!$AR$15:$AR$121) -> 0 | G28: =SUM(C28:F28) -> 0 | H28: =+G28*$D$14 -> 0 | I28: =IF(ATIVIDADES!D28>0,VLOOKUP(B28,ATIVIDADES!C27:H38,6,FALSE),"")
B29: TOTAL | C29: =SUM(C18:C28) -> 1.65 | D29: =SUM(D18:D28) -> 38.6 | E29: =SUM(E18:E28) -> 63.05 | F29: =SUM(F18:F28) -> 31.01 | G29: =SUM(G18:G28) -> 134.31 | H29: =SUM(H18:H28) -> 580219.2
B33: ATIVIDADE | C33: =RH_ETI_Atividade!AO13 -> 2026 | D33: =RH_ETI_Atividade!AP13 -> 2027 | E33: =RH_ETI_Atividade!AQ13 -> 2028 | F33: =RH_ETI_Atividade!AR13 -> 2029 | G33: TOTAL
B34: A1 | C34: =+$D$14*C18 -> 7128 | D34: =+$D$14*D18 -> 6912 | E34: =+E18*$D$14 -> 6480 | F34: =+F18*$D$14 -> 8640 | G34: =SUM(C34:F34) -> 29160
B35: A2 | C35: =+$D$14*C19 -> 0 | D35: =+$D$14*D19 -> 60480 | E35: =+E19*$D$14 -> 55296 | F35: =+F19*$D$14 -> 0 | G35: =SUM(C35:F35) -> 115776
B36: A3 | C36: =+$D$14*C20 -> 0 | D36: =+$D$14*D20 -> 64800 | E36: =+E20*$D$14 -> 45360 | F36: =+F20*$D$14 -> 4320 | G36: =SUM(C36:F36) -> 114480
B37: A4 | C37: =+$D$14*C21 -> 0 | D37: =+$D$14*D21 -> 34560 | E37: =+E21*$D$14 -> 21600 | F37: =+F21*$D$14 -> 2160 | G37: =SUM(C37:F37) -> 58320
B38: A5 | C38: =+$D$14*C22 -> 0 | D38: =+$D$14*D22 -> 0 | E38: =+E22*$D$14 -> 87480 | F38: =+F22*$D$14 -> 60739.2 | G38: =SUM(C38:F38) -> 148219.2
B39: A6 | C39: =+$D$14*C23 -> 0 | D39: =+$D$14*D23 -> 0 | E39: =+E23*$D$14 -> 56160 | F39: =+F23*$D$14 -> 58104 | G39: =SUM(C39:F39) -> 114264
B40: A7 | C40: =+$D$14*C24 -> 0 | D40: =+$D$14*D24 -> 0 | E40: =+E24*$D$14 -> 0 | F40: =+F24*$D$14 -> 0 | G40: =SUM(C40:F40) -> 0
B41: A8 | C41: =+$D$14*C25 -> 0 | D41: =+$D$14*D25 -> 0 | E41: =+E25*$D$14 -> 0 | F41: =+F25*$D$14 -> 0 | G41: =SUM(C41:F41) -> 0
B42: A9 | C42: =+$D$14*C26 -> 0 | D42: =+$D$14*D26 -> 0 | E42: =+E26*$D$14 -> 0 | F42: =+F26*$D$14 -> 0 | G42: =SUM(C42:F42) -> 0
B43: A10 | C43: =+$D$14*C27 -> 0 | D43: =+$D$14*D27 -> 0 | E43: =+E27*$D$14 -> 0 | F43: =+F27*$D$14 -> 0 | G43: =SUM(C43:F43) -> 0
B44: A11 | C44: =+$D$14*C28 -> 0 | D44: =+$D$14*D28 -> 0 | E44: =+E28*$D$14 -> 0 | F44: =+F28*$D$14 -> 0 | G44: =SUM(C44:F44) -> 0
B45: TOTAL | C45: =SUM(C34:C44) -> 7128 | D45: =SUM(D34:D44) -> 166752 | E45: =SUM(E34:E44) -> 272376 | F45: =SUM(F34:F44) -> 133963.2 | G45: =SUM(G34:G44) -> 580219.2
B47: Autofinanciamento | C47: =+C45*0.25 -> 1782 | D47: =+D45*0.25 -> 41688 | E47: =+E45*0.25 -> 68094 | F47: =+F45*0.25 -> 33490.8 | G47: =+G45*0.25 -> 145054.8
B49: Identificação da EQUIPA por FTE | ORÇAMENTO
C52: FTE/ETI
B53: EQUIPA | C53: A1 | D53: A2 | E53: A3 | F53: A4 | G53: A5 | H53: A6 | I53: A7 | J53: A8 | K53: A9 | L53: A10 | M53: A11 | N53: TOTAL | O53: FOLHA RH_EQUIPA
B54: ='Valores bolsas e 57_2016'!A42 -> Ana Cristina Coelho | C54: =SUMIFS(RH_ETI_Atividade!$AN$15:$AN$121,RH_ETI_Atividade!$B$15:$B$121,B54,RH_ETI_Atividade!$C$15:$C$121,$C$53) -> 3.65 | D54: =SUMIFS(RH_ETI_Atividade!$AN$15:$AN$121,RH_ETI_Atividade!$B$15:$B$121,B54,RH_ETI_Atividade!$C$15:$C$121,$D$53) -> 1.3 | E54: =SUMIFS(RH_ETI_Atividade!$AN$15:$AN$121,RH_ETI_Atividade!$B$15:$B$121,B54,RH_ETI_Atividade!$C$15:$C$121,$E$53) -> 1.5 | F54: =SUMIFS(RH_ETI_Atividade!$AN$15:$AN$121,RH_ETI_Atividade!$B$15:$B$121,$B54,RH_ETI_Atividade!$C$15:$C$121,$F$53) -> 2 | G54: =SUMIFS(RH_ETI_Atividade!$AN$15:$AN$121,RH_ETI_Atividade!$B$15:$B$121,$B54,RH_ETI_Atividade!$C$15:$C$121,$G$53) -> 2 | H54: =SUMIFS(RH_ETI_Atividade!$AN$15:$AN$121,RH_ETI_Atividade!$B$15:$B$121,$B54,RH_ETI_Atividade!$C$15:$C$121,$H$53) -> 1.1 | I54: =SUMIFS(RH_ETI_Atividade!$AN$15:$AN$121,RH_ETI_Atividade!$B$15:$B$121,$B54,RH_ETI_Atividade!$C$15:$C$121,$I$53) -> 0 | J54: =SUMIFS(RH_ETI_Atividade!$AN$15:$AN$121,RH_ETI_Atividade!$B$15:$B$121,$B54,RH_ETI_Atividade!$C$15:$C$121,$J$53) -> 0 | K54: =SUMIFS(RH_ETI_Atividade!$AN$15:$AN$121,RH_ETI_Atividade!$B$15:$B$121,$B54,RH_ETI_Atividade!$C$15:$C$121,$K$53) -> 0 | L54: =SUMIFS(RH_ETI_Atividade!$AN$15:$AN$121,RH_ETI_Atividade!$B$15:$B$121,$B54,RH_ETI_Atividade!$C$15:$C$121,$L$53) -> 0 | M54: =SUMIFS(RH_ETI_Atividade!$AN$15:$AN$121,RH_ETI_Atividade!$B$15:$B$121,$B54,RH_ETI_Atividade!$C$15:$C$121,$M$53) -> 0 | N54: =SUM(C54:M54) -> 11.55 | O54: =RH_EQUIPA!L19 -> 11.55
B55: ='Valores bolsas e 57_2016'!A43 -> Ana Maria Costa | C55: =SUMIFS(RH_ETI_Atividade!$AN$15:$AN$121,RH_ETI_Atividade!$B$15:$B$121,B55,RH_ETI_Atividade!$C$15:$C$121,$C$53) -> 1 | D55: =SUMIFS(RH_ETI_Atividade!$AN$15:$AN$121,RH_ETI_Atividade!$B$15:$B$121,B55,RH_ETI_Atividade!$C$15:$C$121,$D$53) -> 0 | E55: =SUMIFS(RH_ETI_Atividade!$AN$15:$AN$121,RH_ETI_Atividade!$B$15:$B$121,B55,RH_ETI_Atividade!$C$15:$C$121,$E$53) -> 0 | F55: =SUMIFS(RH_ETI_Atividade!$AN$15:$AN$121,RH_ETI_Atividade!$B$15:$B$121,$B55,RH_ETI_Atividade!$C$15:$C$121,$F$53) -> 2 | G55: =SUMIFS(RH_ETI_Atividade!$AN$15:$AN$121,RH_ETI_Atividade!$B$15:$B$121,$B55,RH_ETI_Atividade!$C$15:$C$121,$G$53) -> 1 | H55: =SUMIFS(RH_ETI_Atividade!$AN$15:$AN$121,RH_ETI_Atividade!$B$15:$B$121,$B55,RH_ETI_Atividade!$C$15:$C$121,$H$53) -> 0.95 | I55: =SUMIFS(RH_ETI_Atividade!$AN$15:$AN$121,RH_ETI_Atividade!$B$15:$B$121,$B55,RH_ETI_Atividade!$C$15:$C$121,$I$53) -> 0 | J55: =SUMIFS(RH_ETI_Atividade!$AN$15:$AN$121,RH_ETI_Atividade!$B$15:$B$121,$B55,RH_ETI_Atividade!$C$15:$C$121,$J$53) -> 0 | K55: =SUMIFS(RH_ETI_Atividade!$AN$15:$AN$121,RH_ETI_Atividade!$B$15:$B$121,$B55,RH_ETI_Atividade!$C$15:$C$121,$K$53) -> 0 | L55: =SUMIFS(RH_ETI_Atividade!$AN$15:$AN$121,RH_ETI_Atividade!$B$15:$B$121,$B55,RH_ETI_Atividade!$C$15:$C$121,$L$53) -> 0 | M55: =SUMIFS(RH_ETI_Atividade!$AN$15:$AN$121,RH_ETI_Atividade!$B$15:$B$121,$B55,RH_ETI_Atividade!$C$15:$C$121,$M$53) -> 0 | N55: =SUM(C55:M55) -> 4.95 | O55: =RH_EQUIPA!L20 -> 4.95
B56: ='Valores bolsas e 57_2016'!A44 -> Cristina Veiga-Pires | C56: =SUMIFS(RH_ETI_Atividade!$AN$15:$AN$121,RH_ETI_Atividade!$B$15:$B$121,B56,RH_ETI_Atividade!$C$15:$C$121,$C$53) -> 1 | D56: =SUMIFS(RH_ETI_Atividade!$AN$15:$AN$121,RH_ETI_Atividade!$B$15:$B$121,B56,RH_ETI_Atividade!$C$15:$C$121,$D$53) -> 0 | E56: =SUMIFS(RH_ETI_Atividade!$AN$15:$AN$121,RH_ETI_Atividade!$B$15:$B$121,B56,RH_ETI_Atividade!$C$15:$C$121,$E$53) -> 2 | F56: =SUMIFS(RH_ETI_Atividade!$AN$15:$AN$121,RH_ETI_Atividade!$B$15:$B$121,$B56,RH_ETI_Atividade!$C$15:$C$121,$F$53) -> 0 | G56: =SUMIFS(RH_ETI_Atividade!$AN$15:$AN$121,RH_ETI_Atividade!$B$15:$B$121,$B56,RH_ETI_Atividade!$C$15:$C$121,$G$53) -> 1 | H56: =SUMIFS(RH_ETI_Atividade!$AN$15:$AN$121,RH_ETI_Atividade!$B$15:$B$121,$B56,RH_ETI_Atividade!$C$15:$C$121,$H$53) -> 0.95 | I56: =SUMIFS(RH_ETI_Atividade!$AN$15:$AN$121,RH_ETI_Atividade!$B$15:$B$121,$B56,RH_ETI_Atividade!$C$15:$C$121,$I$53) -> 0 | J56: =SUMIFS(RH_ETI_Atividade!$AN$15:$AN$121,RH_ETI_Atividade!$B$15:$B$121,$B56,RH_ETI_Atividade!$C$15:$C$121,$J$53) -> 0 | K56: =SUMIFS(RH_ETI_Atividade!$AN$15:$AN$121,RH_ETI_Atividade!$B$15:$B$121,$B56,RH_ETI_Atividade!$C$15:$C$121,$K$53) -> 0 | L56: =SUMIFS(RH_ETI_Atividade!$AN$15:$AN$121,RH_ETI_Atividade!$B$15:$B$121,$B56,RH_ETI_Atividade!$C$15:$C$121,$L$53) -> 0 | M56: =SUMIFS(RH_ETI_Atividade!$AN$15:$AN$121,RH_ETI_Atividade!$B$15:$B$121,$B56,RH_ETI_Atividade!$C$15:$C$121,$M$53) -> 0 | N56: =SUM(C56:M56) -> 4.95 | O56: =RH_EQUIPA!L21 -> 4.95
B57: ='Valores bolsas e 57_2016'!A45 -> Jorge Semião | C57: =SUMIFS(RH_ETI_Atividade!$AN$15:$AN$121,RH_ETI_Atividade!$B$15:$B$121,B57,RH_ETI_Atividade!$C$15:$C$121,$C$53) -> 0 | D57: =SUMIFS(RH_ETI_Atividade!$AN$15:$AN$121,RH_ETI_Atividade!$B$15:$B$121,B57,RH_ETI_Atividade!$C$15:$C$121,$D$53) -> 1 | E57: =SUMIFS(RH_ETI_Atividade!$AN$15:$AN$121,RH_ETI_Atividade!$B$15:$B$121,B57,RH_ETI_Atividade!$C$15:$C$121,$E$53) -> 0 | F57: =SUMIFS(RH_ETI_Atividade!$AN$15:$AN$121,RH_ETI_Atividade!$B$15:$B$121,$B57,RH_ETI_Atividade!$C$15:$C$121,$F$53) -> 0 | G57: =SUMIFS(RH_ETI_Atividade!$AN$15:$AN$121,RH_ETI_Atividade!$B$15:$B$121,$B57,RH_ETI_Atividade!$C$15:$C$121,$G$53) -> 0.65 | H57: =SUMIFS(RH_ETI_Atividade!$AN$15:$AN$121,RH_ETI_Atividade!$B$15:$B$121,$B57,RH_ETI_Atividade!$C$15:$C$121,$H$53) -> 0 | I57: =SUMIFS(RH_ETI_Atividade!$AN$15:$AN$121,RH_ETI_Atividade!$B$15:$B$121,$B57,RH_ETI_Atividade!$C$15:$C$121,$I$53) -> 0 | J57: =SUMIFS(RH_ETI_Atividade!$AN$15:$AN$121,RH_ETI_Atividade!$B$15:$B$121,$B57,RH_ETI_Atividade!$C$15:$C$121,$J$53) -> 0 | K57: =SUMIFS(RH_ETI_Atividade!$AN$15:$AN$121,RH_ETI_Atividade!$B$15:$B$121,$B57,RH_ETI_Atividade!$C$15:$C$121,$K$53) -> 0 | L57: =SUMIFS(RH_ETI_Atividade!$AN$15:$AN$121,RH_ETI_Atividade!$B$15:$B$121,$B57,RH_ETI_Atividade!$C$15:$C$121,$L$53) -> 0 | M57: =SUMIFS(RH_ETI_Atividade!$AN$15:$AN$121,RH_ETI_Atividade!$B$15:$B$121,$B57,RH_ETI_Atividade!$C$15:$C$121,$M$53) -> 0 | N57: =SUM(C57:M57) -> 1.65 | O57: =RH_EQUIPA!L22 -> 1.65
B58: ='Valores bolsas e 57_2016'!A46 -> Jânio Monteiro | C58: =SUMIFS(RH_ETI_Atividade!$AN$15:$AN$121,RH_ETI_Atividade!$B$15:$B$121,B58,RH_ETI_Atividade!$C$15:$C$121,$C$53) -> 0 | D58: =SUMIFS(RH_ETI_Atividade!$AN$15:$AN$121,RH_ETI_Atividade!$B$15:$B$121,B58,RH_ETI_Atividade!$C$15:$C$121,$D$53) -> 0 | E58: =SUMIFS(RH_ETI_Atividade!$AN$15:$AN$121,RH_ETI_Atividade!$B$15:$B$121,B58,RH_ETI_Atividade!$C$15:$C$121,$E$53) -> 1 | F58: =SUMIFS(RH_ETI_Atividade!$AN$15:$AN$121,RH_ETI_Atividade!$B$15:$B$121,$B58,RH_ETI_Atividade!$C$15:$C$121,$F$53) -> 0 | G58: =SUMIFS(RH_ETI_Atividade!$AN$15:$AN$121,RH_ETI_Atividade!$B$15:$B$121,$B58,RH_ETI_Atividade!$C$15:$C$121,$G$53) -> 0.65 | H58: =SUMIFS(RH_ETI_Atividade!$AN$15:$AN$121,RH_ETI_Atividade!$B$15:$B$121,$B58,RH_ETI_Atividade!$C$15:$C$121,$H$53) -> 0 | I58: =SUMIFS(RH_ETI_Atividade!$AN$15:$AN$121,RH_ETI_Atividade!$B$15:$B$121,$B58,RH_ETI_Atividade!$C$15:$C$121,$I$53) -> 0 | J58: =SUMIFS(RH_ETI_Atividade!$AN$15:$AN$121,RH_ETI_Atividade!$B$15:$B$121,$B58,RH_ETI_Atividade!$C$15:$C$121,$J$53) -> 0 | K58: =SUMIFS(RH_ETI_Atividade!$AN$15:$AN$121,RH_ETI_Atividade!$B$15:$B$121,$B58,RH_ETI_Atividade!$C$15:$C$121,$K$53) -> 0 | L58: =SUMIFS(RH_ETI_Atividade!$AN$15:$AN$121,RH_ETI_Atividade!$B$15:$B$121,$B58,RH_ETI_Atividade!$C$15:$C$121,$L$53) -> 0 | M58: =SUMIFS(RH_ETI_Atividade!$AN$15:$AN$121,RH_ETI_Atividade!$B$15:$B$121,$B58,RH_ETI_Atividade!$C$15:$C$121,$M$53) -> 0 | N58: =SUM(C58:M58) -> 1.65 | O58: =RH_EQUIPA!L23 -> 1.65
B59: ='Valores bolsas e 57_2016'!A47 -> Pedro cardoso | C59: =SUMIFS(RH_ETI_Atividade!$AN$15:$AN$121,RH_ETI_Atividade!$B$15:$B$121,B59,RH_ETI_Atividade!$C$15:$C$121,$C$53) -> 0 | D59: =SUMIFS(RH_ETI_Atividade!$AN$15:$AN$121,RH_ETI_Atividade!$B$15:$B$121,B59,RH_ETI_Atividade!$C$15:$C$121,$D$53) -> 0 | E59: =SUMIFS(RH_ETI_Atividade!$AN$15:$AN$121,RH_ETI_Atividade!$B$15:$B$121,B59,RH_ETI_Atividade!$C$15:$C$121,$E$53) -> 0 | F59: =SUMIFS(RH_ETI_Atividade!$AN$15:$AN$121,RH_ETI_Atividade!$B$15:$B$121,$B59,RH_ETI_Atividade!$C$15:$C$121,$F$53) -> 0 | G59: =SUMIFS(RH_ETI_Atividade!$AN$15:$AN$121,RH_ETI_Atividade!$B$15:$B$121,$B59,RH_ETI_Atividade!$C$15:$C$121,$G$53) -> 1.65 | H59: =SUMIFS(RH_ETI_Atividade!$AN$15:$AN$121,RH_ETI_Atividade!$B$15:$B$121,$B59,RH_ETI_Atividade!$C$15:$C$121,$H$53) -> 0 | I59: =SUMIFS(RH_ETI_Atividade!$AN$15:$AN$121,RH_ETI_Atividade!$B$15:$B$121,$B59,RH_ETI_Atividade!$C$15:$C$121,$I$53) -> 0 | J59: =SUMIFS(RH_ETI_Atividade!$AN$15:$AN$121,RH_ETI_Atividade!$B$15:$B$121,$B59,RH_ETI_Atividade!$C$15:$C$121,$J$53) -> 0 | K59: =SUMIFS(RH_ETI_Atividade!$AN$15:$AN$121,RH_ETI_Atividade!$B$15:$B$121,$B59,RH_ETI_Atividade!$C$15:$C$121,$K$53) -> 0 | L59: =SUMIFS(RH_ETI_Atividade!$AN$15:$AN$121,RH_ETI_Atividade!$B$15:$B$121,$B59,RH_ETI_Atividade!$C$15:$C$121,$L$53) -> 0 | M59: =SUMIFS(RH_ETI_Atividade!$AN$15:$AN$121,RH_ETI_Atividade!$B$15:$B$121,$B59,RH_ETI_Atividade!$C$15:$C$121,$M$53) -> 0 | N59: =SUM(C59:M59) -> 1.65 | O59: =RH_EQUIPA!L24 -> 1.65
B60: ='Valores bolsas e 57_2016'!A48 -> Roberto Lam | C60: =SUMIFS(RH_ETI_Atividade!$AN$15:$AN$121,RH_ETI_Atividade!$B$15:$B$121,B60,RH_ETI_Atividade!$C$15:$C$121,$C$53) -> 0 | D60: =SUMIFS(RH_ETI_Atividade!$AN$15:$AN$121,RH_ETI_Atividade!$B$15:$B$121,B60,RH_ETI_Atividade!$C$15:$C$121,$D$53) -> 1 | E60: =SUMIFS(RH_ETI_Atividade!$AN$15:$AN$121,RH_ETI_Atividade!$B$15:$B$121,B60,RH_ETI_Atividade!$C$15:$C$121,$E$53) -> 0 | F60: =SUMIFS(RH_ETI_Atividade!$AN$15:$AN$121,RH_ETI_Atividade!$B$15:$B$121,$B60,RH_ETI_Atividade!$C$15:$C$121,$F$53) -> 0 | G60: =SUMIFS(RH_ETI_Atividade!$AN$15:$AN$121,RH_ETI_Atividade!$B$15:$B$121,$B60,RH_ETI_Atividade!$C$15:$C$121,$G$53) -> 0.65 | H60: =SUMIFS(RH_ETI_Atividade!$AN$15:$AN$121,RH_ETI_Atividade!$B$15:$B$121,$B60,RH_ETI_Atividade!$C$15:$C$121,$H$53) -> 0 | I60: =SUMIFS(RH_ETI_Atividade!$AN$15:$AN$121,RH_ETI_Atividade!$B$15:$B$121,$B60,RH_ETI_Atividade!$C$15:$C$121,$I$53) -> 0 | J60: =SUMIFS(RH_ETI_Atividade!$AN$15:$AN$121,RH_ETI_Atividade!$B$15:$B$121,$B60,RH_ETI_Atividade!$C$15:$C$121,$J$53) -> 0 | K60: =SUMIFS(RH_ETI_Atividade!$AN$15:$AN$121,RH_ETI_Atividade!$B$15:$B$121,$B60,RH_ETI_Atividade!$C$15:$C$121,$K$53) -> 0 | L60: =SUMIFS(RH_ETI_Atividade!$AN$15:$AN$121,RH_ETI_Atividade!$B$15:$B$121,$B60,RH_ETI_Atividade!$C$15:$C$121,$L$53) -> 0 | M60: =SUMIFS(RH_ETI_Atividade!$AN$15:$AN$121,RH_ETI_Atividade!$B$15:$B$121,$B60,RH_ETI_Atividade!$C$15:$C$121,$M$53) -> 0 | N60: =SUM(C60:M60) -> 1.65 | O60: =RH_EQUIPA!L25 -> 1.65
B61: ='Valores bolsas e 57_2016'!A49 -> Cristiano Cabrita | C61: =SUMIFS(RH_ETI_Atividade!$AN$15:$AN$121,RH_ETI_Atividade!$B$15:$B$121,B61,RH_ETI_Atividade!$C$15:$C$121,$C$53) -> 0 | D61: =SUMIFS(RH_ETI_Atividade!$AN$15:$AN$121,RH_ETI_Atividade!$B$15:$B$121,B61,RH_ETI_Atividade!$C$15:$C$121,$D$53) -> 1 | E61: =SUMIFS(RH_ETI_Atividade!$AN$15:$AN$121,RH_ETI_Atividade!$B$15:$B$121,B61,RH_ETI_Atividade!$C$15:$C$121,$E$53) -> 0 | F61: =SUMIFS(RH_ETI_Atividade!$AN$15:$AN$121,RH_ETI_Atividade!$B$15:$B$121,$B61,RH_ETI_Atividade!$C$15:$C$121,$F$53) -> 0 | G61: =SUMIFS(RH_ETI_Atividade!$AN$15:$AN$121,RH_ETI_Atividade!$B$15:$B$121,$B61,RH_ETI_Atividade!$C$15:$C$121,$G$53) -> 0.65 | H61: =SUMIFS(RH_ETI_Atividade!$AN$15:$AN$121,RH_ETI_Atividade!$B$15:$B$121,$B61,RH_ETI_Atividade!$C$15:$C$121,$H$53) -> 0 | I61: =SUMIFS(RH_ETI_Atividade!$AN$15:$AN$121,RH_ETI_Atividade!$B$15:$B$121,$B61,RH_ETI_Atividade!$C$15:$C$121,$I$53) -> 0 | J61: =SUMIFS(RH_ETI_Atividade!$AN$15:$AN$121,RH_ETI_Atividade!$B$15:$B$121,$B61,RH_ETI_Atividade!$C$15:$C$121,$J$53) -> 0 | K61: =SUMIFS(RH_ETI_Atividade!$AN$15:$AN$121,RH_ETI_Atividade!$B$15:$B$121,$B61,RH_ETI_Atividade!$C$15:$C$121,$K$53) -> 0 | L61: =SUMIFS(RH_ETI_Atividade!$AN$15:$AN$121,RH_ETI_Atividade!$B$15:$B$121,$B61,RH_ETI_Atividade!$C$15:$C$121,$L$53) -> 0 | M61: =SUMIFS(RH_ETI_Atividade!$AN$15:$AN$121,RH_ETI_Atividade!$B$15:$B$121,$B61,RH_ETI_Atividade!$C$15:$C$121,$M$53) -> 0 | N61: =SUM(C61:M61) -> 1.65 | O61: =RH_EQUIPA!L26 -> 1.65
B62: ='Valores bolsas e 57_2016'!A50 -> Jaime Martins | C62: =SUMIFS(RH_ETI_Atividade!$AN$15:$AN$121,RH_ETI_Atividade!$B$15:$B$121,B62,RH_ETI_Atividade!$C$15:$C$121,$C$53) -> 0 | D62: =SUMIFS(RH_ETI_Atividade!$AN$15:$AN$121,RH_ETI_Atividade!$B$15:$B$121,B62,RH_ETI_Atividade!$C$15:$C$121,$D$53) -> 0 | E62: =SUMIFS(RH_ETI_Atividade!$AN$15:$AN$121,RH_ETI_Atividade!$B$15:$B$121,B62,RH_ETI_Atividade!$C$15:$C$121,$E$53) -> 0 | F62: =SUMIFS(RH_ETI_Atividade!$AN$15:$AN$121,RH_ETI_Atividade!$B$15:$B$121,$B62,RH_ETI_Atividade!$C$15:$C$121,$F$53) -> 0 | G62: =SUMIFS(RH_ETI_Atividade!$AN$15:$AN$121,RH_ETI_Atividade!$B$15:$B$121,$B62,RH_ETI_Atividade!$C$15:$C$121,$G$53) -> 1.65 | H62: =SUMIFS(RH_ETI_Atividade!$AN$15:$AN$121,RH_ETI_Atividade!$B$15:$B$121,$B62,RH_ETI_Atividade!$C$15:$C$121,$H$53) -> 0 | I62: =SUMIFS(RH_ETI_Atividade!$AN$15:$AN$121,RH_ETI_Atividade!$B$15:$B$121,$B62,RH_ETI_Atividade!$C$15:$C$121,$I$53) -> 0 | J62: =SUMIFS(RH_ETI_Atividade!$AN$15:$AN$121,RH_ETI_Atividade!$B$15:$B$121,$B62,RH_ETI_Atividade!$C$15:$C$121,$J$53) -> 0 | K62: =SUMIFS(RH_ETI_Atividade!$AN$15:$AN$121,RH_ETI_Atividade!$B$15:$B$121,$B62,RH_ETI_Atividade!$C$15:$C$121,$K$53) -> 0 | L62: =SUMIFS(RH_ETI_Atividade!$AN$15:$AN$121,RH_ETI_Atividade!$B$15:$B$121,$B62,RH_ETI_Atividade!$C$15:$C$121,$L$53) -> 0 | M62: =SUMIFS(RH_ETI_Atividade!$AN$15:$AN$121,RH_ETI_Atividade!$B$15:$B$121,$B62,RH_ETI_Atividade!$C$15:$C$121,$M$53) -> 0 | N62: =SUM(C62:M62) -> 1.65 | O62: =RH_EQUIPA!L27 -> 1.65
B63: ='Valores bolsas e 57_2016'!A51 -> Paulo Silva | C63: =SUMIFS(RH_ETI_Atividade!$AN$15:$AN$121,RH_ETI_Atividade!$B$15:$B$121,B63,RH_ETI_Atividade!$C$15:$C$121,$C$53) -> 0 | D63: =SUMIFS(RH_ETI_Atividade!$AN$15:$AN$121,RH_ETI_Atividade!$B$15:$B$121,B63,RH_ETI_Atividade!$C$15:$C$121,$D$53) -> 2 | E63: =SUMIFS(RH_ETI_Atividade!$AN$15:$AN$121,RH_ETI_Atividade!$B$15:$B$121,B63,RH_ETI_Atividade!$C$15:$C$121,$E$53) -> 2 | F63: =SUMIFS(RH_ETI_Atividade!$AN$15:$AN$121,RH_ETI_Atividade!$B$15:$B$121,$B63,RH_ETI_Atividade!$C$15:$C$121,$F$53) -> 0 | G63: =SUMIFS(RH_ETI_Atividade!$AN$15:$AN$121,RH_ETI_Atividade!$B$15:$B$121,$B63,RH_ETI_Atividade!$C$15:$C$121,$G$53) -> 0.95 | H63: =SUMIFS(RH_ETI_Atividade!$AN$15:$AN$121,RH_ETI_Atividade!$B$15:$B$121,$B63,RH_ETI_Atividade!$C$15:$C$121,$H$53) -> 0 | I63: =SUMIFS(RH_ETI_Atividade!$AN$15:$AN$121,RH_ETI_Atividade!$B$15:$B$121,$B63,RH_ETI_Atividade!$C$15:$C$121,$I$53) -> 0 | J63: =SUMIFS(RH_ETI_Atividade!$AN$15:$AN$121,RH_ETI_Atividade!$B$15:$B$121,$B63,RH_ETI_Atividade!$C$15:$C$121,$J$53) -> 0 | K63: =SUMIFS(RH_ETI_Atividade!$AN$15:$AN$121,RH_ETI_Atividade!$B$15:$B$121,$B63,RH_ETI_Atividade!$C$15:$C$121,$K$53) -> 0 | L63: =SUMIFS(RH_ETI_Atividade!$AN$15:$AN$121,RH_ETI_Atividade!$B$15:$B$121,$B63,RH_ETI_Atividade!$C$15:$C$121,$L$53) -> 0 | M63: =SUMIFS(RH_ETI_Atividade!$AN$15:$AN$121,RH_ETI_Atividade!$B$15:$B$121,$B63,RH_ETI_Atividade!$C$15:$C$121,$M$53) -> 0 | N63: =SUM(C63:M63) -> 4.95 | O63: =RH_EQUIPA!L28 -> 4.95
B64: ='Valores bolsas e 57_2016'!A52 -> João Rodrigues | C64: =SUMIFS(RH_ETI_Atividade!$AN$15:$AN$121,RH_ETI_Atividade!$B$15:$B$121,B64,RH_ETI_Atividade!$C$15:$C$121,$C$53) -> 0 | D64: =SUMIFS(RH_ETI_Atividade!$AN$15:$AN$121,RH_ETI_Atividade!$B$15:$B$121,B64,RH_ETI_Atividade!$C$15:$C$121,$D$53) -> 0 | E64: =SUMIFS(RH_ETI_Atividade!$AN$15:$AN$121,RH_ETI_Atividade!$B$15:$B$121,B64,RH_ETI_Atividade!$C$15:$C$121,$E$53) -> 0 | F64: =SUMIFS(RH_ETI_Atividade!$AN$15:$AN$121,RH_ETI_Atividade!$B$15:$B$121,$B64,RH_ETI_Atividade!$C$15:$C$121,$F$53) -> 0 | G64: =SUMIFS(RH_ETI_Atividade!$AN$15:$AN$121,RH_ETI_Atividade!$B$15:$B$121,$B64,RH_ETI_Atividade!$C$15:$C$121,$G$53) -> 0.66 | H64: =SUMIFS(RH_ETI_Atividade!$AN$15:$AN$121,RH_ETI_Atividade!$B$15:$B$121,$B64,RH_ETI_Atividade!$C$15:$C$121,$H$53) -> 0 | I64: =SUMIFS(RH_ETI_Atividade!$AN$15:$AN$121,RH_ETI_Atividade!$B$15:$B$121,$B64,RH_ETI_Atividade!$C$15:$C$121,$I$53) -> 0 | J64: =SUMIFS(RH_ETI_Atividade!$AN$15:$AN$121,RH_ETI_Atividade!$B$15:$B$121,$B64,RH_ETI_Atividade!$C$15:$C$121,$J$53) -> 0 | K64: =SUMIFS(RH_ETI_Atividade!$AN$15:$AN$121,RH_ETI_Atividade!$B$15:$B$121,$B64,RH_ETI_Atividade!$C$15:$C$121,$K$53) -> 0 | L64: =SUMIFS(RH_ETI_Atividade!$AN$15:$AN$121,RH_ETI_Atividade!$B$15:$B$121,$B64,RH_ETI_Atividade!$C$15:$C$121,$L$53) -> 0 | M64: =SUMIFS(RH_ETI_Atividade!$AN$15:$AN$121,RH_ETI_Atividade!$B$15:$B$121,$B64,RH_ETI_Atividade!$C$15:$C$121,$M$53) -> 0 | N64: =SUM(C64:M64) -> 0.66 | O64: =RH_EQUIPA!L29 -> 0.66
B65: ='Valores bolsas e 57_2016'!A53 -> Joana Lessa | C65: =SUMIFS(RH_ETI_Atividade!$AN$15:$AN$121,RH_ETI_Atividade!$B$15:$B$121,B65,RH_ETI_Atividade!$C$15:$C$121,$C$53) -> 1.1 | D65: =SUMIFS(RH_ETI_Atividade!$AN$15:$AN$121,RH_ETI_Atividade!$B$15:$B$121,B65,RH_ETI_Atividade!$C$15:$C$121,$D$53) -> 0 | E65: =SUMIFS(RH_ETI_Atividade!$AN$15:$AN$121,RH_ETI_Atividade!$B$15:$B$121,B65,RH_ETI_Atividade!$C$15:$C$121,$E$53) -> 0 | F65: =SUMIFS(RH_ETI_Atividade!$AN$15:$AN$121,RH_ETI_Atividade!$B$15:$B$121,$B65,RH_ETI_Atividade!$C$15:$C$121,$F$53) -> 0 | G65: =SUMIFS(RH_ETI_Atividade!$AN$15:$AN$121,RH_ETI_Atividade!$B$15:$B$121,$B65,RH_ETI_Atividade!$C$15:$C$121,$G$53) -> 0 | H65: =SUMIFS(RH_ETI_Atividade!$AN$15:$AN$121,RH_ETI_Atividade!$B$15:$B$121,$B65,RH_ETI_Atividade!$C$15:$C$121,$H$53) -> 5.5 | I65: =SUMIFS(RH_ETI_Atividade!$AN$15:$AN$121,RH_ETI_Atividade!$B$15:$B$121,$B65,RH_ETI_Atividade!$C$15:$C$121,$I$53) -> 0 | J65: =SUMIFS(RH_ETI_Atividade!$AN$15:$AN$121,RH_ETI_Atividade!$B$15:$B$121,$B65,RH_ETI_Atividade!$C$15:$C$121,$J$53) -> 0 | K65: =SUMIFS(RH_ETI_Atividade!$AN$15:$AN$121,RH_ETI_Atividade!$B$15:$B$121,$B65,RH_ETI_Atividade!$C$15:$C$121,$K$53) -> 0 | L65: =SUMIFS(RH_ETI_Atividade!$AN$15:$AN$121,RH_ETI_Atividade!$B$15:$B$121,$B65,RH_ETI_Atividade!$C$15:$C$121,$L$53) -> 0 | M65: =SUMIFS(RH_ETI_Atividade!$AN$15:$AN$121,RH_ETI_Atividade!$B$15:$B$121,$B65,RH_ETI_Atividade!$C$15:$C$121,$M$53) -> 0 | N65: =SUM(C65:M65) -> 6.6 | O65: =RH_EQUIPA!L30 -> 6.6
... B67: ='Valores bolsas e 57_2016'!A55 -> Joel Guerreiro | C67: =SUMIFS(RH_ETI_Atividade!$AN$15:$AN$121,RH_ETI_Atividade!$B$15:$B$121,B67,RH_ETI_Atividade!$C$15:$C$121,$C$53) -> 0 | D67: =SUMIFS(RH_ETI_Atividade!$AN$15:$AN$121,RH_ETI_Atividade!$B$15:$B$121,B67,RH_ETI_Atividade!$C$15:$C$121,$D$53) -> 1.5 | E67: =SUMIFS(RH_ETI_Atividade!$AN$15:$AN$121,RH_ETI_Atividade!$B$15:$B$121,B67,RH_ETI_Atividade!$C$15:$C$121,$E$53) -> 0 | F67: =SUMIFS(RH_ETI_Atividade!$AN$15:$AN$121,RH_ETI_Atividade!$B$15:$B$121,$B67,RH_ETI_Atividade!$C$15:$C$121,$F$53) -> 0 | G67: =SUMIFS(RH_ETI_Atividade!$AN$15:$AN$121,RH_ETI_Atividade!$B$15:$B$121,$B67,RH_ETI_Atividade!$C$15:$C$121,$G$53) -> 1.8 | H67: =SUMIFS(RH_ETI_Atividade!$AN$15:$AN$121,RH_ETI_Atividade!$B$15:$B$121,$B67,RH_ETI_Atividade!$C$15:$C$121,$H$53) -> 0 | I67: =SUMIFS(RH_ETI_Atividade!$AN$15:$AN$121,RH_ETI_Atividade!$B$15:$B$121,$B67,RH_ETI_Atividade!$C$15:$C$121,$I$53) -> 0 | J67: =SUMIFS(RH_ETI_Atividade!$AN$15:$AN$121,RH_ETI_Atividade!$B$15:$B$121,$B67,RH_ETI_Atividade!$C$15:$C$121,$J$53) -> 0 | K67: =SUMIFS(RH_ETI_Atividade!$AN$15:$AN$121,RH_ETI_Atividade!$B$15:$B$121,$B67,RH_ETI_Atividade!$C$15:$C$121,$K$53) -> 0 | L67: =SUMIFS(RH_ETI_Atividade!$AN$15:$AN$121,RH_ETI_Atividade!$B$15:$B$121,$B67,RH_ETI_Atividade!$C$15:$C$121,$L$53) -> 0 | M67: =SUMIFS(RH_ETI_Atividade!$AN$15:$AN$121,RH_ETI_Atividade!$B$15:$B$121,$B67,RH_ETI_Atividade!$C$15:$C$121,$M$53) -> 0 | N67: =SUM(C67:M67) -> 3.3 | O67: =RH_EQUIPA!L32 -> 3.3
B68: ='Valores bolsas e 57_2016'!A56 | C68: =SUMIFS(RH_ETI_Atividade!$AN$15:$AN$121,RH_ETI_Atividade!$B$15:$B$121,B68,RH_ETI_Atividade!$C$15:$C$121,$C$53) -> 0 | D68: =SUMIFS(RH_ETI_Atividade!$AN$15:$AN$121,RH_ETI_Atividade!$B$15:$B$121,B68,RH_ETI_Atividade!$C$15:$C$121,$D$53) -> 0 | E68: =SUMIFS(RH_ETI_Atividade!$AN$15:$AN$121,RH_ETI_Atividade!$B$15:$B$121,B68,RH_ETI_Atividade!$C$15:$C$121,$E$53) -> 0 | F68: =SUMIFS(RH_ETI_Atividade!$AN$15:$AN$121,RH_ETI_Atividade!$B$15:$B$121,$B68,RH_ETI_Atividade!$C$15:$C$121,$F$53) -> 0 | G68: =SUMIFS(RH_ETI_Atividade!$AN$15:$AN$121,RH_ETI_Atividade!$B$15:$B$121,$B68,RH_ETI_Atividade!$C$15:$C$121,$G$53) -> 0 | H68: =SUMIFS(RH_ETI_Atividade!$AN$15:$AN$121,RH_ETI_Atividade!$B$15:$B$121,$B68,RH_ETI_Atividade!$C$15:$C$121,$H$53) -> 0 | I68: =SUMIFS(RH_ETI_Atividade!$AN$15:$AN$121,RH_ETI_Atividade!$B$15:$B$121,$B68,RH_ETI_Atividade!$C$15:$C$121,$I$53) -> 0 | J68: =SUMIFS(RH_ETI_Atividade!$AN$15:$AN$121,RH_ETI_Atividade!$B$15:$B$121,$B68,RH_ETI_Atividade!$C$15:$C$121,$J$53) -> 0 | K68: =SUMIFS(RH_ETI_Atividade!$AN$15:$AN$121,RH_ETI_Atividade!$B$15:$B$121,$B68,RH_ETI_Atividade!$C$15:$C$121,$K$53) -> 0 | L68: =SUMIFS(RH_ETI_Atividade!$AN$15:$AN$121,RH_ETI_Atividade!$B$15:$B$121,$B68,RH_ETI_Atividade!$C$15:$C$121,$L$53) -> 0 | M68: =SUMIFS(RH_ETI_Atividade!$AN$15:$AN$121,RH_ETI_Atividade!$B$15:$B$121,$B68,RH_ETI_Atividade!$C$15:$C$121,$M$53) -> 0 | N68: =SUM(C68:M68) -> 0 | O68: =RH_EQUIPA!L34 -> 27.5
B69: ='Valores bolsas e 57_2016'!A57 -> B1 | C69: =SUMIFS(RH_ETI_Atividade!$AN$15:$AN$121,RH_ETI_Atividade!$B$15:$B$121,B69,RH_ETI_Atividade!$C$15:$C$121,$C$53) -> 0 | D69: =SUMIFS(RH_ETI_Atividade!$AN$15:$AN$121,RH_ETI_Atividade!$B$15:$B$121,B69,RH_ETI_Atividade!$C$15:$C$121,$D$53) -> 6 | E69: =SUMIFS(RH_ETI_Atividade!$AN$15:$AN$121,RH_ETI_Atividade!$B$15:$B$121,B69,RH_ETI_Atividade!$C$15:$C$121,$E$53) -> 8 | F69: =SUMIFS(RH_ETI_Atividade!$AN$15:$AN$121,RH_ETI_Atividade!$B$15:$B$121,$B69,RH_ETI_Atividade!$C$15:$C$121,$F$53) -> 3 | G69: =SUMIFS(RH_ETI_Atividade!$AN$15:$AN$121,RH_ETI_Atividade!$B$15:$B$121,$B69,RH_ETI_Atividade!$C$15:$C$121,$G$53) -> 5.5 | H69: =SUMIFS(RH_ETI_Atividade!$AN$15:$AN$121,RH_ETI_Atividade!$B$15:$B$121,$B69,RH_ETI_Atividade!$C$15:$C$121,$H$53) -> 5 | I69: =SUMIFS(RH_ETI_Atividade!$AN$15:$AN$121,RH_ETI_Atividade!$B$15:$B$121,$B69,RH_ETI_Atividade!$C$15:$C$121,$I$53) -> 0 | J69: =SUMIFS(RH_ETI_Atividade!$AN$15:$AN$121,RH_ETI_Atividade!$B$15:$B$121,I69,RH_ETI_Atividade!$C$15:$C$121,$C$53) -> 0 | K69: =SUMIFS(RH_ETI_Atividade!$AN$15:$AN$121,RH_ETI_Atividade!$B$15:$B$121,J69,RH_ETI_Atividade!$C$15:$C$121,$C$53) -> 0 | L69: =SUMIFS(RH_ETI_Atividade!$AN$15:$AN$121,RH_ETI_Atividade!$B$15:$B$121,K69,RH_ETI_Atividade!$C$15:$C$121,$C$53) -> 0 | M69: =SUMIFS(RH_ETI_Atividade!$AN$15:$AN$121,RH_ETI_Atividade!$B$15:$B$121,L69,RH_ETI_Atividade!$C$15:$C$121,$C$53) -> 0 | N69: =SUM(C69:M69) -> 27.5 | O69: =RH_EQUIPA!L35 -> 27.5
B70: ='Valores bolsas e 57_2016'!A58 -> B2 | C70: =SUMIFS(RH_ETI_Atividade!$AN$15:$AN$121,RH_ETI_Atividade!$B$15:$B$121,B70,RH_ETI_Atividade!$C$15:$C$121,$C$53) -> 0 | D70: =SUMIFS(RH_ETI_Atividade!$AN$15:$AN$121,RH_ETI_Atividade!$B$15:$B$121,B70,RH_ETI_Atividade!$C$15:$C$121,$D$53) -> 6 | E70: =SUMIFS(RH_ETI_Atividade!$AN$15:$AN$121,RH_ETI_Atividade!$B$15:$B$121,B70,RH_ETI_Atividade!$C$15:$C$121,$E$53) -> 6 | F70: =SUMIFS(RH_ETI_Atividade!$AN$15:$AN$121,RH_ETI_Atividade!$B$15:$B$121,$B70,RH_ETI_Atividade!$C$15:$C$121,$F$53) -> 3 | G70: =SUMIFS(RH_ETI_Atividade!$AN$15:$AN$121,RH_ETI_Atividade!$B$15:$B$121,$B70,RH_ETI_Atividade!$C$15:$C$121,$G$53) -> 7 | H70: =SUMIFS(RH_ETI_Atividade!$AN$15:$AN$121,RH_ETI_Atividade!$B$15:$B$121,$B70,RH_ETI_Atividade!$C$15:$C$121,$H$53) -> 5.5 | I70: =SUMIFS(RH_ETI_Atividade!$AN$15:$AN$121,RH_ETI_Atividade!$B$15:$B$121,$B70,RH_ETI_Atividade!$C$15:$C$121,$I$53) -> 0 | J70: =SUMIFS(RH_ETI_Atividade!$AN$15:$AN$121,RH_ETI_Atividade!$B$15:$B$121,$B70,RH_ETI_Atividade!$C$15:$C$121,$J$53) -> 0 | K70: =SUMIFS(RH_ETI_Atividade!$AN$15:$AN$121,RH_ETI_Atividade!$B$15:$B$121,$B70,RH_ETI_Atividade!$C$15:$C$121,$K$53) -> 0 | L70: =SUMIFS(RH_ETI_Atividade!$AN$15:$AN$121,RH_ETI_Atividade!$B$15:$B$121,$B70,RH_ETI_Atividade!$C$15:$C$121,$L$53) -> 0 | M70: =SUMIFS(RH_ETI_Atividade!$AN$15:$AN$121,RH_ETI_Atividade!$B$15:$B$121,$B70,RH_ETI_Atividade!$C$15:$C$121,$M$53) -> 0 | N70: =SUM(C70:M70) -> 27.5 | O70: =RH_EQUIPA!L36 -> 27.5
B71: ='Valores bolsas e 57_2016'!A59 -> B3 | C71: =SUMIFS(RH_ETI_Atividade!$AN$15:$AN$121,RH_ETI_Atividade!$B$15:$B$121,B71,RH_ETI_Atividade!$C$15:$C$121,$C$53) -> 0 | D71: =SUMIFS(RH_ETI_Atividade!$AN$15:$AN$121,RH_ETI_Atividade!$B$15:$B$121,B71,RH_ETI_Atividade!$C$15:$C$121,$D$53) -> 7 | E71: =SUMIFS(RH_ETI_Atividade!$AN$15:$AN$121,RH_ETI_Atividade!$B$15:$B$121,B71,RH_ETI_Atividade!$C$15:$C$121,$E$53) -> 6 | F71: =SUMIFS(RH_ETI_Atividade!$AN$15:$AN$121,RH_ETI_Atividade!$B$15:$B$121,$B71,RH_ETI_Atividade!$C$15:$C$121,$F$53) -> 2 | G71: =SUMIFS(RH_ETI_Atividade!$AN$15:$AN$121,RH_ETI_Atividade!$B$15:$B$121,$B71,RH_ETI_Atividade!$C$15:$C$121,$G$53) -> 7 | H71: =SUMIFS(RH_ETI_Atividade!$AN$15:$AN$121,RH_ETI_Atividade!$B$15:$B$121,$B71,RH_ETI_Atividade!$C$15:$C$121,$H$53) -> 5.5 | I71: =SUMIFS(RH_ETI_Atividade!$AN$15:$AN$121,RH_ETI_Atividade!$B$15:$B$121,$B71,RH_ETI_Atividade!$C$15:$C$121,$I$53) -> 0 | J71: =SUMIFS(RH_ETI_Atividade!$AN$15:$AN$121,RH_ETI_Atividade!$B$15:$B$121,$B71,RH_ETI_Atividade!$C$15:$C$121,$J$53) -> 0 | K71: =SUMIFS(RH_ETI_Atividade!$AN$15:$AN$121,RH_ETI_Atividade!$B$15:$B$121,$B71,RH_ETI_Atividade!$C$15:$C$121,$K$53) -> 0 | L71: =SUMIFS(RH_ETI_Atividade!$AN$15:$AN$121,RH_ETI_Atividade!$B$15:$B$121,$B71,RH_ETI_Atividade!$C$15:$C$121,$L$53) -> 0 | M71: =SUMIFS(RH_ETI_Atividade!$AN$15:$AN$121,RH_ETI_Atividade!$B$15:$B$121,$B71,RH_ETI_Atividade!$C$15:$C$121,$M$53) -> 0 | N71: =SUM(C71:M71) -> 27.5 | O71: =RH_EQUIPA!L37 -> 0
B72: ='Valores bolsas e 57_2016'!A60 -> B4 | C72: =SUMIFS(RH_ETI_Atividade!$AN$15:$AN$121,RH_ETI_Atividade!$B$15:$B$121,B72,RH_ETI_Atividade!$C$15:$C$121,$C$53) -> 0 | D72: =SUMIFS(RH_ETI_Atividade!$AN$15:$AN$121,RH_ETI_Atividade!$B$15:$B$121,B72,RH_ETI_Atividade!$C$15:$C$121,$D$53) -> 0 | E72: =SUMIFS(RH_ETI_Atividade!$AN$15:$AN$121,RH_ETI_Atividade!$B$15:$B$121,B72,RH_ETI_Atividade!$C$15:$C$121,$E$53) -> 0 | F72: =SUMIFS(RH_ETI_Atividade!$AN$15:$AN$121,RH_ETI_Atividade!$B$15:$B$121,$B72,RH_ETI_Atividade!$C$15:$C$121,$F$53) -> 0 | G72: =SUMIFS(RH_ETI_Atividade!$AN$15:$AN$121,RH_ETI_Atividade!$B$15:$B$121,$B72,RH_ETI_Atividade!$C$15:$C$121,$G$53) -> 0 | H72: =SUMIFS(RH_ETI_Atividade!$AN$15:$AN$121,RH_ETI_Atividade!$B$15:$B$121,$B72,RH_ETI_Atividade!$C$15:$C$121,$H$53) -> 0 | I72: =SUMIFS(RH_ETI_Atividade!$AN$15:$AN$121,RH_ETI_Atividade!$B$15:$B$121,$B72,RH_ETI_Atividade!$C$15:$C$121,$I$53) -> 0 | J72: =SUMIFS(RH_ETI_Atividade!$AN$15:$AN$121,RH_ETI_Atividade!$B$15:$B$121,$B72,RH_ETI_Atividade!$C$15:$C$121,$J$53) -> 0 | K72: =SUMIFS(RH_ETI_Atividade!$AN$15:$AN$121,RH_ETI_Atividade!$B$15:$B$121,$B72,RH_ETI_Atividade!$C$15:$C$121,$K$53) -> 0 | L72: =SUMIFS(RH_ETI_Atividade!$AN$15:$AN$121,RH_ETI_Atividade!$B$15:$B$121,$B72,RH_ETI_Atividade!$C$15:$C$121,$L$53) -> 0 | M72: =SUMIFS(RH_ETI_Atividade!$AN$15:$AN$121,RH_ETI_Atividade!$B$15:$B$121,$B72,RH_ETI_Atividade!$C$15:$C$121,$M$53) -> 0 | N72: =SUM(C72:M72) -> 0 | O72: =SUM(D72:N72) -> 0
B73: TOTAL | C73: =SUM(C54:C72) -> 6.75 | D73: =SUM(D54:D72) -> 26.8 | E73: =SUM(E54:E72) -> 26.5 | F73: =SUM(F54:F72) -> 13.5 | G73: =SUM(G54:G72) -> 34.31 | H73: =SUM(H54:H72) -> 26.45 | I73: =SUM(I54:I72) -> 0 | J73: =SUM(J54:J72) -> 0 | ... O73: =SUM(O54:O72) -> 134.31
C77: FTE/ETI
B78: EQUIPA | C78: A1 | D78: A2 | E78: A3 | F78: A4 | G78: A5 | H78: A6 | I78: A7 | J78: A8 | K78: A9 | L78: A10 | M78: A11 | N78: TOTAL
B79: =+B54 -> Ana Cristina Coelho | C79: =+C54*$D$14 -> 15768 | D79: =+D54*$D$14 -> 5616 | E79: =+E54*$D$14 -> 6480 | F79: =+F54*$D$14 -> 8640 | G79: =+G54*$D$14 -> 8640 | H79: =+H54*$D$14 -> 4752 | I79: =+I54*$D$14 -> 0 | J79: =+J54*$D$14 -> 0 | ... M79: =+M54*$D$14 -> 0 | N79: =SUM(C79:M79) -> 49896
B80: =+B55 -> Ana Maria Costa | C80: =+C55*$D$14 -> 4320 | D80: =+D55*$D$14 -> 0 | E80: =+E55*$D$14 -> 0 | F80: =+F55*$D$14 -> 8640 | G80: =+G55*$D$14 -> 4320 | H80: =+H55*$D$14 -> 4104 | I80: =+I55*$D$14 -> 0 | J80: =+J55*$D$14 -> 0 | ... M80: =+M55*$D$14 -> 0 | N80: =SUM(C80:M80) -> 21384
B81: =+B56 -> Cristina Veiga-Pires | C81: =+C56*$D$14 -> 4320 | D81: =+D56*$D$14 -> 0 | E81: =+E56*$D$14 -> 8640 | F81: =+F56*$D$14 -> 0 | G81: =+G56*$D$14 -> 4320 | H81: =+H56*$D$14 -> 4104 | I81: =+I56*$D$14 -> 0 | J81: =+J56*$D$14 -> 0 | ... M81: =+M56*$D$14 -> 0 | N81: =SUM(C81:M81) -> 21384
B82: =+B57 -> Jorge Semião | C82: =+C57*$D$14 -> 0 | D82: =+D57*$D$14 -> 4320 | E82: =+E57*$D$14 -> 0 | F82: =+F57*$D$14 -> 0 | G82: =+G57*$D$14 -> 2808 | H82: =+H57*$D$14 -> 0 | I82: =+I57*$D$14 -> 0 | J82: =+J57*$D$14 -> 0 | ... M82: =+M57*$D$14 -> 0 | N82: =SUM(C82:M82) -> 7128
B83: =+B58 -> Jânio Monteiro | C83: =+C58*$D$14 -> 0 | D83: =+D58*$D$14 -> 0 | E83: =+E58*$D$14 -> 4320 | F83: =+F58*$D$14 -> 0 | G83: =+G58*$D$14 -> 2808 | H83: =+H58*$D$14 -> 0 | I83: =+I58*$D$14 -> 0 | J83: =+J58*$D$14 -> 0 | ... M83: =+M58*$D$14 -> 0 | N83: =SUM(C83:M83) -> 7128
B84: =+B59 -> Pedro cardoso | C84: =+C59*$D$14 -> 0 | D84: =+D59*$D$14 -> 0 | E84: =+E59*$D$14 -> 0 | F84: =+F59*$D$14 -> 0 | G84: =+G59*$D$14 -> 7128 | H84: =+H59*$D$14 -> 0 | I84: =+I59*$D$14 -> 0 | J84: =+J59*$D$14 -> 0 | ... M84: =+M59*$D$14 -> 0 | N84: =SUM(C84:M84) -> 7128
B85: =+B60 -> Roberto Lam | C85: =+C60*$D$14 -> 0 | D85: =+D60*$D$14 -> 4320 | E85: =+E60*$D$14 -> 0 | F85: =+F60*$D$14 -> 0 | G85: =+G60*$D$14 -> 2808 | H85: =+H60*$D$14 -> 0 | I85: =+I60*$D$14 -> 0 | J85: =+J60*$D$14 -> 0 | ... M85: =+M60*$D$14 -> 0 | N85: =SUM(C85:M85) -> 7128
B86: =+B61 -> Cristiano Cabrita | C86: =+C61*$D$14 -> 0 | D86: =+D61*$D$14 -> 4320 | E86: =+E61*$D$14 -> 0 | F86: =+F61*$D$14 -> 0 | G86: =+G61*$D$14 -> 2808 | H86: =+H61*$D$14 -> 0 | I86: =+I61*$D$14 -> 0 | J86: =+J61*$D$14 -> 0 | ... M86: =+M61*$D$14 -> 0 | N86: =SUM(C86:M86) -> 7128
B87: =+B62 -> Jaime Martins | C87: =+C62*$D$14 -> 0 | D87: =+D62*$D$14 -> 0 | E87: =+E62*$D$14 -> 0 | F87: =+F62*$D$14 -> 0 | G87: =+G62*$D$14 -> 7128 | H87: =+H62*$D$14 -> 0 | I87: =+I62*$D$14 -> 0 | J87: =+J62*$D$14 -> 0 | ... M87: =+M62*$D$14 -> 0 | N87: =SUM(C87:M87) -> 7128
B88: =+B63 -> Paulo Silva | C88: =+C63*$D$14 -> 0 | D88: =+D63*$D$14 -> 8640 | E88: =+E63*$D$14 -> 8640 | F88: =+F63*$D$14 -> 0 | G88: =+G63*$D$14 -> 4104 | H88: =+H63*$D$14 -> 0 | I88: =+I63*$D$14 -> 0 | J88: =+J63*$D$14 -> 0 | ... M88: =+M63*$D$14 -> 0 | N88: =SUM(C88:M88) -> 21384
B89: =+B64 -> João Rodrigues | C89: =+C64*$D$14 -> 0 | D89: =+D64*$D$14 -> 0 | E89: =+E64*$D$14 -> 0 | F89: =+F64*$D$14 -> 0 | G89: =+G64*$D$14 -> 2851.2 | H89: =+H64*$D$14 -> 0 | I89: =+I64*$D$14 -> 0 | J89: =+J64*$D$14 -> 0 | ... M89: =+M64*$D$14 -> 0 | N89: =SUM(C89:M89) -> 2851.2
B90: =+B65 -> Joana Lessa | C90: =+C65*$D$14 -> 4752 | D90: =+D65*$D$14 -> 0 | E90: =+E65*$D$14 -> 0 | F90: =+F65*$D$14 -> 0 | G90: =+G65*$D$14 -> 0 | H90: =+H65*$D$14 -> 23760 | I90: =+I65*$D$14 -> 0 | J90: =+J65*$D$14 -> 0 | ... M90: =+M65*$D$14 -> 0 | N90: =SUM(C90:M90) -> 28512
... B95: =+B70 -> B2 | C95: =+C70*$D$14 -> 0 | D95: =+D70*$D$14 -> 25920 | E95: =+E70*$D$14 -> 25920 | F95: =+F70*$D$14 -> 12960 | G95: =+G70*$D$14 -> 30240 | H95: =+H70*$D$14 -> 23760 | I95: =+I70*$D$14 -> 0 | J95: =+J70*$D$14 -> 0 | ... M95: =+M70*$D$14 -> 0 | N95: =SUM(C95:M95) -> 118800
B96: =+B71 -> B3 | C96: =+C71*$D$14 -> 0 | D96: =+D71*$D$14 -> 30240 | E96: =+E71*$D$14 -> 25920 | F96: =+F71*$D$14 -> 8640 | G96: =+G71*$D$14 -> 30240 | H96: =+H71*$D$14 -> 23760 | I96: =+I72*$D$14 -> 0 | J96: =+J72*$D$14 -> 0 | K96: =+K72*$D$14 -> 0 | L96: =+L72*$D$14 -> 0 | M96: =+M72*$D$14 -> 0 | N96: =SUM(C96:M96) -> 118800
B97: TOTAL | C97: =SUM(C79:C96) -> 29160 | D97: =SUM(D79:D96) -> 115776 | E97: =SUM(E79:E96) -> 114480 | F97: =SUM(F79:F96) -> 58320 | G97: =SUM(G79:G96) -> 148219.2 | H97: =SUM(H79:H96) -> 114264 | I97: =SUM(I79:I96) -> 0 | J97: =SUM(J79:J96) -> 0 | ... N97: =SUM(N79:N96) -> 580219.2

Sheet Equipamento
E8: SACCT-Projetos de Investigação Científica e Desenvolvimento Tecnológico (IC&DT)
E9: Equipamentos sujeitos a amortizações
J10: =YEAR(J18) -> 2026 | K10: =YEAR(L18) -> 2029
E12: Atenção: A inclusão de equipamentos cuja vida útil não se esgote totalmente dentro do período de execução do projeto e/ ou que não sejam utilizados exclusivamente no âmbito do projeto implica que há uma parcela do valor de aquisição que não é elegível para financiamento pelo projeto. Nestes casos, o valor da amortização não elegível será suportado pelos custos indiretos do projeto. Alerta-se que de acordo com o Despacho n.º RT/ de 13 março o projeto terá que ter um mínimo de 20% de overheads, caso esta condição não seja possível ficará sujeito à aprovação da Reitoria.
D16: Valor da Unidade | E16: Nº | F16: Designação | G16: Classificação das despesas | H16: Valor aquisição | I16: Taxa amortiz. anual | J16: Período de afetação | M16: Nº meses elegivel | N16: Valor elegível | O16: Taxa amort. acumulada (Degressiva) | P16: Valor não elegível | Q16: Valor total | R16: 2026 | S16: =R16+1 -> 2027 | T16: =S16+1 -> 2028 | U16: =T16+1 -> 2029
J17: Início | L17: Fim | R17: Despesa elegível por anos
D18: 1000 | E18: =IF(F18<>"",E17+1,"") -> 1 | F18: Dendómetros (30) | G18: =IF(F18="","","Instrumentos e equipamento científico") -> Instrumentos e equipamento científico | H18: 30000 | I18: 1 | J18: 46296 | K18: =+IF(J18<>"",YEAR(J18),"") -> 2026 | L18: 47391 | M18: =IF(AND(J18<>"",L18<>""),(YEAR(L18)-YEAR(J18))*12+MONTH(L18)-MONTH(J18)+1,"") -> 36 | N18: =IF(AND(M18>0,M18<=12),M18*AO23,IF(AND(M18>12,M18<=24),12*AO23+(M18-12)*AP23,IF(AND(M18>24,M18<=36),12*AO23+12*AP23+(M18-24)*AQ23,IF(AND(M18>36,M18<=48),12*AO23+12*AP23+12*AQ23+(M18-36)*AR23,0)))) -> 30000 | O18: =IF(E18="","",N18/H18) -> 1 | P18: =IF(E18<>"",H18-N18,"") -> 0 | Q18: =IF(E18<>"",P18+N18,"") -> 30000 | R18: =IF(R$16=$K18,$N18,0) -> 30000 | S18: =IF(S$16=$K18,$N18,0) -> 0 | T18: =IF(T$16=$K18,$N18,0) -> 0 | U18: =IF(U$16=$K18,$N18,0) -> 0
D19: 5000 | E19: =IF(F19<>"",E18+1,"") -> 2 | F19: Estação meteorológica | G19: =IF(F19="","","Instrumentos e equipamento científico") -> Instrumentos e equipamento científico | H19: 5000 | I19: 0.2 | J19: 46296 | K19: =+IF(J19<>"",YEAR(J19),"") -> 2026 | L19: 47391 | M19: =IF(AND(J19<>"",L19<>""),(YEAR(L19)-YEAR(J19))*12+MONTH(L19)-MONTH(J19)+1,"") -> 36 | N19: =IF(AND(M19>0,M19<=12),M19*AO26,IF(AND(M19>12,M19<=24),12*AO26+(M19-12)*AP26,IF(AND(M19>24,M19<=36),12*AO26+12*AP26+(M19-24)*AQ26,IF(AND(M19>36,M19<=48),12*AO26+12*AP26+12*AQ26+(M19-36)*AR26,0)))) -> 3920 | O19: =IF(E19="","",N19/H19) -> 0.784 | P19: =IF(E19<>"",H19-N19,"") -> 1080 | Q19: =IF(E19<>"",P19+N19,"") -> 5000 | R19: =IF(R$16=$K19,$N19,0) -> 3920 | S19: =IF(S$16=$K19,$N19,0) -> 0 | T19: =IF(T$16=$K19,$N19,0) -> 0 | U19: =IF(U$16=$K19,$N19,0) -> 0
D20: 1500 | E20: =IF(F20<>"",E19+1,"") -> 3 | F20: sensores de solo (2) | G20: =IF(F20="","","Instrumentos e equipamento científico") -> Instrumentos e equipamento científico | H20: 3000 | I20: 0.2 | J20: 46296 | K20: =+IF(J20<>"",YEAR(J20),"") -> 2026 | L20: 47391 | M20: =IF(AND(J20<>"",L20<>""),(YEAR(L20)-YEAR(J20))*12+MONTH(L20)-MONTH(J20)+1,"") -> 36 | N20: =IF(AND(M20>0,M20<=12),M20*AO29,IF(AND(M20>12,M20<=24),12*AO29+(M20-12)*AP29,IF(AND(M20>24,M20<=36),12*AO29+12*AP29+(M20-24)*AQ29,IF(AND(M20>36,M20<=48),12*AO29+12*AP29+12*AQ29+(M20-36)*AR29,0)))) -> 2352 | O20: =IF(E20="","",N20/H20) -> 0.784 | P20: =IF(E20<>"",H20-N20,"") -> 648 | Q20: =IF(E20<>"",P20+N20,"") -> 3000 | R20: =IF(R$16=$K20,$N20,0) -> 2352 | S20: =IF(S$16=$K20,$N20,0) -> 0 | T20: =IF(T$16=$K20,$N20,0) -> 0 | U20: =IF(U$16=$K20,$N20,0) -> 0 | AB20: Vida útil Standard | AC20: Taxa depreciação | AE20: Período vida útil | AF20: Coeficiente | AH20: Equip. | AI20: Valor aquisição | AJ20: Tx CIBE | AK20: Vida útil | AL20: Coeficiente | AM20: Nova Tx | AN20: Descrição | AO20: 1 | AP20: 2 | AQ20: 3 | AR20: 4 | AS20: 5 | AT20: 6 | AU20: 7 | AV20: 8 | AW20: 9 | AX20: 10 | AY20: 11 | AZ20: 12 | BA20: 13 | BB20: 14 | BC20: 15 | BD20: 16 | BE20: 17 | BF20: 18 | BG20: 19 | BH20: 20 | BI20: Total amort.
D21: 2000 | E21: 3 | F21: Computador (3) | G21: =IF(F21="","","Instrumentos e equipamento científico") -> Instrumentos e equipamento científico | H21: 6000 | I21: 0.25 | J21: 46296 | K21: =+IF(J21<>"",YEAR(J21),"") -> 2026 | L21: 47391 | M21: =IF(AND(J21<>"",L21<>""),(YEAR(L21)-YEAR(J21))*12+MONTH(L21)-MONTH(J21)+1,"") -> 36 | N21: =IF(AND(M21>0,M21<=12),M21*AO32,IF(AND(M21>12,M21<=24),12*AO32+(M21-12)*AP32,IF(AND(M21>24,M21<=36),12*AO32+12*AP32+(M21-24)*AQ32,IF(AND(M21>36,M21<=48),12*AO32+12*AP32+12*AQ32+(M21-36)*AR32,0)))) -> 4828.125 | O21: =IF(E21="","",N21/H21) -> 0.8046875 | P21: =IF(E21<>"",H21-N21,"") -> 1171.875 | Q21: =IF(E21<>"",P21+N21,"") -> 6000 | R21: =IF(R$16=$K21,$N21,0) -> 4828.125 | S21: =IF(S$16=$K21,$N21,0) -> 0 | T21: =IF(T$16=$K21,$N21,0) -> 0 | U21: =IF(U$16=$K21,$N21,0) -> 0 | AB21: 20 | AC21: =100/AB21 -> 5 | AE21: 20 | AF21: 2.5 | AH21: 1 | AI21: =H18 -> 30000 | AJ21: =I18 -> 1 | AK21: =IF(AJ21=0,0,ROUNDUP(100/AJ21/100,2)) -> 1 | AL21: =IF(AND(AK21>=1,AK21<=4),1.5,IF(AND(AK21>4,AK21<=6),2,2.5)) -> 1.5 | AM21: =IF(AJ21=100%,100%,AJ21*AL21) -> 1 | AN21: Quota | AO21: =IF(AK21=0,"",AI21/AK21) -> 30000 | AP21: =IF($AK21-AP$20<0,"",($AI21-$AO22)/($AK21-AO$20)) | AQ21: =IF($AK21-AQ$20<0,"",($AI21-SUM($AO22:AP22))/($AK21-AP$20)) | AR21: =IF($AK21-AR$20<0,"",($AI21-SUM($AO22:AQ22))/($AK21-AQ$20)) | AS21: =IF($AK21-AS$20<0,"",($AI21-SUM($AO22:AR22))/($AK21-AR$20)) | AT21: =IF($AK21-AT$20<0,"",($AI21-SUM($AO22:AS22))/($AK21-AS$20)) | AU21: =IF($AK21-AU$20<0,"",($AI21-SUM($AO22:AT22))/($AK21-AT$20)) | AV21: =IF($AK21-AV$20<0,"",($AI21-SUM($AO22:AU22))/($AK21-AU$20)) | AW21: =IF($AK21-AW$20<0,"",($AI21-SUM($AO22:AV22))/($AK21-AV$20)) | AX21: =IF($AK21-AX$20<0,"",($AI21-SUM($AO22:AW22))/($AK21-AW$20)) | ... BH21: =IF($AK21-BH$20<0,"",($AI21-SUM($AO22:BG22))/($AK21-BG$20))
D22: 11000 | E22: =IF(F22<>"",E21+1,"") -> 4 | F22: Arca -80º | G22: =IF(F22="","","Instrumentos e equipamento científico") -> Instrumentos e equipamento científico | H22: 12000 | I22: 0.2 | J22: 46296 | K22: =+IF(J22<>"",YEAR(J22),"") -> 2026 | L22: 47391 | M22: =IF(AND(J22<>"",L22<>""),(YEAR(L22)-YEAR(J22))*12+MONTH(L22)-MONTH(J22)+1,"") -> 36 | N22: =IF(AND(M22>0,M22<=12),M22*AO35,IF(AND(M22>12,M22<=24),12*AO35+(M22-12)*AP35,IF(AND(M22>24,M22<=36),12*AO35+12*AP35+(M22-24)*AQ35,IF(AND(M22>36,M22<=48),12*AO35+12*AP35+12*AQ35+(M22-36)*AR35,0)))) -> 9408 | O22: =IF(E22="","",N22/H22) -> 0.784 | P22: =IF(E22<>"",H22-N22,"") -> 2592 | Q22: =IF(E22<>"",P22+N22,"") -> 12000 | R22: =IF(R$16=$K22,$N22,0) -> 9408 | S22: =IF(S$16=$K22,$N22,0) -> 0 | T22: =IF(T$16=$K22,$N22,0) -> 0 | U22: =IF(U$16=$K22,$N22,0) -> 0 | AB22: 16 | AC22: =100/AB22 -> 6.25 | AE22: 16 | AF22: 2.5 | AN22: Amort/ano | AO22: =IF(AO$20<=$AK21,AI21*AM21,0) -> 30000 | AP22: =IF(AP$20<=$AK21,IF(($AI21-$AO22)*$AM21<AP21,AP21,(AI21-AO22)*AM21),0) -> 0 | AQ22: =IF(AQ$20<=$AK21,IF(($AI21-SUM($AO22:AP22))*$AM21<AQ21,AQ21,(($AI21-SUM($AO22:AP22))*$AM21)),0) -> 0 | AR22: =IF(AR$20<=$AK21,IF(($AI21-SUM($AO22:AQ22))*$AM21<AR21,AR21,(($AI21-SUM($AO22:AQ22))*$AM21)),0) -> 0 | AS22: =IF(AS$20<=$AK21,IF(($AI21-SUM($AO22:AR22))*$AM21<AS21,AS21,(($AI21-SUM($AO22:AR22))*$AM21)),0) -> 0 | AT22: =IF(AT$20<=$AK21,IF(($AI21-SUM($AO22:AS22))*$AM21<AT21,AT21,(($AI21-SUM($AO22:AS22))*$AM21)),0) -> 0 | AU22: =IF(AU$20<=$AK21,IF(($AI21-SUM($AO22:AT22))*$AM21<AU21,AU21,(($AI21-SUM($AO22:AT22))*$AM21)),0) -> 0 | AV22: =IF(AV$20<=$AK21,IF(($AI21-SUM($AO22:AU22))*$AM21<AV21,AV21,(($AI21-SUM($AO22:AU22))*$AM21)),0) -> 0 | AW22: =IF(AW$20<=$AK21,IF(($AI21-SUM($AO22:AV22))*$AM21<AW21,AW21,(($AI21-SUM($AO22:AV22))*$AM21)),0) -> 0 | AX22: =IF(AX$20<=$AK21,IF(($AI21-SUM($AO22:AW22))*$AM21<AX21,AX21,(($AI21-SUM($AO22:AW22))*$AM21)),0) -> 0 | ... BH22: =IF(BH$20<=$AK21,IF(($AI21-SUM($AO22:BG22))*$AM21<BH21,BH21,(($AI21-SUM($AO22:BG22))*$AM21)),0) -> 0 | BI22: =SUM(AO22:BH22) -> 30000
E23: =IF(F23<>"",E22+1,"") | G23: =IF(F23="","","Instrumentos e equipamento científico") | K23: =+IF(J23<>"",YEAR(J23),"") | M23: =IF(AND(J23<>"",L23<>""),(YEAR(L23)-YEAR(J23))*12+MONTH(L23)-MONTH(J23)+1,"") | N23: =IF(AND(M23>0,M23<=12),M23*AO38,IF(AND(M23>12,M23<=24),12*AO38+(M23-12)*AP38,IF(AND(M23>24,M23<=36),12*AO38+12*AP38+(M23-24)*AQ38,IF(AND(M23>36,M23<=48),12*AO38+12*AP38+12*AQ38+(M23-36)*AR38,0)))) -> 0 | O23: =IF(E23="","",N23/H23) | P23: =IF(E23<>"",H23-N23,"") | Q23: =IF(E23<>"",P23+N23,"") | R23: =IF(R$16=$K23,$N23,0) -> 0 | S23: =IF(S$16=$K23,$N23,0) -> 0 | T23: =IF(T$16=$K23,$N23,0) -> 0 | U23: =IF(U$16=$K23,$N23,0) -> 0 | AB23: 14 | AC23: =100/AB23 -> 7.1428571 | AE23: 14 | AF23: 2.5 | AN23: Amort/mês | AO23: =AO22/12 -> 2500 | AP23: =AP22/12 -> 0 | AQ23: =AQ22/12 -> 0 | AR23: =AR22/12 -> 0 | AS23: =AS22/12 -> 0 | AT23: =AT22/12 -> 0 | AU23: =AU22/12 -> 0 | AV23: =AV22/12 -> 0 | ... BH23: =BH22/12 -> 0
E24: =IF(F24<>"",E23+1,"") | G24: =IF(F24="","","Instrumentos e equipamento científico") | K24: =+IF(J24<>"",YEAR(J24),"") | M24: =IF(AND(J24<>"",L24<>""),(YEAR(L24)-YEAR(J24))*12+MONTH(L24)-MONTH(J24)+1,"") | N24: =IF(AND(M24>0,M24<=12),M24*AO41,IF(AND(M24>12,M24<=24),12*AO41+(M24-12)*AP41,IF(AND(M24>24,M24<=36),12*AO41+12*AP41+(M24-24)*AQ41,IF(AND(M24>36,M24<=48),12*AO41+12*AP41+12*AQ41+(M24-36)*AR41,0)))) -> 0 | O24: =IF(E24="","",N24/H24) | P24: =IF(E24<>"",H24-N24,"") | Q24: =IF(E24<>"",P24+N24,"") | R24: =IF(R$16=$K24,$N24,0) -> 0 | S24: =IF(S$16=$K24,$N24,0) -> 0 | T24: =IF(T$16=$K24,$N24,0) -> 0 | U24: =IF(U$16=$K24,$N24,0) -> 0 | AB24: 13 | AC24: =100/AB24 -> 7.6923077 | AE24: 12 | AF24: 2.5 | AH24: 2 | AI24: =H19 -> 5000 | AJ24: =I19 -> 0.2 | AK24: =IF(AJ24=0,0,ROUNDUP(100/AJ24/100,2)) -> 5 | AL24: =IF(AND(AK24>=1,AK24<=4),1.5,IF(AND(AK24>4,AK24<=6),2,2.5)) -> 2 | AM24: =IF(AJ24=100%,100%,AJ24*AL24) -> 0.4 | AN24: Quota | AO24: =IF(AK24=0,"",AI24/AK24) -> 1000 | AP24: =IF($AK24-AP$20<0,"",($AI24-$AO25)/($AK24-AO$20)) -> 750 | AQ24: =IF($AK24-AQ$20<0,"",($AI24-SUM($AO25:AP25))/($AK24-AP$20)) -> 600 | AR24: =IF($AK24-AR$20<0,"",($AI24-SUM($AO25:AQ25))/($AK24-AQ$20)) -> 540 | AS24: =IF($AK24-AS$20<0,"",($AI24-SUM($AO25:AR25))/($AK24-AR$20)) -> 540 | AT24: =IF($AK24-AT$20<0,"",($AI24-SUM($AO25:AS25))/($AK24-AS$20)) | AU24: =IF($AK24-AU$20<0,"",($AI24-SUM($AO25:AT25))/($AK24-AT$20)) | AV24: =IF($AK24-AV$20<0,"",($AI24-SUM($AO25:AU25))/($AK24-AU$20)) | AW24: =IF($AK24-AW$20<0,"",($AI24-SUM($AO25:AV25))/($AK24-AV$20)) | AX24: =IF($AK24-AX$20<0,"",($AI24-SUM($AO25:AW25))/($AK24-AW$20)) | ... BH24: =IF($AK24-BH$20<0,"",($AI24-SUM($AO25:BG25))/($AK24-BG$20))
E25: =IF(F25<>"",E24+1,"") | G25: =IF(F25="","","Instrumentos e equipamento científico") | K25: =+IF(J25<>"",YEAR(J25),"") | M25: =IF(AND(J25<>"",L25<>""),(YEAR(L25)-YEAR(J25))*12+MONTH(L25)-MONTH(J25)+1,"") | N25: =IF(AND(M25>0,M25<=12),M25*AO44,IF(AND(M25>12,M25<=24),12*AO44+(M25-12)*AP44,IF(AND(M25>24,M25<=36),12*AO44+12*AP44+(M25-24)*AQ44,IF(AND(M25>36,M25<=48),12*AO44+12*AP44+12*AQ44+(M25-36)*AR44,0)))) -> 0 | O25: =IF(E25="","",N25/H25) | P25: =IF(E25<>"",H25-N25,"") | Q25: =IF(E25<>"",P25+N25,"") | R25: =IF(R$16=$K25,$N25,0) -> 0 | S25: =IF(S$16=$K25,$N25,0) -> 0 | T25: =IF(T$16=$K25,$N25,0) -> 0 | U25: =IF(U$16=$K25,$N25,0) -> 0 | AB25: 12 | AC25: =100/AB25 -> 8.3333333 | AE25: 10 | AF25: 2.5 | AN25: Amort/ano | AO25: =IF(AO$20<=$AK24,AI24*AM24,0) -> 2000 | AP25: =IF(AP$20<=$AK24,IF(($AI24-$AO25)*$AM24<AP24,AP24,(AI24-AO25)*AM24),0) -> 1200 | AQ25: =IF(AQ$20<=$AK24,IF(($AI24-SUM($AO25:AP25))*$AM24<AQ24,AQ24,(($AI24-SUM($AO25:AP25))*$AM24)),0) -> 720 | AR25: =IF(AR$20<=$AK24,IF(($AI24-SUM($AO25:AQ25))*$AM24<AR24,AR24,(($AI24-SUM($AO25:AQ25))*$AM24)),0) -> 540 | AS25: =IF(AS$20<=$AK24,IF(($AI24-SUM($AO25:AR25))*$AM24<AS24,AS24,(($AI24-SUM($AO25:AR25))*$AM24)),0) -> 540 | AT25: =IF(AT$20<=$AK24,IF(($AI24-SUM($AO25:AS25))*$AM24<AT24,AT24,(($AI24-SUM($AO25:AS25))*$AM24)),0) -> 0 | AU25: =IF(AU$20<=$AK24,IF(($AI24-SUM($AO25:AT25))*$AM24<AU24,AU24,(($AI24-SUM($AO25:AT25))*$AM24)),0) -> 0 | AV25: =IF(AV$20<=$AK24,IF(($AI24-SUM($AO25:AU25))*$AM24<AV24,AV24,(($AI24-SUM($AO25:AU25))*$AM24)),0) -> 0 | AW25: =IF(AW$20<=$AK24,IF(($AI24-SUM($AO25:AV25))*$AM24<AW24,AW24,(($AI24-SUM($AO25:AV25))*$AM24)),0) -> 0 | AX25: =IF(AX$20<=$AK24,IF(($AI24-SUM($AO25:AW25))*$AM24<AX24,AX24,(($AI24-SUM($AO25:AW25))*$AM24)),0) -> 0 | ... BH25: =IF(BH$20<=$AK24,IF(($AI24-SUM($AO25:BG25))*$AM24<BH24,BH24,(($AI24-SUM($AO25:BG25))*$AM24)),0) -> 0 | BI25: =SUM(AO25:BH25) -> 5000
E26: =IF(F26<>"",E25+1,"") | G26: =IF(F26="","","Instrumentos e equipamento científico") | K26: =+IF(J26<>"",YEAR(J26),"") | M26: =IF(AND(J26<>"",L26<>""),(YEAR(L26)-YEAR(J26))*12+MONTH(L26)-MONTH(J26)+1,"") | N26: =IF(AND(M26>0,M26<=12),M26*AO47,IF(AND(M26>12,M26<=24),12*AO47+(M26-12)*AP47,IF(AND(M26>24,M26<=36),12*AO47+12*AP47+(M26-24)*AQ47,IF(AND(M26>36,M26<=48),12*AO47+12*AP47+12*AQ47+(M26-36)*AR47,0)))) -> 0 | O26: =IF(E26="","",N26/H26) | P26: =IF(E26<>"",H26-N26,"") | Q26: =IF(E26<>"",P26+N26,"") | R26: =IF(R$16=$K26,$N26,0) -> 0 | S26: =IF(S$16=$K26,$N26,0) -> 0 | T26: =IF(T$16=$K26,$N26,0) -> 0 | U26: =IF(U$16=$K26,$N26,0) -> 0 | AB26: 10 | AC26: =100/AB26 -> 10 | AE26: 8 | AF26: 2.5 | AN26: Amort/mês | AO26: =AO25/12 -> 166.66667 | AP26: =AP25/12 -> 100 | AQ26: =AQ25/12 -> 60 | AR26: =AR25/12 -> 45 | AS26: =AS25/12 -> 45 | AT26: =AT25/12 -> 0 | AU26: =AU25/12 -> 0 | AV26: =AV25/12 -> 0 | ... BH26: =BH25/12 -> 0
E27: =IF(F27<>"",E26+1,"") | G27: =IF(F27="","","Instrumentos e equipamento científico") | K27: =+IF(J27<>"",YEAR(J27),"") | M27: =IF(AND(J27<>"",L27<>""),(YEAR(L27)-YEAR(J27))*12+MONTH(L27)-MONTH(J27)+1,"") | N27: =IF(AND(M27>0,M27<=12),M27*AO50,IF(AND(M27>12,M27<=24),12*AO50+(M27-12)*AP50,IF(AND(M27>24,M27<=36),12*AO50+12*AP50+(M27-24)*AQ50,IF(AND(M27>36,M27<=48),12*AO50+12*AP50+12*AQ50+(M27-36)*AR50,0)))) -> 0 | O27: =IF(E27="","",N27/H27) | P27: =IF(E27<>"",H27-N27,"") | Q27: =IF(E27<>"",P27+N27,"") | R27: =IF(R$16=$K27,$N27,0) -> 0 | S27: =IF(S$16=$K27,$N27,0) -> 0 | T27: =IF(T$16=$K27,$N27,0) -> 0 | U27: =IF(U$16=$K27,$N27,0) -> 0 | AB27: 8 | AC27: =100/AB27 -> 12.5 | AE27: 7 | AF27: 2.5 | AH27: 3 | AI27: =H20 -> 3000 | AJ27: =I20 -> 0.2 | AK27: =IF(AJ27=0,0,ROUNDUP(100/AJ27/100,2)) -> 5 | AL27: =IF(AND(AK27>=1,AK27<=4),1.5,IF(AND(AK27>4,AK27<=6),2,2.5)) -> 2 | AM27: =IF(AJ27=100%,100%,AJ27*AL27) -> 0.4 | AN27: Quota | AO27: =IF(AK27=0,"",AI27/AK27) -> 600 | AP27: =IF($AK27-AP$20<0,"",($AI27-$AO28)/($AK27-AO$20)) -> 450 | AQ27: =IF($AK27-AQ$20<0,"",($AI27-SUM($AO28:AP28))/($AK27-AP$20)) -> 360 | AR27: =IF($AK27-AR$20<0,"",($AI27-SUM($AO28:AQ28))/($AK27-AQ$20)) -> 324 | AS27: =IF($AK27-AS$20<0,"",($AI27-SUM($AO28:AR28))/($AK27-AR$20)) -> 324 | AT27: =IF($AK27-AT$20<0,"",($AI27-SUM($AO28:AS28))/($AK27-AS$20)) | AU27: =IF($AK27-AU$20<0,"",($AI27-SUM($AO28:AT28))/($AK27-AT$20)) | AV27: =IF($AK27-AV$20<0,"",($AI27-SUM($AO28:AU28))/($AK27-AU$20)) | AW27: =IF($AK27-AW$20<0,"",($AI27-SUM($AO28:AV28))/($AK27-AV$20)) | AX27: =IF($AK27-AX$20<0,"",($AI27-SUM($AO28:AW28))/($AK27-AW$20)) | ... BH27: =IF($AK27-BH$20<0,"",($AI27-SUM($AO28:BG28))/($AK27-BG$20))
E28: =IF(F28<>"",E27+1,"") | G28: =IF(F28="","","Instrumentos e equipamento científico") | K28: =+IF(J28<>"",YEAR(J28),"") | M28: =IF(AND(J28<>"",L28<>""),(YEAR(L28)-YEAR(J28))*12+MONTH(L28)-MONTH(J28)+1,"") | N28: =IF(AND(M28>0,M28<=12),M28*AO53,IF(AND(M28>12,M28<=24),12*AO53+(M28-12)*AP53,IF(AND(M28>24,M28<=36),12*AO53+12*AP53+(M28-24)*AQ53,IF(AND(M28>36,M28<=48),12*AO53+12*AP53+12*AQ53+(M28-36)*AR53,0)))) -> 0 | O28: =IF(E28="","",N28/H28) | P28: =IF(E28<>"",H28-N28,"") | Q28: =IF(E28<>"",P28+N28,"") | R28: =IF(R$16=$K28,$N28,0) -> 0 | S28: =IF(S$16=$K28,$N28,0) -> 0 | T28: =IF(T$16=$K28,$N28,0) -> 0 | U28: =IF(U$16=$K28,$N28,0) -> 0 | AB28: 7 | AC28: =100/AB28 -> 14.285714 | AE28: 6 | AF28: 2 | AN28: Amort/ano | AO28: =IF(AO$20<=$AK27,AI27*AM27,0) -> 1200 | AP28: =IF(AP$20<=$AK27,IF(($AI27-$AO28)*$AM27<AP27,AP27,(AI27-AO28)*AM27),0) -> 720 | AQ28: =IF(AQ$20<=$AK27,IF(($AI27-SUM($AO28:AP28))*$AM27<AQ27,AQ27,(($AI27-SUM($AO28:AP28))*$AM27)),0) -> 432 | AR28: =IF(AR$20<=$AK27,IF(($AI27-SUM($AO28:AQ28))*$AM27<AR27,AR27,(($AI27-SUM($AO28:AQ28))*$AM27)),0) -> 324 | AS28: =IF(AS$20<=$AK27,IF(($AI27-SUM($AO28:AR28))*$AM27<AS27,AS27,(($AI27-SUM($AO28:AR28))*$AM27)),0) -> 324 | AT28: =IF(AT$20<=$AK27,IF(($AI27-SUM($AO28:AS28))*$AM27<AT27,AT27,(($AI27-SUM($AO28:AS28))*$AM27)),0) -> 0 | AU28: =IF(AU$20<=$AK27,IF(($AI27-SUM($AO28:AT28))*$AM27<AU27,AU27,(($AI27-SUM($AO28:AT28))*$AM27)),0) -> 0 | AV28: =IF(AV$20<=$AK27,IF(($AI27-SUM($AO28:AU28))*$AM27<AV27,AV27,(($AI27-SUM($AO28:AU28))*$AM27)),0) -> 0 | AW28: =IF(AW$20<=$AK27,IF(($AI27-SUM($AO28:AV28))*$AM27<AW27,AW27,(($AI27-SUM($AO28:AV28))*$AM27)),0) -> 0 | AX28: =IF(AX$20<=$AK27,IF(($AI27-SUM($AO28:AW28))*$AM27<AX27,AX27,(($AI27-SUM($AO28:AW28))*$AM27)),0) -> 0 | ... BH28: =IF(BH$20<=$AK27,IF(($AI27-SUM($AO28:BG28))*$AM27<BH27,BH27,(($AI27-SUM($AO28:BG28))*$AM27)),0) -> 0 | BI28: =SUM(AO28:BH28) -> 3000
E29: =IF(F29<>"",E28+1,"") | G29: =IF(F29="","","Instrumentos e equipamento científico") | K29: =+IF(J29<>"",YEAR(J29),"") | M29: =IF(AND(J29<>"",L29<>""),(YEAR(L29)-YEAR(J29))*12+MONTH(L29)-MONTH(J29)+1,"") | N29: =IF(AND(M29>0,M29<=12),M29*AO56,IF(AND(M29>12,M29<=24),12*AO56+(M29-12)*AP56,IF(AND(M29>24,M29<=36),12*AO56+12*AP56+(M29-24)*AQ56,IF(AND(M29>36,M29<=48),12*AO56+12*AP56+12*AQ56+(M29-36)*AR56,0)))) -> 0 | O29: =IF(E29="","",N29/H29) | P29: =IF(E29<>"",H29-N29,"") | Q29: =IF(E29<>"",P29+N29,"") | R29: =IF(R$16=$K29,$N29,0) -> 0 | S29: =IF(S$16=$K29,$N29,0) -> 0 | T29: =IF(T$16=$K29,$N29,0) -> 0 | U29: =IF(U$16=$K29,$N29,0) -> 0 | AB29: 6 | AC29: =100/AB29 -> 16.666667 | AE29: 5 | AF29: 2 | AN29: Amort/mês | AO29: =AO28/12 -> 100 | AP29: =AP28/12 -> 60 | AQ29: =AQ28/12 -> 36 | AR29: =AR28/12 -> 27 | AS29: =AS28/12 -> 27 | AT29: =AT28/12 -> 0 | AU29: =AU28/12 -> 0 | AV29: =AV28/12 -> 0 | ... BH29: =BH28/12 -> 0
E30: =IF(F30<>"",E29+1,"") | G30: =IF(F30="","","Instrumentos e equipamento científico") | K30: =+IF(J30<>"",YEAR(J30),"") | M30: =IF(AND(J30<>"",L30<>""),(YEAR(L30)-YEAR(J30))*12+MONTH(L30)-MONTH(J30)+1,"") | N30: =IF(AND(M30>0,M30<=12),M30*AO59,IF(AND(M30>12,M30<=24),12*AO59+(M30-12)*AP59,IF(AND(M30>24,M30<=36),12*AO59+12*AP59+(M30-24)*AQ59,IF(AND(M30>36,M30<=48),12*AO59+12*AP59+12*AQ59+(M30-36)*AR59,0)))) -> 0 | O30: =IF(E30="","",N30/H30) | P30: =IF(E30<>"",H30-N30,"") | Q30: =IF(E30<>"",P30+N30,"") | R30: =IF(R$16=$K30,$N30,0) -> 0 | S30: =IF(S$16=$K30,$N30,0) -> 0 | T30: =IF(T$16=$K30,$N30,0) -> 0 | U30: =IF(U$16=$K30,$N30,0) -> 0 | AB30: 5 | AC30: =100/AB30 -> 20 | AE30: 4 | AF30: 1.5 | AH30: 4 | AI30: =H21 -> 6000 | AJ30: =I21 -> 0.25 | AK30: =IF(AJ30=0,0,ROUNDUP(100/AJ30/100,2)) -> 4 | AL30: =IF(AND(AK30>=1,AK30<=4),1.5,IF(AND(AK30>4,AK30<=6),2,2.5)) -> 1.5 | AM30: =IF(AJ30=100%,100%,AJ30*AL30) -> 0.375 | AN30: Quota | AO30: =IF(AK30=0,"",AI30/AK30) -> 1500 | AP30: =IF($AK30-AP$20<0,"",($AI30-$AO31)/($AK30-AO$20)) -> 1250 | AQ30: =IF($AK30-AQ$20<0,"",($AI30-SUM($AO31:AP31))/($AK30-AP$20)) -> 1171.875 | AR30: =IF($AK30-AR$20<0,"",($AI30-SUM($AO31:AQ31))/($AK30-AQ$20)) -> 1171.875 | AS30: =IF($AK30-AS$20<0,"",($AI30-SUM($AO31:AR31))/($AK30-AR$20)) | AT30: =IF($AK30-AT$20<0,"",($AI30-SUM($AO31:AS31))/($AK30-AS$20)) | AU30: =IF($AK30-AU$20<0,"",($AI30-SUM($AO31:AT31))/($AK30-AT$20)) | AV30: =IF($AK30-AV$20<0,"",($AI30-SUM($AO31:AU31))/($AK30-AU$20)) | AW30: =IF($AK30-AW$20<0,"",($AI30-SUM($AO31:AV31))/($AK30-AV$20)) | AX30: =IF($AK30-AX$20<0,"",($AI30-SUM($AO31:AW31))/($AK30-AW$20)) | ... BH30: =IF($AK30-BH$20<0,"",($AI30-SUM($AO31:BG31))/($AK30-BG$20))
E31: =IF(F31<>"",E30+1,"") | G31: =IF(F31="","","Instrumentos e equipamento científico") | K31: =+IF(J31<>"",YEAR(J31),"") | M31: =IF(AND(J31<>"",L31<>""),(YEAR(L31)-YEAR(J31))*12+MONTH(L31)-MONTH(J31)+1,"") | N31: =IF(AND(M31>0,M31<=12),M31*AO62,IF(AND(M31>12,M31<=24),12*AO62+(M31-12)*AP62,IF(AND(M31>24,M31<=36),12*AO62+12*AP62+(M31-24)*AQ62,IF(AND(M31>36,M31<=48),12*AO62+12*AP62+12*AQ62+(M31-36)*AR62,0)))) -> 0 | O31: =IF(E31="","",N31/H31) | P31: =IF(E31<>"",H31-N31,"") | Q31: =IF(E31<>"",P31+N31,"") | R31: =IF(R$16=$K31,$N31,0) -> 0 | S31: =IF(S$16=$K31,$N31,0) -> 0 | T31: =IF(T$16=$K31,$N31,0) -> 0 | U31: =IF(U$16=$K31,$N31,0) -> 0 | AB31: 4 | AC31: =100/AB31 -> 25 | AE31: 3 | AF31: 1.5 | AN31: Amort/ano | AO31: =IF(AO$20<=$AK30,AI30*AM30,0) -> 2250 | AP31: =IF(AP$20<=$AK30,IF(($AI30-$AO31)*$AM30<AP30,AP30,(AI30-AO31)*AM30),0) -> 1406.25 | AQ31: =IF(AQ$20<=$AK30,IF(($AI30-SUM($AO31:AP31))*$AM30<AQ30,AQ30,(($AI30-SUM($AO31:AP31))*$AM30)),0) -> 1171.875 | AR31: =IF(AR$20<=$AK30,IF(($AI30-SUM($AO31:AQ31))*$AM30<AR30,AR30,(($AI30-SUM($AO31:AQ31))*$AM30)),0) -> 1171.875 | AS31: =IF(AS$20<=$AK30,IF(($AI30-SUM($AO31:AR31))*$AM30<AS30,AS30,(($AI30-SUM($AO31:AR31))*$AM30)),0) -> 0 | AT31: =IF(AT$20<=$AK30,IF(($AI30-SUM($AO31:AS31))*$AM30<AT30,AT30,(($AI30-SUM($AO31:AS31))*$AM30)),0) -> 0 | AU31: =IF(AU$20<=$AK30,IF(($AI30-SUM($AO31:AT31))*$AM30<AU30,AU30,(($AI30-SUM($AO31:AT31))*$AM30)),0) -> 0 | AV31: =IF(AV$20<=$AK30,IF(($AI30-SUM($AO31:AU31))*$AM30<AV30,AV30,(($AI30-SUM($AO31:AU31))*$AM30)),0) -> 0 | AW31: =IF(AW$20<=$AK30,IF(($AI30-SUM($AO31:AV31))*$AM30<AW30,AW30,(($AI30-SUM($AO31:AV31))*$AM30)),0) -> 0 | AX31: =IF(AX$20<=$AK30,IF(($AI30-SUM($AO31:AW31))*$AM30<AX30,AX30,(($AI30-SUM($AO31:AW31))*$AM30)),0) -> 0 | ... BH31: =IF(BH$20<=$AK30,IF(($AI30-SUM($AO31:BG31))*$AM30<BH30,BH30,(($AI30-SUM($AO31:BG31))*$AM30)),0) -> 0 | BI31: =SUM(AO31:BH31) -> 6000
E32: =IF(F32<>"",E31+1,"") | G32: =IF(F32="","","Instrumentos e equipamento científico") | K32: =+IF(J32<>"",YEAR(J32),"") | M32: =IF(AND(J32<>"",L32<>""),(YEAR(L32)-YEAR(J32))*12+MONTH(L32)-MONTH(J32)+1,"") | N32: =IF(AND(M32>0,M32<=12),M32*AO65,IF(AND(M32>12,M32<=24),12*AO65+(M32-12)*AP65,IF(AND(M32>24,M32<=36),12*AO65+12*AP65+(M32-24)*AQ65,IF(AND(M32>36,M32<=48),12*AO65+12*AP65+12*AQ65+(M32-36)*AR65,0)))) -> 0 | O32: =IF(E32="","",N32/H32) | P32: =IF(E32<>"",H32-N32,"") | Q32: =IF(E32<>"",P32+N32,"") | R32: =IF(R$16=$K32,$N32,0) -> 0 | S32: =IF(S$16=$K32,$N32,0) -> 0 | T32: =IF(T$16=$K32,$N32,0) -> 0 | U32: =IF(U$16=$K32,$N32,0) -> 0 | AB32: 3 | AC32: =100/AB32 -> 33.333333 | AE32: 2 | AF32: 1.5 | AN32: Amort/mês | AO32: =AO31/12 -> 187.5 | AP32: =AP31/12 -> 117.1875 | AQ32: =AQ31/12 -> 97.65625 | AR32: =AR31/12 -> 97.65625 | AS32: =AS31/12 -> 0 | AT32: =AT31/12 -> 0 | AU32: =AU31/12 -> 0 | AV32: =AV31/12 -> 0 | ... BH32: =BH31/12 -> 0
E33: =IF(F33<>"",E32+1,"") | G33: =IF(F33="","","Instrumentos e equipamento científico") | K33: =+IF(J33<>"",YEAR(J33),"") | M33: =IF(AND(J33<>"",L33<>""),(YEAR(L33)-YEAR(J33))*12+MONTH(L33)-MONTH(J33)+1,"") | N33: =IF(AND(M33>0,M33<=12),M33*AO68,IF(AND(M33>12,M33<=24),12*AO68+(M33-12)*AP68,IF(AND(M33>24,M33<=36),12*AO68+12*AP68+(M33-24)*AQ68,IF(AND(M33>36,M33<=48),12*AO68+12*AP68+12*AQ68+(M33-36)*AR68,0)))) -> 0 | O33: =IF(E33="","",N33/H33) | P33: =IF(E33<>"",H33-N33,"") | Q33: =IF(E33<>"",P33+N33,"") | R33: =IF(R$16=$K33,$N33,0) -> 0 | S33: =IF(S$16=$K33,$N33,0) -> 0 | T33: =IF(T$16=$K33,$N33,0) -> 0 | U33: =IF(U$16=$K33,$N33,0) -> 0 | AB33: 2 | AC33: =100/AB33 -> 50 | AE33: 1 | AF33: 1.5 | AH33: 5 | AI33: =H22 -> 12000 | AJ33: =I22 -> 0.2 | AK33: =IF(AJ33=0,0,ROUNDUP(100/AJ33/100,2)) -> 5 | AL33: =IF(AND(AK33>=1,AK33<=4),1.5,IF(AND(AK33>4,AK33<=6),2,2.5)) -> 2 | AM33: =IF(AJ33=100%,100%,AJ33*AL33) -> 0.4 | AN33: Quota | AO33: =IF(AK33=0,"",AI33/AK33) -> 2400 | AP33: =IF($AK33-AP$20<0,"",($AI33-$AO34)/($AK33-AO$20)) -> 1800 | AQ33: =IF($AK33-AQ$20<0,"",($AI33-SUM($AO34:AP34))/($AK33-AP$20)) -> 1440 | AR33: =IF($AK33-AR$20<0,"",($AI33-SUM($AO34:AQ34))/($AK33-AQ$20)) -> 1296 | AS33: =IF($AK33-AS$20<0,"",($AI33-SUM($AO34:AR34))/($AK33-AR$20)) -> 1296 | AT33: =IF($AK33-AT$20<0,"",($AI33-SUM($AO34:AS34))/($AK33-AS$20)) | AU33: =IF($AK33-AU$20<0,"",($AI33-SUM($AO34:AT34))/($AK33-AT$20)) | AV33: =IF($AK33-AV$20<0,"",($AI33-SUM($AO34:AU34))/($AK33-AU$20)) | AW33: =IF($AK33-AW$20<0,"",($AI33-SUM($AO34:AV34))/($AK33-AV$20)) | AX33: =IF($AK33-AX$20<0,"",($AI33-SUM($AO34:AW34))/($AK33-AW$20)) | ... BH33: =IF($AK33-BH$20<0,"",($AI33-SUM($AO34:BG34))/($AK33-BG$20))
E34: =IF(F34<>"",E33+1,"") | G34: =IF(F34="","","Instrumentos e equipamento científico") | K34: =+IF(J34<>"",YEAR(J34),"") | M34: =IF(AND(J34<>"",L34<>""),(YEAR(L34)-YEAR(J34))*12+MONTH(L34)-MONTH(J34)+1,"") | N34: =IF(AND(M34>0,M34<=12),M34*AO71,IF(AND(M34>12,M34<=24),12*AO71+(M34-12)*AP71,IF(AND(M34>24,M34<=36),12*AO71+12*AP71+(M34-24)*AQ71,IF(AND(M34>36,M34<=48),12*AO71+12*AP71+12*AQ71+(M34-36)*AR71,0)))) -> 0 | O34: =IF(E34="","",N34/H34) | P34: =IF(E34<>"",H34-N34,"") | Q34: =IF(E34<>"",P34+N34,"") | R34: =IF(R$16=$K34,$N34,0) -> 0 | S34: =IF(S$16=$K34,$N34,0) -> 0 | T34: =IF(T$16=$K34,$N34,0) -> 0 | U34: =IF(U$16=$K34,$N34,0) -> 0 | AN34: Amort/ano | AO34: =IF(AO$20<=$AK33,AI33*AM33,0) -> 4800 | AP34: =IF(AP$20<=$AK33,IF(($AI33-$AO34)*$AM33<AP33,AP33,(AI33-AO34)*AM33),0) -> 2880 | AQ34: =IF(AQ$20<=$AK33,IF(($AI33-SUM($AO34:AP34))*$AM33<AQ33,AQ33,(($AI33-SUM($AO34:AP34))*$AM33)),0) -> 1728 | AR34: =IF(AR$20<=$AK33,IF(($AI33-SUM($AO34:AQ34))*$AM33<AR33,AR33,(($AI33-SUM($AO34:AQ34))*$AM33)),0) -> 1296 | AS34: =IF(AS$20<=$AK33,IF(($AI33-SUM($AO34:AR34))*$AM33<AS33,AS33,(($AI33-SUM($AO34:AR34))*$AM33)),0) -> 1296 | AT34: =IF(AT$20<=$AK33,IF(($AI33-SUM($AO34:AS34))*$AM33<AT33,AT33,(($AI33-SUM($AO34:AS34))*$AM33)),0) -> 0 | AU34: =IF(AU$20<=$AK33,IF(($AI33-SUM($AO34:AT34))*$AM33<AU33,AU33,(($AI33-SUM($AO34:AT34))*$AM33)),0) -> 0 | AV34: =IF(AV$20<=$AK33,IF(($AI33-SUM($AO34:AU34))*$AM33<AV33,AV33,(($AI33-SUM($AO34:AU34))*$AM33)),0) -> 0 | AW34: =IF(AW$20<=$AK33,IF(($AI33-SUM($AO34:AV34))*$AM33<AW33,AW33,(($AI33-SUM($AO34:AV34))*$AM33)),0) -> 0 | AX34: =IF(AX$20<=$AK33,IF(($AI33-SUM($AO34:AW34))*$AM33<AX33,AX33,(($AI33-SUM($AO34:AW34))*$AM33)),0) -> 0 | ... BH34: =IF(BH$20<=$AK33,IF(($AI33-SUM($AO34:BG34))*$AM33<BH33,BH33,(($AI33-SUM($AO34:BG34))*$AM33)),0) -> 0 | BI34: =SUM(AO34:BH34) -> 12000
E35: =IF(F35<>"",E34+1,"") | G35: =IF(F35="","","Instrumentos e equipamento científico") | K35: =+IF(J35<>"",YEAR(J35),"") | M35: =IF(AND(J35<>"",L35<>""),(YEAR(L35)-YEAR(J35))*12+MONTH(L35)-MONTH(J35)+1,"") | N35: =IF(AND(M35>0,M35<=12),M35*AO74,IF(AND(M35>12,M35<=24),12*AO74+(M35-12)*AP74,IF(AND(M35>24,M35<=36),12*AO74+12*AP74+(M35-24)*AQ74,IF(AND(M35>36,M35<=48),12*AO74+12*AP74+12*AQ74+(M35-36)*AR74,0)))) -> 0 | O35: =IF(E35="","",N35/H35) | P35: =IF(E35<>"",H35-N35,"") | Q35: =IF(E35<>"",P35+N35,"") | R35: =IF(R$16=$K35,$N35,0) -> 0 | S35: =IF(S$16=$K35,$N35,0) -> 0 | T35: =IF(T$16=$K35,$N35,0) -> 0 | U35: =IF(U$16=$K35,$N35,0) -> 0 | AN35: Amort/mês | AO35: =AO34/12 -> 400 | AP35: =AP34/12 -> 240 | AQ35: =AQ34/12 -> 144 | AR35: =AR34/12 -> 108 | AS35: =AS34/12 -> 108 | AT35: =AT34/12 -> 0 | AU35: =AU34/12 -> 0 | AV35: =AV34/12 -> 0 | ... BH35: =BH34/12 -> 0
E36: =IF(F36<>"",E35+1,"") | G36: =IF(F36="","","Instrumentos e equipamento científico") | K36: =+IF(J36<>"",YEAR(J36),"") | M36: =IF(AND(J36<>"",L36<>""),(YEAR(L36)-YEAR(J36))*12+MONTH(L36)-MONTH(J36)+1,"") | N36: =IF(AND(M36>0,M36<=12),M36*AO77,IF(AND(M36>12,M36<=24),12*AO77+(M36-12)*AP77,IF(AND(M36>24,M36<=36),12*AO77+12*AP77+(M36-24)*AQ77,IF(AND(M36>36,M36<=48),12*AO77+12*AP77+12*AQ77+(M36-36)*AR77,0)))) -> 0 | O36: =IF(E36="","",N36/H36) | P36: =IF(E36<>"",H36-N36,"") | Q36: =IF(E36<>"",P36+N36,"") | R36: =IF(R$16=$K36,$N36,0) -> 0 | S36: =IF(S$16=$K36,$N36,0) -> 0 | T36: =IF(T$16=$K36,$N36,0) -> 0 | U36: =IF(U$16=$K36,$N36,0) -> 0 | AH36: 6 | AI36: =H23 -> 0 | AJ36: =I23 -> 0 | AK36: =IF(AJ36=0,0,ROUNDUP(100/AJ36/100,2)) -> 0 | AL36: =IF(AND(AK36>=1,AK36<=4),1.5,IF(AND(AK36>4,AK36<=6),2,2.5)) -> 2.5 | AM36: =IF(AJ36=100%,100%,AJ36*AL36) -> 0 | AN36: Quota | AO36: =IF(AK36=0,"",AI36/AK36) | AP36: =IF($AK36-AP$20<0,"",($AI36-$AO37)/($AK36-AO$20)) | AQ36: =IF($AK36-AQ$20<0,"",($AI36-SUM($AO37:AP37))/($AK36-AP$20)) | AR36: =IF($AK36-AR$20<0,"",($AI36-SUM($AO37:AQ37))/($AK36-AQ$20)) | AS36: =IF($AK36-AS$20<0,"",($AI36-SUM($AO37:AR37))/($AK36-AR$20)) | AT36: =IF($AK36-AT$20<0,"",($AI36-SUM($AO37:AS37))/($AK36-AS$20)) | AU36: =IF($AK36-AU$20<0,"",($AI36-SUM($AO37:AT37))/($AK36-AT$20)) | AV36: =IF($AK36-AV$20<0,"",($AI36-SUM($AO37:AU37))/($AK36-AU$20)) | AW36: =IF($AK36-AW$20<0,"",($AI36-SUM($AO37:AV37))/($AK36-AV$20)) | AX36: =IF($AK36-AX$20<0,"",($AI36-SUM($AO37:AW37))/($AK36-AW$20)) | ... BH36: =IF($AK36-BH$20<0,"",($AI36-SUM($AO37:BG37))/($AK36-BG$20))
E37: =IF(F37<>"",E36+1,"") | G37: =IF(F37="","","Instrumentos e equipamento científico") | K37: =+IF(J37<>"",YEAR(J37),"") | M37: =IF(AND(J37<>"",L37<>""),(YEAR(L37)-YEAR(J37))*12+MONTH(L37)-MONTH(J37)+1,"") | N37: =IF(AND(M37>0,M37<=12),M37*AO80,IF(AND(M37>12,M37<=24),12*AO80+(M37-12)*AP80,IF(AND(M37>24,M37<=36),12*AO80+12*AP80+(M37-24)*AQ80,IF(AND(M37>36,M37<=48),12*AO80+12*AP80+12*AQ80+(M37-36)*AR80,0)))) -> 0 | O37: =IF(E37="","",N37/H37) | P37: =IF(E37<>"",H37-N37,"") | Q37: =IF(E37<>"",P37+N37,"") | R37: =IF(R$16=$K37,$N37,0) -> 0 | S37: =IF(S$16=$K37,$N37,0) -> 0 | T37: =IF(T$16=$K37,$N37,0) -> 0 | U37: =IF(U$16=$K37,$N37,0) -> 0 | AN37: Amort/ano | AO37: =IF(AO$20<=$AK36,AI36*AM36,0) -> 0 | AP37: =IF(AP$20<=$AK36,IF(($AI36-$AO37)*$AM36<AP36,AP36,(AI36-AO37)*AM36),0) -> 0 | AQ37: =IF(AQ$20<=$AK36,IF(($AI36-SUM($AO37:AP37))*$AM36<AQ36,AQ36,(($AI36-SUM($AO37:AP37))*$AM36)),0) -> 0 | AR37: =IF(AR$20<=$AK36,IF(($AI36-SUM($AO37:AQ37))*$AM36<AR36,AR36,(($AI36-SUM($AO37:AQ37))*$AM36)),0) -> 0 | AS37: =IF(AS$20<=$AK36,IF(($AI36-SUM($AO37:AR37))*$AM36<AS36,AS36,(($AI36-SUM($AO37:AR37))*$AM36)),0) -> 0 | AT37: =IF(AT$20<=$AK36,IF(($AI36-SUM($AO37:AS37))*$AM36<AT36,AT36,(($AI36-SUM($AO37:AS37))*$AM36)),0) -> 0 | AU37: =IF(AU$20<=$AK36,IF(($AI36-SUM($AO37:AT37))*$AM36<AU36,AU36,(($AI36-SUM($AO37:AT37))*$AM36)),0) -> 0 | AV37: =IF(AV$20<=$AK36,IF(($AI36-SUM($AO37:AU37))*$AM36<AV36,AV36,(($AI36-SUM($AO37:AU37))*$AM36)),0) -> 0 | AW37: =IF(AW$20<=$AK36,IF(($AI36-SUM($AO37:AV37))*$AM36<AW36,AW36,(($AI36-SUM($AO37:AV37))*$AM36)),0) -> 0 | AX37: =IF(AX$20<=$AK36,IF(($AI36-SUM($AO37:AW37))*$AM36<AX36,AX36,(($AI36-SUM($AO37:AW37))*$AM36)),0) -> 0 | ... BH37: =IF(BH$20<=$AK36,IF(($AI36-SUM($AO37:BG37))*$AM36<BH36,BH36,(($AI36-SUM($AO37:BG37))*$AM36)),0) -> 0 | BI37: =SUM(AO37:BH37) -> 0
E38: =IF(F38<>"",E37+1,"") | G38: =IF(F38="","","Instrumentos e equipamento científico") | K38: =+IF(J38<>"",YEAR(J38),"") | M38: =IF(AND(J38<>"",L38<>""),(YEAR(L38)-YEAR(J38))*12+MONTH(L38)-MONTH(J38)+1,"") | N38: =IF(AND(M38>0,M38<=12),M38*AO83,IF(AND(M38>12,M38<=24),12*AO83+(M38-12)*AP83,IF(AND(M38>24,M38<=36),12*AO83+12*AP83+(M38-24)*AQ83,IF(AND(M38>36,M38<=48),12*AO83+12*AP83+12*AQ83+(M38-36)*AR83,0)))) -> 0 | O38: =IF(E38="","",N38/H38) | P38: =IF(E38<>"",H38-N38,"") | Q38: =IF(E38<>"",P38+N38,"") | R38: =IF(R$16=$K38,$N38,0) -> 0 | S38: =IF(S$16=$K38,$N38,0) -> 0 | T38: =IF(T$16=$K38,$N38,0) -> 0 | U38: =IF(U$16=$K38,$N38,0) -> 0 | AN38: Amort/mês | AO38: =AO37/12 -> 0 | AP38: =AP37/12 -> 0 | AQ38: =AQ37/12 -> 0 | AR38: =AR37/12 -> 0 | AS38: =AS37/12 -> 0 | AT38: =AT37/12 -> 0 | AU38: =AU37/12 -> 0 | AV38: =AV37/12 -> 0 | ... BH38: =BH37/12 -> 0
E39: TOTAL | N39: =ROUND(SUM(N18:N38),2) -> 50508.13 | P39: =ROUND(SUM(P18:P38),2) -> 5491.88 | Q39: =ROUND(SUM(Q18:Q38),2) -> 56000 | R39: =ROUND(SUM(R18:R38),2) -> 50508.13 | S39: =ROUND(SUM(S18:S38),2) -> 0 | T39: =ROUND(SUM(T18:T38),2) -> 0 | U39: =ROUND(SUM(U18:U38),2) -> 0 | AH39: 7 | AI39: =H24 -> 0 | AJ39: =I24 -> 0 | AK39: =IF(AJ39=0,0,ROUNDUP(100/AJ39/100,2)) -> 0 | AL39: =IF(AND(AK39>=1,AK39<=4),1.5,IF(AND(AK39>4,AK39<=6),2,2.5)) -> 2.5 | AM39: =IF(AJ39=100%,100%,AJ39*AL39) -> 0 | AN39: Quota | AO39: =IF(AK39=0,"",AI39/AK39) | AP39: =IF($AK39-AP$20<0,"",($AI39-$AO40)/($AK39-AO$20)) | AQ39: =IF($AK39-AQ$20<0,"",($AI39-SUM($AO40:AP40))/($AK39-AP$20)) | AR39: =IF($AK39-AR$20<0,"",($AI39-SUM($AO40:AQ40))/($AK39-AQ$20)) | AS39: =IF($AK39-AS$20<0,"",($AI39-SUM($AO40:AR40))/($AK39-AR$20)) | AT39: =IF($AK39-AT$20<0,"",($AI39-SUM($AO40:AS40))/($AK39-AS$20)) | AU39: =IF($AK39-AU$20<0,"",($AI39-SUM($AO40:AT40))/($AK39-AT$20)) | AV39: =IF($AK39-AV$20<0,"",($AI39-SUM($AO40:AU40))/($AK39-AU$20)) | AW39: =IF($AK39-AW$20<0,"",($AI39-SUM($AO40:AV40))/($AK39-AV$20)) | AX39: =IF($AK39-AX$20<0,"",($AI39-SUM($AO40:AW40))/($AK39-AW$20)) | ... BH39: =IF($AK39-BH$20<0,"",($AI39-SUM($AO40:BG40))/($AK39-BG$20))
AN40: Amort/ano | AO40: =IF(AO$20<=$AK39,AI39*AM39,0) -> 0 | AP40: =IF(AP$20<=$AK39,IF(($AI39-$AO40)*$AM39<AP39,AP39,(AI39-AO40)*AM39),0) -> 0 | AQ40: =IF(AQ$20<=$AK39,IF(($AI39-SUM($AO40:AP40))*$AM39<AQ39,AQ39,(($AI39-SUM($AO40:AP40))*$AM39)),0) -> 0 | AR40: =IF(AR$20<=$AK39,IF(($AI39-SUM($AO40:AQ40))*$AM39<AR39,AR39,(($AI39-SUM($AO40:AQ40))*$AM39)),0) -> 0 | AS40: =IF(AS$20<=$AK39,IF(($AI39-SUM($AO40:AR40))*$AM39<AS39,AS39,(($AI39-SUM($AO40:AR40))*$AM39)),0) -> 0 | AT40: =IF(AT$20<=$AK39,IF(($AI39-SUM($AO40:AS40))*$AM39<AT39,AT39,(($AI39-SUM($AO40:AS40))*$AM39)),0) -> 0 | AU40: =IF(AU$20<=$AK39,IF(($AI39-SUM($AO40:AT40))*$AM39<AU39,AU39,(($AI39-SUM($AO40:AT40))*$AM39)),0) -> 0 | AV40: =IF(AV$20<=$AK39,IF(($AI39-SUM($AO40:AU40))*$AM39<AV39,AV39,(($AI39-SUM($AO40:AU40))*$AM39)),0) -> 0 | AW40: =IF(AW$20<=$AK39,IF(($AI39-SUM($AO40:AV40))*$AM39<AW39,AW39,(($AI39-SUM($AO40:AV40))*$AM39)),0) -> 0 | AX40: =IF(AX$20<=$AK39,IF(($AI39-SUM($AO40:AW40))*$AM39<AX39,AX39,(($AI39-SUM($AO40:AW40))*$AM39)),0) -> 0 | ... BH40: =IF(BH$20<=$AK39,IF(($AI39-SUM($AO40:BG40))*$AM39<BH39,BH39,(($AI39-SUM($AO40:BG40))*$AM39)),0) -> 0 | BI40: =SUM(AO40:BH40) -> 0
AN41: Amort/mês | AO41: =AO40/12 -> 0 | AP41: =AP40/12 -> 0 | AQ41: =AQ40/12 -> 0 | AR41: =AR40/12 -> 0 | AS41: =AS40/12 -> 0 | AT41: =AT40/12 -> 0 | AU41: =AU40/12 -> 0 | AV41: =AV40/12 -> 0 | ... BH41: =BH40/12 -> 0
AH42: 8 | AI42: =H25 -> 0 | AJ42: =I25 -> 0 | AK42: =IF(AJ42=0,0,ROUNDUP(100/AJ42/100,2)) -> 0 | AL42: =IF(AND(AK42>=1,AK42<=4),1.5,IF(AND(AK42>4,AK42<=6),2,2.5)) -> 2.5 | AM42: =IF(AJ42=100%,100%,AJ42*AL42) -> 0 | AN42: Quota | AO42: =IF(AK42=0,"",AI42/AK42) | AP42: =IF($AK42-AP$20<0,"",($AI42-$AO43)/($AK42-AO$20)) | AQ42: =IF($AK42-AQ$20<0,"",($AI42-SUM($AO43:AP43))/($AK42-AP$20)) | AR42: =IF($AK42-AR$20<0,"",($AI42-SUM($AO43:AQ43))/($AK42-AQ$20)) | AS42: =IF($AK42-AS$20<0,"",($AI42-SUM($AO43:AR43))/($AK42-AR$20)) | AT42: =IF($AK42-AT$20<0,"",($AI42-SUM($AO43:AS43))/($AK42-AS$20)) | AU42: =IF($AK42-AU$20<0,"",($AI42-SUM($AO43:AT43))/($AK42-AT$20)) | AV42: =IF($AK42-AV$20<0,"",($AI42-SUM($AO43:AU43))/($AK42-AU$20)) | AW42: =IF($AK42-AW$20<0,"",($AI42-SUM($AO43:AV43))/($AK42-AV$20)) | AX42: =IF($AK42-AX$20<0,"",($AI42-SUM($AO43:AW43))/($AK42-AW$20)) | ... BH42: =IF($AK42-BH$20<0,"",($AI42-SUM($AO43:BG43))/($AK42-BG$20))
AN43: Amort/ano | AO43: =IF(AO$20<=$AK42,AI42*AM42,0) -> 0 | AP43: =IF(AP$20<=$AK42,IF(($AI42-$AO43)*$AM42<AP42,AP42,(AI42-AO43)*AM42),0) -> 0 | AQ43: =IF(AQ$20<=$AK42,IF(($AI42-SUM($AO43:AP43))*$AM42<AQ42,AQ42,(($AI42-SUM($AO43:AP43))*$AM42)),0) -> 0 | AR43: =IF(AR$20<=$AK42,IF(($AI42-SUM($AO43:AQ43))*$AM42<AR42,AR42,(($AI42-SUM($AO43:AQ43))*$AM42)),0) -> 0 | AS43: =IF(AS$20<=$AK42,IF(($AI42-SUM($AO43:AR43))*$AM42<AS42,AS42,(($AI42-SUM($AO43:AR43))*$AM42)),0) -> 0 | AT43: =IF(AT$20<=$AK42,IF(($AI42-SUM($AO43:AS43))*$AM42<AT42,AT42,(($AI42-SUM($AO43:AS43))*$AM42)),0) -> 0 | AU43: =IF(AU$20<=$AK42,IF(($AI42-SUM($AO43:AT43))*$AM42<AU42,AU42,(($AI42-SUM($AO43:AT43))*$AM42)),0) -> 0 | AV43: =IF(AV$20<=$AK42,IF(($AI42-SUM($AO43:AU43))*$AM42<AV42,AV42,(($AI42-SUM($AO43:AU43))*$AM42)),0) -> 0 | AW43: =IF(AW$20<=$AK42,IF(($AI42-SUM($AO43:AV43))*$AM42<AW42,AW42,(($AI42-SUM($AO43:AV43))*$AM42)),0) -> 0 | AX43: =IF(AX$20<=$AK42,IF(($AI42-SUM($AO43:AW43))*$AM42<AX42,AX42,(($AI42-SUM($AO43:AW43))*$AM42)),0) -> 0 | ... BH43: =IF(BH$20<=$AK42,IF(($AI42-SUM($AO43:BG43))*$AM42<BH42,BH42,(($AI42-SUM($AO43:BG43))*$AM42)),0) -> 0 | BI43: =SUM(AO43:BH43) -> 0
AN44: Amort/mês | AO44: =AO43/12 -> 0 | AP44: =AP43/12 -> 0 | AQ44: =AQ43/12 -> 0 | AR44: =AR43/12 -> 0 | AS44: =AS43/12 -> 0 | AT44: =AT43/12 -> 0 | AU44: =AU43/12 -> 0 | AV44: =AV43/12 -> 0 | ... BH44: =BH43/12 -> 0
AH45: 9 | AI45: =H26 -> 0 | AJ45: =I26 -> 0 | AK45: =IF(AJ45=0,0,ROUNDUP(100/AJ45/100,2)) -> 0 | AL45: =IF(AND(AK45>=1,AK45<=4),1.5,IF(AND(AK45>4,AK45<=6),2,2.5)) -> 2.5 | AM45: =IF(AJ45=100%,100%,AJ45*AL45) -> 0 | AN45: Quota | AO45: =IF(AK45=0,"",AI45/AK45) | AP45: =IF($AK45-AP$20<0,"",($AI45-$AO46)/($AK45-AO$20)) | AQ45: =IF($AK45-AQ$20<0,"",($AI45-SUM($AO46:AP46))/($AK45-AP$20)) | AR45: =IF($AK45-AR$20<0,"",($AI45-SUM($AO46:AQ46))/($AK45-AQ$20)) | AS45: =IF($AK45-AS$20<0,"",($AI45-SUM($AO46:AR46))/($AK45-AR$20)) | AT45: =IF($AK45-AT$20<0,"",($AI45-SUM($AO46:AS46))/($AK45-AS$20)) | AU45: =IF($AK45-AU$20<0,"",($AI45-SUM($AO46:AT46))/($AK45-AT$20)) | AV45: =IF($AK45-AV$20<0,"",($AI45-SUM($AO46:AU46))/($AK45-AU$20)) | AW45: =IF($AK45-AW$20<0,"",($AI45-SUM($AO46:AV46))/($AK45-AV$20)) | AX45: =IF($AK45-AX$20<0,"",($AI45-SUM($AO46:AW46))/($AK45-AW$20)) | ... BH45: =IF($AK45-BH$20<0,"",($AI45-SUM($AO46:BG46))/($AK45-BG$20))
AN46: Amort/ano | AO46: =IF(AO$20<=$AK45,AI45*AM45,0) -> 0 | AP46: =IF(AP$20<=$AK45,IF(($AI45-$AO46)*$AM45<AP45,AP45,(AI45-AO46)*AM45),0) -> 0 | AQ46: =IF(AQ$20<=$AK45,IF(($AI45-SUM($AO46:AP46))*$AM45<AQ45,AQ45,(($AI45-SUM($AO46:AP46))*$AM45)),0) -> 0 | AR46: =IF(AR$20<=$AK45,IF(($AI45-SUM($AO46:AQ46))*$AM45<AR45,AR45,(($AI45-SUM($AO46:AQ46))*$AM45)),0) -> 0 | AS46: =IF(AS$20<=$AK45,IF(($AI45-SUM($AO46:AR46))*$AM45<AS45,AS45,(($AI45-SUM($AO46:AR46))*$AM45)),0) -> 0 | AT46: =IF(AT$20<=$AK45,IF(($AI45-SUM($AO46:AS46))*$AM45<AT45,AT45,(($AI45-SUM($AO46:AS46))*$AM45)),0) -> 0 | AU46: =IF(AU$20<=$AK45,IF(($AI45-SUM($AO46:AT46))*$AM45<AU45,AU45,(($AI45-SUM($AO46:AT46))*$AM45)),0) -> 0 | AV46: =IF(AV$20<=$AK45,IF(($AI45-SUM($AO46:AU46))*$AM45<AV45,AV45,(($AI45-SUM($AO46:AU46))*$AM45)),0) -> 0 | AW46: =IF(AW$20<=$AK45,IF(($AI45-SUM($AO46:AV46))*$AM45<AW45,AW45,(($AI45-SUM($AO46:AV46))*$AM45)),0) -> 0 | AX46: =IF(AX$20<=$AK45,IF(($AI45-SUM($AO46:AW46))*$AM45<AX45,AX45,(($AI45-SUM($AO46:AW46))*$AM45)),0) -> 0 | ... BH46: =IF(BH$20<=$AK45,IF(($AI45-SUM($AO46:BG46))*$AM45<BH45,BH45,(($AI45-SUM($AO46:BG46))*$AM45)),0) -> 0 | BI46: =SUM(AO46:BH46) -> 0
AN47: Amort/mês | AO47: =AO46/12 -> 0 | AP47: =AP46/12 -> 0 | AQ47: =AQ46/12 -> 0 | AR47: =AR46/12 -> 0 | AS47: =AS46/12 -> 0 | AT47: =AT46/12 -> 0 | AU47: =AU46/12 -> 0 | AV47: =AV46/12 -> 0 | ... BH47: =BH46/12 -> 0
AH48: 10 | AI48: =H27 -> 0 | AJ48: =I27 -> 0 | AK48: =IF(AJ48=0,0,ROUNDUP(100/AJ48/100,2)) -> 0 | AL48: =IF(AND(AK48>=1,AK48<=4),1.5,IF(AND(AK48>4,AK48<=6),2,2.5)) -> 2.5 | AM48: =IF(AJ48=100%,100%,AJ48*AL48) -> 0 | AN48: Quota | AO48: =IF(AK48=0,"",AI48/AK48) | AP48: =IF($AK48-AP$20<0,"",($AI48-$AO49)/($AK48-AO$20)) | AQ48: =IF($AK48-AQ$20<0,"",($AI48-SUM($AO49:AP49))/($AK48-AP$20)) | AR48: =IF($AK48-AR$20<0,"",($AI48-SUM($AO49:AQ49))/($AK48-AQ$20)) | AS48: =IF($AK48-AS$20<0,"",($AI48-SUM($AO49:AR49))/($AK48-AR$20)) | AT48: =IF($AK48-AT$20<0,"",($AI48-SUM($AO49:AS49))/($AK48-AS$20)) | AU48: =IF($AK48-AU$20<0,"",($AI48-SUM($AO49:AT49))/($AK48-AT$20)) | AV48: =IF($AK48-AV$20<0,"",($AI48-SUM($AO49:AU49))/($AK48-AU$20)) | AW48: =IF($AK48-AW$20<0,"",($AI48-SUM($AO49:AV49))/($AK48-AV$20)) | AX48: =IF($AK48-AX$20<0,"",($AI48-SUM($AO49:AW49))/($AK48-AW$20)) | ... BH48: =IF($AK48-BH$20<0,"",($AI48-SUM($AO49:BG49))/($AK48-BG$20))
AN49: Amort/ano | AO49: =IF(AO$20<=$AK48,AI48*AM48,0) -> 0 | AP49: =IF(AP$20<=$AK48,IF(($AI48-$AO49)*$AM48<AP48,AP48,(AI48-AO49)*AM48),0) -> 0 | AQ49: =IF(AQ$20<=$AK48,IF(($AI48-SUM($AO49:AP49))*$AM48<AQ48,AQ48,(($AI48-SUM($AO49:AP49))*$AM48)),0) -> 0 | AR49: =IF(AR$20<=$AK48,IF(($AI48-SUM($AO49:AQ49))*$AM48<AR48,AR48,(($AI48-SUM($AO49:AQ49))*$AM48)),0) -> 0 | AS49: =IF(AS$20<=$AK48,IF(($AI48-SUM($AO49:AR49))*$AM48<AS48,AS48,(($AI48-SUM($AO49:AR49))*$AM48)),0) -> 0 | AT49: =IF(AT$20<=$AK48,IF(($AI48-SUM($AO49:AS49))*$AM48<AT48,AT48,(($AI48-SUM($AO49:AS49))*$AM48)),0) -> 0 | AU49: =IF(AU$20<=$AK48,IF(($AI48-SUM($AO49:AT49))*$AM48<AU48,AU48,(($AI48-SUM($AO49:AT49))*$AM48)),0) -> 0 | AV49: =IF(AV$20<=$AK48,IF(($AI48-SUM($AO49:AU49))*$AM48<AV48,AV48,(($AI48-SUM($AO49:AU49))*$AM48)),0) -> 0 | AW49: =IF(AW$20<=$AK48,IF(($AI48-SUM($AO49:AV49))*$AM48<AW48,AW48,(($AI48-SUM($AO49:AV49))*$AM48)),0) -> 0 | AX49: =IF(AX$20<=$AK48,IF(($AI48-SUM($AO49:AW49))*$AM48<AX48,AX48,(($AI48-SUM($AO49:AW49))*$AM48)),0) -> 0 | ... BH49: =IF(BH$20<=$AK48,IF(($AI48-SUM($AO49:BG49))*$AM48<BH48,BH48,(($AI48-SUM($AO49:BG49))*$AM48)),0) -> 0 | BI49: =SUM(AO49:BH49) -> 0
AN50: Amort/mês | AO50: =AO49/12 -> 0 | AP50: =AP49/12 -> 0 | AQ50: =AQ49/12 -> 0 | AR50: =AR49/12 -> 0 | AS50: =AS49/12 -> 0 | AT50: =AT49/12 -> 0 | AU50: =AU49/12 -> 0 | AV50: =AV49/12 -> 0 | ... BH50: =BH49/12 -> 0
AH51: 11 | AI51: =H28 -> 0 | AJ51: =I28 -> 0 | AK51: =IF(AJ51=0,0,ROUNDUP(100/AJ51/100,2)) -> 0 | AL51: =IF(AND(AK51>=1,AK51<=4),1.5,IF(AND(AK51>4,AK51<=6),2,2.5)) -> 2.5 | AM51: =AJ51*AL51 -> 0 | AN51: Quota | AO51: =IF(AK51=0,"",AI51/AK51) | AP51: =IF($AK51-AP$20<0,"",($AI51-$AO52)/($AK51-AO$20)) | AQ51: =IF($AK51-AQ$20<0,"",($AI51-SUM($AO52:AP52))/($AK51-AP$20)) | AR51: =IF($AK51-AR$20<0,"",($AI51-SUM($AO52:AQ52))/($AK51-AQ$20)) | AS51: =IF($AK51-AS$20<0,"",($AI51-SUM($AO52:AR52))/($AK51-AR$20)) | AT51: =IF($AK51-AT$20<0,"",($AI51-SUM($AO52:AS52))/($AK51-AS$20)) | AU51: =IF($AK51-AU$20<0,"",($AI51-SUM($AO52:AT52))/($AK51-AT$20)) | AV51: =IF($AK51-AV$20<0,"",($AI51-SUM($AO52:AU52))/($AK51-AU$20)) | AW51: =IF($AK51-AW$20<0,"",($AI51-SUM($AO52:AV52))/($AK51-AV$20)) | AX51: =IF($AK51-AX$20<0,"",($AI51-SUM($AO52:AW52))/($AK51-AW$20)) | ... BH51: =IF($AK51-BH$20<0,"",($AI51-SUM($AO52:BG52))/($AK51-BG$20))
AN52: Amort/ano | AO52: =IF(AO$20<=$AK51,AI51*AM51,0) -> 0 | AP52: =IF(AP$20<=$AK51,IF(($AI51-$AO52)*$AM51<AP51,AP51,(AI51-AO52)*AM51),0) -> 0 | AQ52: =IF(AQ$20<=$AK51,IF(($AI51-SUM($AO52:AP52))*$AM51<AQ51,AQ51,(($AI51-SUM($AO52:AP52))*$AM51)),0) -> 0 | AR52: =IF(AR$20<=$AK51,IF(($AI51-SUM($AO52:AQ52))*$AM51<AR51,AR51,(($AI51-SUM($AO52:AQ52))*$AM51)),0) -> 0 | AS52: =IF(AS$20<=$AK51,IF(($AI51-SUM($AO52:AR52))*$AM51<AS51,AS51,(($AI51-SUM($AO52:AR52))*$AM51)),0) -> 0 | AT52: =IF(AT$20<=$AK51,IF(($AI51-SUM($AO52:AS52))*$AM51<AT51,AT51,(($AI51-SUM($AO52:AS52))*$AM51)),0) -> 0 | AU52: =IF(AU$20<=$AK51,IF(($AI51-SUM($AO52:AT52))*$AM51<AU51,AU51,(($AI51-SUM($AO52:AT52))*$AM51)),0) -> 0 | AV52: =IF(AV$20<=$AK51,IF(($AI51-SUM($AO52:AU52))*$AM51<AV51,AV51,(($AI51-SUM($AO52:AU52))*$AM51)),0) -> 0 | AW52: =IF(AW$20<=$AK51,IF(($AI51-SUM($AO52:AV52))*$AM51<AW51,AW51,(($AI51-SUM($AO52:AV52))*$AM51)),0) -> 0 | AX52: =IF(AX$20<=$AK51,IF(($AI51-SUM($AO52:AW52))*$AM51<AX51,AX51,(($AI51-SUM($AO52:AW52))*$AM51)),0) -> 0 | ... BH52: =IF(BH$20<=$AK51,IF(($AI51-SUM($AO52:BG52))*$AM51<BH51,BH51,(($AI51-SUM($AO52:BG52))*$AM51)),0) -> 0 | BI52: =SUM(AO52:BH52) -> 0
AN53: Amort/mês | AO53: =AO52/12 -> 0 | AP53: =AP52/12 -> 0 | AQ53: =AQ52/12 -> 0 | AR53: =AR52/12 -> 0 | AS53: =AS52/12 -> 0 | AT53: =AT52/12 -> 0 | AU53: =AU52/12 -> 0 | AV53: =AV52/12 -> 0 | ... BH53: =BH52/12 -> 0
AH54: 12 | AI54: =H29 -> 0 | AJ54: =I29 -> 0 | AK54: =IF(AJ54=0,0,ROUNDUP(100/AJ54/100,2)) -> 0 | AL54: =IF(AND(AK54>=1,AK54<=4),1.5,IF(AND(AK54>4,AK54<=6),2,2.5)) -> 2.5 | AM54: =AJ54*AL54 -> 0 | AN54: Quota | AO54: =IF(AK54=0,"",AI54/AK54) | AP54: =IF($AK54-AP$20<0,"",($AI54-$AO55)/($AK54-AO$20)) | AQ54: =IF($AK54-AQ$20<0,"",($AI54-SUM($AO55:AP55))/($AK54-AP$20)) | AR54: =IF($AK54-AR$20<0,"",($AI54-SUM($AO55:AQ55))/($AK54-AQ$20)) | AS54: =IF($AK54-AS$20<0,"",($AI54-SUM($AO55:AR55))/($AK54-AR$20)) | AT54: =IF($AK54-AT$20<0,"",($AI54-SUM($AO55:AS55))/($AK54-AS$20)) | AU54: =IF($AK54-AU$20<0,"",($AI54-SUM($AO55:AT55))/($AK54-AT$20)) | AV54: =IF($AK54-AV$20<0,"",($AI54-SUM($AO55:AU55))/($AK54-AU$20)) | AW54: =IF($AK54-AW$20<0,"",($AI54-SUM($AO55:AV55))/($AK54-AV$20)) | AX54: =IF($AK54-AX$20<0,"",($AI54-SUM($AO55:AW55))/($AK54-AW$20)) | ... BH54: =IF($AK54-BH$20<0,"",($AI54-SUM($AO55:BG55))/($AK54-BG$20))
AN55: Amort/ano | AO55: =IF(AO$20<=$AK54,AI54*AM54,0) -> 0 | AP55: =IF(AP$20<=$AK54,IF(($AI54-$AO55)*$AM54<AP54,AP54,(AI54-AO55)*AM54),0) -> 0 | AQ55: =IF(AQ$20<=$AK54,IF(($AI54-SUM($AO55:AP55))*$AM54<AQ54,AQ54,(($AI54-SUM($AO55:AP55))*$AM54)),0) -> 0 | AR55: =IF(AR$20<=$AK54,IF(($AI54-SUM($AO55:AQ55))*$AM54<AR54,AR54,(($AI54-SUM($AO55:AQ55))*$AM54)),0) -> 0 | AS55: =IF(AS$20<=$AK54,IF(($AI54-SUM($AO55:AR55))*$AM54<AS54,AS54,(($AI54-SUM($AO55:AR55))*$AM54)),0) -> 0 | AT55: =IF(AT$20<=$AK54,IF(($AI54-SUM($AO55:AS55))*$AM54<AT54,AT54,(($AI54-SUM($AO55:AS55))*$AM54)),0) -> 0 | AU55: =IF(AU$20<=$AK54,IF(($AI54-SUM($AO55:AT55))*$AM54<AU54,AU54,(($AI54-SUM($AO55:AT55))*$AM54)),0) -> 0 | AV55: =IF(AV$20<=$AK54,IF(($AI54-SUM($AO55:AU55))*$AM54<AV54,AV54,(($AI54-SUM($AO55:AU55))*$AM54)),0) -> 0 | AW55: =IF(AW$20<=$AK54,IF(($AI54-SUM($AO55:AV55))*$AM54<AW54,AW54,(($AI54-SUM($AO55:AV55))*$AM54)),0) -> 0 | AX55: =IF(AX$20<=$AK54,IF(($AI54-SUM($AO55:AW55))*$AM54<AX54,AX54,(($AI54-SUM($AO55:AW55))*$AM54)),0) -> 0 | ... BH55: =IF(BH$20<=$AK54,IF(($AI54-SUM($AO55:BG55))*$AM54<BH54,BH54,(($AI54-SUM($AO55:BG55))*$AM54)),0) -> 0 | BI55: =SUM(AO55:BH55) -> 0
AN56: Amort/mês | AO56: =AO55/12 -> 0 | AP56: =AP55/12 -> 0 | AQ56: =AQ55/12 -> 0 | AR56: =AR55/12 -> 0 | AS56: =AS55/12 -> 0 | AT56: =AT55/12 -> 0 | AU56: =AU55/12 -> 0 | AV56: =AV55/12 -> 0 | ... BH56: =BH55/12 -> 0
AH57: 13 | AI57: =H30 -> 0 | AJ57: =I30 -> 0 | AK57: =IF(AJ57=0,0,ROUNDUP(100/AJ57/100,2)) -> 0 | AL57: =IF(AND(AK57>=1,AK57<=4),1.5,IF(AND(AK57>4,AK57<=6),2,2.5)) -> 2.5 | AM57: =AJ57*AL57 -> 0 | AN57: Quota | AO57: =IF(AK57=0,"",AI57/AK57) | AP57: =IF($AK57-AP$20<0,"",($AI57-$AO58)/($AK57-AO$20)) | AQ57: =IF($AK57-AQ$20<0,"",($AI57-SUM($AO58:AP58))/($AK57-AP$20)) | AR57: =IF($AK57-AR$20<0,"",($AI57-SUM($AO58:AQ58))/($AK57-AQ$20)) | AS57: =IF($AK57-AS$20<0,"",($AI57-SUM($AO58:AR58))/($AK57-AR$20)) | AT57: =IF($AK57-AT$20<0,"",($AI57-SUM($AO58:AS58))/($AK57-AS$20)) | AU57: =IF($AK57-AU$20<0,"",($AI57-SUM($AO58:AT58))/($AK57-AT$20)) | AV57: =IF($AK57-AV$20<0,"",($AI57-SUM($AO58:AU58))/($AK57-AU$20)) | AW57: =IF($AK57-AW$20<0,"",($AI57-SUM($AO58:AV58))/($AK57-AV$20)) | AX57: =IF($AK57-AX$20<0,"",($AI57-SUM($AO58:AW58))/($AK57-AW$20)) | ... BH57: =IF($AK57-BH$20<0,"",($AI57-SUM($AO58:BG58))/($AK57-BG$20))
AN58: Amort/ano | AO58: =IF(AO$20<=$AK57,AI57*AM57,0) -> 0 | AP58: =IF(AP$20<=$AK57,IF(($AI57-$AO58)*$AM57<AP57,AP57,(AI57-AO58)*AM57),0) -> 0 | AQ58: =IF(AQ$20<=$AK57,IF(($AI57-SUM($AO58:AP58))*$AM57<AQ57,AQ57,(($AI57-SUM($AO58:AP58))*$AM57)),0) -> 0 | AR58: =IF(AR$20<=$AK57,IF(($AI57-SUM($AO58:AQ58))*$AM57<AR57,AR57,(($AI57-SUM($AO58:AQ58))*$AM57)),0) -> 0 | AS58: =IF(AS$20<=$AK57,IF(($AI57-SUM($AO58:AR58))*$AM57<AS57,AS57,(($AI57-SUM($AO58:AR58))*$AM57)),0) -> 0 | AT58: =IF(AT$20<=$AK57,IF(($AI57-SUM($AO58:AS58))*$AM57<AT57,AT57,(($AI57-SUM($AO58:AS58))*$AM57)),0) -> 0 | AU58: =IF(AU$20<=$AK57,IF(($AI57-SUM($AO58:AT58))*$AM57<AU57,AU57,(($AI57-SUM($AO58:AT58))*$AM57)),0) -> 0 | AV58: =IF(AV$20<=$AK57,IF(($AI57-SUM($AO58:AU58))*$AM57<AV57,AV57,(($AI57-SUM($AO58:AU58))*$AM57)),0) -> 0 | AW58: =IF(AW$20<=$AK57,IF(($AI57-SUM($AO58:AV58))*$AM57<AW57,AW57,(($AI57-SUM($AO58:AV58))*$AM57)),0) -> 0 | AX58: =IF(AX$20<=$AK57,IF(($AI57-SUM($AO58:AW58))*$AM57<AX57,AX57,(($AI57-SUM($AO58:AW58))*$AM57)),0) -> 0 | ... BH58: =IF(BH$20<=$AK57,IF(($AI57-SUM($AO58:BG58))*$AM57<BH57,BH57,(($AI57-SUM($AO58:BG58))*$AM57)),0) -> 0 | BI58: =SUM(AO58:BH58) -> 0
AN59: Amort/mês | AO59: =AO58/12 -> 0 | AP59: =AP58/12 -> 0 | AQ59: =AQ58/12 -> 0 | AR59: =AR58/12 -> 0 | AS59: =AS58/12 -> 0 | AT59: =AT58/12 -> 0 | AU59: =AU58/12 -> 0 | AV59: =AV58/12 -> 0 | ... BH59: =BH58/12 -> 0
AH60: 14 | AI60: =H31 -> 0 | AJ60: =I31 -> 0 | AK60: =IF(AJ60=0,0,ROUNDUP(100/AJ60/100,2)) -> 0 | AL60: =IF(AND(AK60>=1,AK60<=4),1.5,IF(AND(AK60>4,AK60<=6),2,2.5)) -> 2.5 | AM60: =AJ60*AL60 -> 0 | AN60: Quota | AO60: =IF(AK60=0,"",AI60/AK60) | AP60: =IF($AK60-AP$20<0,"",($AI60-$AO61)/($AK60-AO$20)) | AQ60: =IF($AK60-AQ$20<0,"",($AI60-SUM($AO61:AP61))/($AK60-AP$20)) | AR60: =IF($AK60-AR$20<0,"",($AI60-SUM($AO61:AQ61))/($AK60-AQ$20)) | AS60: =IF($AK60-AS$20<0,"",($AI60-SUM($AO61:AR61))/($AK60-AR$20)) | AT60: =IF($AK60-AT$20<0,"",($AI60-SUM($AO61:AS61))/($AK60-AS$20)) | AU60: =IF($AK60-AU$20<0,"",($AI60-SUM($AO61:AT61))/($AK60-AT$20)) | AV60: =IF($AK60-AV$20<0,"",($AI60-SUM($AO61:AU61))/($AK60-AU$20)) | AW60: =IF($AK60-AW$20<0,"",($AI60-SUM($AO61:AV61))/($AK60-AV$20)) | AX60: =IF($AK60-AX$20<0,"",($AI60-SUM($AO61:AW61))/($AK60-AW$20)) | ... BH60: =IF($AK60-BH$20<0,"",($AI60-SUM($AO61:BG61))/($AK60-BG$20))
AN61: Amort/ano | AO61: =IF(AO$20<=$AK60,AI60*AM60,0) -> 0 | AP61: =IF(AP$20<=$AK60,IF(($AI60-$AO61)*$AM60<AP60,AP60,(AI60-AO61)*AM60),0) -> 0 | AQ61: =IF(AQ$20<=$AK60,IF(($AI60-SUM($AO61:AP61))*$AM60<AQ60,AQ60,(($AI60-SUM($AO61:AP61))*$AM60)),0) -> 0 | AR61: =IF(AR$20<=$AK60,IF(($AI60-SUM($AO61:AQ61))*$AM60<AR60,AR60,(($AI60-SUM($AO61:AQ61))*$AM60)),0) -> 0 | AS61: =IF(AS$20<=$AK60,IF(($AI60-SUM($AO61:AR61))*$AM60<AS60,AS60,(($AI60-SUM($AO61:AR61))*$AM60)),0) -> 0 | AT61: =IF(AT$20<=$AK60,IF(($AI60-SUM($AO61:AS61))*$AM60<AT60,AT60,(($AI60-SUM($AO61:AS61))*$AM60)),0) -> 0 | AU61: =IF(AU$20<=$AK60,IF(($AI60-SUM($AO61:AT61))*$AM60<AU60,AU60,(($AI60-SUM($AO61:AT61))*$AM60)),0) -> 0 | AV61: =IF(AV$20<=$AK60,IF(($AI60-SUM($AO61:AU61))*$AM60<AV60,AV60,(($AI60-SUM($AO61:AU61))*$AM60)),0) -> 0 | AW61: =IF(AW$20<=$AK60,IF(($AI60-SUM($AO61:AV61))*$AM60<AW60,AW60,(($AI60-SUM($AO61:AV61))*$AM60)),0) -> 0 | AX61: =IF(AX$20<=$AK60,IF(($AI60-SUM($AO61:AW61))*$AM60<AX60,AX60,(($AI60-SUM($AO61:AW61))*$AM60)),0) -> 0 | ... BH61: =IF(BH$20<=$AK60,IF(($AI60-SUM($AO61:BG61))*$AM60<BH60,BH60,(($AI60-SUM($AO61:BG61))*$AM60)),0) -> 0 | BI61: =SUM(AO61:BH61) -> 0
AN62: Amort/mês | AO62: =AO61/12 -> 0 | AP62: =AP61/12 -> 0 | AQ62: =AQ61/12 -> 0 | AR62: =AR61/12 -> 0 | AS62: =AS61/12 -> 0 | AT62: =AT61/12 -> 0 | AU62: =AU61/12 -> 0 | AV62: =AV61/12 -> 0 | ... BH62: =BH61/12 -> 0
AH63: 15 | AI63: =H32 -> 0 | AJ63: =I32 -> 0 | AK63: =IF(AJ63=0,0,ROUNDUP(100/AJ63/100,2)) -> 0 | AL63: =IF(AND(AK63>=1,AK63<=4),1.5,IF(AND(AK63>4,AK63<=6),2,2.5)) -> 2.5 | AM63: =AJ63*AL63 -> 0 | AN63: Quota | AO63: =IF(AK63=0,"",AI63/AK63) | AP63: =IF($AK63-AP$20<0,"",($AI63-$AO64)/($AK63-AO$20)) | AQ63: =IF($AK63-AQ$20<0,"",($AI63-SUM($AO64:AP64))/($AK63-AP$20)) | AR63: =IF($AK63-AR$20<0,"",($AI63-SUM($AO64:AQ64))/($AK63-AQ$20)) | AS63: =IF($AK63-AS$20<0,"",($AI63-SUM($AO64:AR64))/($AK63-AR$20)) | AT63: =IF($AK63-AT$20<0,"",($AI63-SUM($AO64:AS64))/($AK63-AS$20)) | AU63: =IF($AK63-AU$20<0,"",($AI63-SUM($AO64:AT64))/($AK63-AT$20)) | AV63: =IF($AK63-AV$20<0,"",($AI63-SUM($AO64:AU64))/($AK63-AU$20)) | AW63: =IF($AK63-AW$20<0,"",($AI63-SUM($AO64:AV64))/($AK63-AV$20)) | AX63: =IF($AK63-AX$20<0,"",($AI63-SUM($AO64:AW64))/($AK63-AW$20)) | ... BH63: =IF($AK63-BH$20<0,"",($AI63-SUM($AO64:BG64))/($AK63-BG$20))
AN64: Amort/ano | AO64: =IF(AO$20<=$AK63,AI63*AM63,0) -> 0 | AP64: =IF(AP$20<=$AK63,IF(($AI63-$AO64)*$AM63<AP63,AP63,(AI63-AO64)*AM63),0) -> 0 | AQ64: =IF(AQ$20<=$AK63,IF(($AI63-SUM($AO64:AP64))*$AM63<AQ63,AQ63,(($AI63-SUM($AO64:AP64))*$AM63)),0) -> 0 | AR64: =IF(AR$20<=$AK63,IF(($AI63-SUM($AO64:AQ64))*$AM63<AR63,AR63,(($AI63-SUM($AO64:AQ64))*$AM63)),0) -> 0 | AS64: =IF(AS$20<=$AK63,IF(($AI63-SUM($AO64:AR64))*$AM63<AS63,AS63,(($AI63-SUM($AO64:AR64))*$AM63)),0) -> 0 | AT64: =IF(AT$20<=$AK63,IF(($AI63-SUM($AO64:AS64))*$AM63<AT63,AT63,(($AI63-SUM($AO64:AS64))*$AM63)),0) -> 0 | AU64: =IF(AU$20<=$AK63,IF(($AI63-SUM($AO64:AT64))*$AM63<AU63,AU63,(($AI63-SUM($AO64:AT64))*$AM63)),0) -> 0 | AV64: =IF(AV$20<=$AK63,IF(($AI63-SUM($AO64:AU64))*$AM63<AV63,AV63,(($AI63-SUM($AO64:AU64))*$AM63)),0) -> 0 | AW64: =IF(AW$20<=$AK63,IF(($AI63-SUM($AO64:AV64))*$AM63<AW63,AW63,(($AI63-SUM($AO64:AV64))*$AM63)),0) -> 0 | AX64: =IF(AX$20<=$AK63,IF(($AI63-SUM($AO64:AW64))*$AM63<AX63,AX63,(($AI63-SUM($AO64:AW64))*$AM63)),0) -> 0 | ... BH64: =IF(BH$20<=$AK63,IF(($AI63-SUM($AO64:BG64))*$AM63<BH63,BH63,(($AI63-SUM($AO64:BG64))*$AM63)),0) -> 0 | BI64: =SUM(AO64:BH64) -> 0
AN65: Amort/mês | AO65: =AO64/12 -> 0 | AP65: =AP64/12 -> 0 | AQ65: =AQ64/12 -> 0 | AR65: =AR64/12 -> 0 | AS65: =AS64/12 -> 0 | AT65: =AT64/12 -> 0 | AU65: =AU64/12 -> 0 | AV65: =AV64/12 -> 0 | ... BH65: =BH64/12 -> 0
AH66: 16 | AI66: =H33 -> 0 | AJ66: =I33 -> 0 | AK66: =IF(AJ66=0,0,ROUNDUP(100/AJ66/100,2)) -> 0 | AL66: =IF(AND(AK66>=1,AK66<=4),1.5,IF(AND(AK66>4,AK66<=6),2,2.5)) -> 2.5 | AM66: =AJ66*AL66 -> 0 | AN66: Quota | AO66: =IF(AK66=0,"",AI66/AK66) | AP66: =IF($AK66-AP$20<0,"",($AI66-$AO67)/($AK66-AO$20)) | AQ66: =IF($AK66-AQ$20<0,"",($AI66-SUM($AO67:AP67))/($AK66-AP$20)) | AR66: =IF($AK66-AR$20<0,"",($AI66-SUM($AO67:AQ67))/($AK66-AQ$20)) | AS66: =IF($AK66-AS$20<0,"",($AI66-SUM($AO67:AR67))/($AK66-AR$20)) | AT66: =IF($AK66-AT$20<0,"",($AI66-SUM($AO67:AS67))/($AK66-AS$20)) | AU66: =IF($AK66-AU$20<0,"",($AI66-SUM($AO67:AT67))/($AK66-AT$20)) | AV66: =IF($AK66-AV$20<0,"",($AI66-SUM($AO67:AU67))/($AK66-AU$20)) | AW66: =IF($AK66-AW$20<0,"",($AI66-SUM($AO67:AV67))/($AK66-AV$20)) | AX66: =IF($AK66-AX$20<0,"",($AI66-SUM($AO67:AW67))/($AK66-AW$20)) | ... BH66: =IF($AK66-BH$20<0,"",($AI66-SUM($AO67:BG67))/($AK66-BG$20))
AN67: Amort/ano | AO67: =IF(AO$20<=$AK66,AI66*AM66,0) -> 0 | AP67: =IF(AP$20<=$AK66,IF(($AI66-$AO67)*$AM66<AP66,AP66,(AI66-AO67)*AM66),0) -> 0 | AQ67: =IF(AQ$20<=$AK66,IF(($AI66-SUM($AO67:AP67))*$AM66<AQ66,AQ66,(($AI66-SUM($AO67:AP67))*$AM66)),0) -> 0 | AR67: =IF(AR$20<=$AK66,IF(($AI66-SUM($AO67:AQ67))*$AM66<AR66,AR66,(($AI66-SUM($AO67:AQ67))*$AM66)),0) -> 0 | AS67: =IF(AS$20<=$AK66,IF(($AI66-SUM($AO67:AR67))*$AM66<AS66,AS66,(($AI66-SUM($AO67:AR67))*$AM66)),0) -> 0 | AT67: =IF(AT$20<=$AK66,IF(($AI66-SUM($AO67:AS67))*$AM66<AT66,AT66,(($AI66-SUM($AO67:AS67))*$AM66)),0) -> 0 | AU67: =IF(AU$20<=$AK66,IF(($AI66-SUM($AO67:AT67))*$AM66<AU66,AU66,(($AI66-SUM($AO67:AT67))*$AM66)),0) -> 0 | AV67: =IF(AV$20<=$AK66,IF(($AI66-SUM($AO67:AU67))*$AM66<AV66,AV66,(($AI66-SUM($AO67:AU67))*$AM66)),0) -> 0 | AW67: =IF(AW$20<=$AK66,IF(($AI66-SUM($AO67:AV67))*$AM66<AW66,AW66,(($AI66-SUM($AO67:AV67))*$AM66)),0) -> 0 | AX67: =IF(AX$20<=$AK66,IF(($AI66-SUM($AO67:AW67))*$AM66<AX66,AX66,(($AI66-SUM($AO67:AW67))*$AM66)),0) -> 0 | ... BH67: =IF(BH$20<=$AK66,IF(($AI66-SUM($AO67:BG67))*$AM66<BH66,BH66,(($AI66-SUM($AO67:BG67))*$AM66)),0) -> 0 | BI67: =SUM(AO67:BH67) -> 0
AN68: Amort/mês | AO68: =AO67/12 -> 0 | AP68: =AP67/12 -> 0 | AQ68: =AQ67/12 -> 0 | AR68: =AR67/12 -> 0 | AS68: =AS67/12 -> 0 | AT68: =AT67/12 -> 0 | AU68: =AU67/12 -> 0 | AV68: =AV67/12 -> 0 | ... BH68: =BH67/12 -> 0
AH69: 17 | AI69: =H34 -> 0 | AJ69: =I34 -> 0 | AK69: =IF(AJ69=0,0,ROUNDUP(100/AJ69/100,2)) -> 0 | AL69: =IF(AND(AK69>=1,AK69<=4),1.5,IF(AND(AK69>4,AK69<=6),2,2.5)) -> 2.5 | AM69: =AJ69*AL69 -> 0 | AN69: Quota | AO69: =IF(AK69=0,"",AI69/AK69) | AP69: =IF($AK69-AP$20<0,"",($AI69-$AO70)/($AK69-AO$20)) | AQ69: =IF($AK69-AQ$20<0,"",($AI69-SUM($AO70:AP70))/($AK69-AP$20)) | AR69: =IF($AK69-AR$20<0,"",($AI69-SUM($AO70:AQ70))/($AK69-AQ$20)) | AS69: =IF($AK69-AS$20<0,"",($AI69-SUM($AO70:AR70))/($AK69-AR$20)) | AT69: =IF($AK69-AT$20<0,"",($AI69-SUM($AO70:AS70))/($AK69-AS$20)) | AU69: =IF($AK69-AU$20<0,"",($AI69-SUM($AO70:AT70))/($AK69-AT$20)) | AV69: =IF($AK69-AV$20<0,"",($AI69-SUM($AO70:AU70))/($AK69-AU$20)) | AW69: =IF($AK69-AW$20<0,"",($AI69-SUM($AO70:AV70))/($AK69-AV$20)) | AX69: =IF($AK69-AX$20<0,"",($AI69-SUM($AO70:AW70))/($AK69-AW$20)) | ... BH69: =IF($AK69-BH$20<0,"",($AI69-SUM($AO70:BG70))/($AK69-BG$20))
AN70: Amort/ano | AO70: =IF(AO$20<=$AK69,AI69*AM69,0) -> 0 | AP70: =IF(AP$20<=$AK69,IF(($AI69-$AO70)*$AM69<AP69,AP69,(AI69-AO70)*AM69),0) -> 0 | AQ70: =IF(AQ$20<=$AK69,IF(($AI69-SUM($AO70:AP70))*$AM69<AQ69,AQ69,(($AI69-SUM($AO70:AP70))*$AM69)),0) -> 0 | AR70: =IF(AR$20<=$AK69,IF(($AI69-SUM($AO70:AQ70))*$AM69<AR69,AR69,(($AI69-SUM($AO70:AQ70))*$AM69)),0) -> 0 | AS70: =IF(AS$20<=$AK69,IF(($AI69-SUM($AO70:AR70))*$AM69<AS69,AS69,(($AI69-SUM($AO70:AR70))*$AM69)),0) -> 0 | AT70: =IF(AT$20<=$AK69,IF(($AI69-SUM($AO70:AS70))*$AM69<AT69,AT69,(($AI69-SUM($AO70:AS70))*$AM69)),0) -> 0 | AU70: =IF(AU$20<=$AK69,IF(($AI69-SUM($AO70:AT70))*$AM69<AU69,AU69,(($AI69-SUM($AO70:AT70))*$AM69)),0) -> 0 | AV70: =IF(AV$20<=$AK69,IF(($AI69-SUM($AO70:AU70))*$AM69<AV69,AV69,(($AI69-SUM($AO70:AU70))*$AM69)),0) -> 0 | AW70: =IF(AW$20<=$AK69,IF(($AI69-SUM($AO70:AV70))*$AM69<AW69,AW69,(($AI69-SUM($AO70:AV70))*$AM69)),0) -> 0 | AX70: =IF(AX$20<=$AK69,IF(($AI69-SUM($AO70:AW70))*$AM69<AX69,AX69,(($AI69-SUM($AO70:AW70))*$AM69)),0) -> 0 | ... BH70: =IF(BH$20<=$AK69,IF(($AI69-SUM($AO70:BG70))*$AM69<BH69,BH69,(($AI69-SUM($AO70:BG70))*$AM69)),0) -> 0 | BI70: =SUM(AO70:BH70) -> 0
AN71: Amort/mês | AO71: =AO70/12 -> 0 | AP71: =AP70/12 -> 0 | AQ71: =AQ70/12 -> 0 | AR71: =AR70/12 -> 0 | AS71: =AS70/12 -> 0 | AT71: =AT70/12 -> 0 | AU71: =AU70/12 -> 0 | AV71: =AV70/12 -> 0 | ... BH71: =BH70/12 -> 0
AH72: 18 | AI72: =H35 -> 0 | AJ72: =I35 -> 0 | AK72: =IF(AJ72=0,0,ROUNDUP(100/AJ72/100,2)) -> 0 | AL72: =IF(AND(AK72>=1,AK72<=4),1.5,IF(AND(AK72>4,AK72<=6),2,2.5)) -> 2.5 | AM72: =AJ72*AL72 -> 0 | AN72: Quota | AO72: =IF(AK72=0,"",AI72/AK72) | AP72: =IF($AK72-AP$20<0,"",($AI72-$AO73)/($AK72-AO$20)) | AQ72: =IF($AK72-AQ$20<0,"",($AI72-SUM($AO73:AP73))/($AK72-AP$20)) | AR72: =IF($AK72-AR$20<0,"",($AI72-SUM($AO73:AQ73))/($AK72-AQ$20)) | AS72: =IF($AK72-AS$20<0,"",($AI72-SUM($AO73:AR73))/($AK72-AR$20)) | AT72: =IF($AK72-AT$20<0,"",($AI72-SUM($AO73:AS73))/($AK72-AS$20)) | AU72: =IF($AK72-AU$20<0,"",($AI72-SUM($AO73:AT73))/($AK72-AT$20)) | AV72: =IF($AK72-AV$20<0,"",($AI72-SUM($AO73:AU73))/($AK72-AU$20)) | AW72: =IF($AK72-AW$20<0,"",($AI72-SUM($AO73:AV73))/($AK72-AV$20)) | AX72: =IF($AK72-AX$20<0,"",($AI72-SUM($AO73:AW73))/($AK72-AW$20)) | ... BH72: =IF($AK72-BH$20<0,"",($AI72-SUM($AO73:BG73))/($AK72-BG$20))
AN73: Amort/ano | AO73: =IF(AO$20<=$AK72,AI72*AM72,0) -> 0 | AP73: =IF(AP$20<=$AK72,IF(($AI72-$AO73)*$AM72<AP72,AP72,(AI72-AO73)*AM72),0) -> 0 | AQ73: =IF(AQ$20<=$AK72,IF(($AI72-SUM($AO73:AP73))*$AM72<AQ72,AQ72,(($AI72-SUM($AO73:AP73))*$AM72)),0) -> 0 | AR73: =IF(AR$20<=$AK72,IF(($AI72-SUM($AO73:AQ73))*$AM72<AR72,AR72,(($AI72-SUM($AO73:AQ73))*$AM72)),0) -> 0 | AS73: =IF(AS$20<=$AK72,IF(($AI72-SUM($AO73:AR73))*$AM72<AS72,AS72,(($AI72-SUM($AO73:AR73))*$AM72)),0) -> 0 | AT73: =IF(AT$20<=$AK72,IF(($AI72-SUM($AO73:AS73))*$AM72<AT72,AT72,(($AI72-SUM($AO73:AS73))*$AM72)),0) -> 0 | AU73: =IF(AU$20<=$AK72,IF(($AI72-SUM($AO73:AT73))*$AM72<AU72,AU72,(($AI72-SUM($AO73:AT73))*$AM72)),0) -> 0 | AV73: =IF(AV$20<=$AK72,IF(($AI72-SUM($AO73:AU73))*$AM72<AV72,AV72,(($AI72-SUM($AO73:AU73))*$AM72)),0) -> 0 | AW73: =IF(AW$20<=$AK72,IF(($AI72-SUM($AO73:AV73))*$AM72<AW72,AW72,(($AI72-SUM($AO73:AV73))*$AM72)),0) -> 0 | AX73: =IF(AX$20<=$AK72,IF(($AI72-SUM($AO73:AW73))*$AM72<AX72,AX72,(($AI72-SUM($AO73:AW73))*$AM72)),0) -> 0 | ... BH73: =IF(BH$20<=$AK72,IF(($AI72-SUM($AO73:BG73))*$AM72<BH72,BH72,(($AI72-SUM($AO73:BG73))*$AM72)),0) -> 0 | BI73: =SUM(AO73:BH73) -> 0
AN74: Amort/mês | AO74: =AO73/12 -> 0 | AP74: =AP73/12 -> 0 | AQ74: =AQ73/12 -> 0 | AR74: =AR73/12 -> 0 | AS74: =AS73/12 -> 0 | AT74: =AT73/12 -> 0 | AU74: =AU73/12 -> 0 | AV74: =AV73/12 -> 0 | ... BH74: =BH73/12 -> 0
AH75: 19 | AI75: =H36 -> 0 | AJ75: =I36 -> 0 | AK75: =IF(AJ75=0,0,ROUNDUP(100/AJ75/100,2)) -> 0 | AL75: =IF(AND(AK75>=1,AK75<=4),1.5,IF(AND(AK75>4,AK75<=6),2,2.5)) -> 2.5 | AM75: =AJ75*AL75 -> 0 | AN75: Quota | AO75: =IF(AK75=0,"",AI75/AK75) | AP75: =IF($AK75-AP$20<0,"",($AI75-$AO76)/($AK75-AO$20)) | AQ75: =IF($AK75-AQ$20<0,"",($AI75-SUM($AO76:AP76))/($AK75-AP$20)) | AR75: =IF($AK75-AR$20<0,"",($AI75-SUM($AO76:AQ76))/($AK75-AQ$20)) | AS75: =IF($AK75-AS$20<0,"",($AI75-SUM($AO76:AR76))/($AK75-AR$20)) | AT75: =IF($AK75-AT$20<0,"",($AI75-SUM($AO76:AS76))/($AK75-AS$20)) | AU75: =IF($AK75-AU$20<0,"",($AI75-SUM($AO76:AT76))/($AK75-AT$20)) | AV75: =IF($AK75-AV$20<0,"",($AI75-SUM($AO76:AU76))/($AK75-AU$20)) | AW75: =IF($AK75-AW$20<0,"",($AI75-SUM($AO76:AV76))/($AK75-AV$20)) | AX75: =IF($AK75-AX$20<0,"",($AI75-SUM($AO76:AW76))/($AK75-AW$20)) | ... BH75: =IF($AK75-BH$20<0,"",($AI75-SUM($AO76:BG76))/($AK75-BG$20))
AN76: Amort/ano | AO76: =IF(AO$20<=$AK75,AI75*AM75,0) -> 0 | AP76: =IF(AP$20<=$AK75,IF(($AI75-$AO76)*$AM75<AP75,AP75,(AI75-AO76)*AM75),0) -> 0 | AQ76: =IF(AQ$20<=$AK75,IF(($AI75-SUM($AO76:AP76))*$AM75<AQ75,AQ75,(($AI75-SUM($AO76:AP76))*$AM75)),0) -> 0 | AR76: =IF(AR$20<=$AK75,IF(($AI75-SUM($AO76:AQ76))*$AM75<AR75,AR75,(($AI75-SUM($AO76:AQ76))*$AM75)),0) -> 0 | AS76: =IF(AS$20<=$AK75,IF(($AI75-SUM($AO76:AR76))*$AM75<AS75,AS75,(($AI75-SUM($AO76:AR76))*$AM75)),0) -> 0 | AT76: =IF(AT$20<=$AK75,IF(($AI75-SUM($AO76:AS76))*$AM75<AT75,AT75,(($AI75-SUM($AO76:AS76))*$AM75)),0) -> 0 | AU76: =IF(AU$20<=$AK75,IF(($AI75-SUM($AO76:AT76))*$AM75<AU75,AU75,(($AI75-SUM($AO76:AT76))*$AM75)),0) -> 0 | AV76: =IF(AV$20<=$AK75,IF(($AI75-SUM($AO76:AU76))*$AM75<AV75,AV75,(($AI75-SUM($AO76:AU76))*$AM75)),0) -> 0 | AW76: =IF(AW$20<=$AK75,IF(($AI75-SUM($AO76:AV76))*$AM75<AW75,AW75,(($AI75-SUM($AO76:AV76))*$AM75)),0) -> 0 | AX76: =IF(AX$20<=$AK75,IF(($AI75-SUM($AO76:AW76))*$AM75<AX75,AX75,(($AI75-SUM($AO76:AW76))*$AM75)),0) -> 0 | ... BH76: =IF(BH$20<=$AK75,IF(($AI75-SUM($AO76:BG76))*$AM75<BH75,BH75,(($AI75-SUM($AO76:BG76))*$AM75)),0) -> 0 | BI76: =SUM(AO76:BH76) -> 0
AN77: Amort/mês | AO77: =AO76/12 -> 0 | AP77: =AP76/12 -> 0 | AQ77: =AQ76/12 -> 0 | AR77: =AR76/12 -> 0 | AS77: =AS76/12 -> 0 | AT77: =AT76/12 -> 0 | AU77: =AU76/12 -> 0 | AV77: =AV76/12 -> 0 | ... BH77: =BH76/12 -> 0
AH78: 20 | AI78: =H37 -> 0 | AJ78: =I37 -> 0 | AK78: =IF(AJ78=0,0,ROUNDUP(100/AJ78/100,2)) -> 0 | AL78: =IF(AND(AK78>=1,AK78<=4),1.5,IF(AND(AK78>4,AK78<=6),2,2.5)) -> 2.5 | AM78: =AJ78*AL78 -> 0 | AN78: Quota | AO78: =IF(AK78=0,"",AI78/AK78) | AP78: =IF($AK78-AP$20<0,"",($AI78-$AO79)/($AK78-AO$20)) | AQ78: =IF($AK78-AQ$20<0,"",($AI78-SUM($AO79:AP79))/($AK78-AP$20)) | AR78: =IF($AK78-AR$20<0,"",($AI78-SUM($AO79:AQ79))/($AK78-AQ$20)) | AS78: =IF($AK78-AS$20<0,"",($AI78-SUM($AO79:AR79))/($AK78-AR$20)) | AT78: =IF($AK78-AT$20<0,"",($AI78-SUM($AO79:AS79))/($AK78-AS$20)) | AU78: =IF($AK78-AU$20<0,"",($AI78-SUM($AO79:AT79))/($AK78-AT$20)) | AV78: =IF($AK78-AV$20<0,"",($AI78-SUM($AO79:AU79))/($AK78-AU$20)) | AW78: =IF($AK78-AW$20<0,"",($AI78-SUM($AO79:AV79))/($AK78-AV$20)) | AX78: =IF($AK78-AX$20<0,"",($AI78-SUM($AO79:AW79))/($AK78-AW$20)) | ... BH78: =IF($AK78-BH$20<0,"",($AI78-SUM($AO79:BG79))/($AK78-BG$20))
AN79: Amort/ano | AO79: =IF(AO$20<=$AK78,AI78*AM78,0) -> 0 | AP79: =IF(AP$20<=$AK78,IF(($AI78-$AO79)*$AM78<AP78,AP78,(AI78-AO79)*AM78),0) -> 0 | AQ79: =IF(AQ$20<=$AK78,IF(($AI78-SUM($AO79:AP79))*$AM78<AQ78,AQ78,(($AI78-SUM($AO79:AP79))*$AM78)),0) -> 0 | AR79: =IF(AR$20<=$AK78,IF(($AI78-SUM($AO79:AQ79))*$AM78<AR78,AR78,(($AI78-SUM($AO79:AQ79))*$AM78)),0) -> 0 | AS79: =IF(AS$20<=$AK78,IF(($AI78-SUM($AO79:AR79))*$AM78<AS78,AS78,(($AI78-SUM($AO79:AR79))*$AM78)),0) -> 0 | AT79: =IF(AT$20<=$AK78,IF(($AI78-SUM($AO79:AS79))*$AM78<AT78,AT78,(($AI78-SUM($AO79:AS79))*$AM78)),0) -> 0 | AU79: =IF(AU$20<=$AK78,IF(($AI78-SUM($AO79:AT79))*$AM78<AU78,AU78,(($AI78-SUM($AO79:AT79))*$AM78)),0) -> 0 | AV79: =IF(AV$20<=$AK78,IF(($AI78-SUM($AO79:AU79))*$AM78<AV78,AV78,(($AI78-SUM($AO79:AU79))*$AM78)),0) -> 0 | AW79: =IF(AW$20<=$AK78,IF(($AI78-SUM($AO79:AV79))*$AM78<AW78,AW78,(($AI78-SUM($AO79:AV79))*$AM78)),0) -> 0 | AX79: =IF(AX$20<=$AK78,IF(($AI78-SUM($AO79:AW79))*$AM78<AX78,AX78,(($AI78-SUM($AO79:AW79))*$AM78)),0) -> 0 | ... BH79: =IF(BH$20<=$AK78,IF(($AI78-SUM($AO79:BG79))*$AM78<BH78,BH78,(($AI78-SUM($AO79:BG79))*$AM78)),0) -> 0 | BI79: =SUM(AO79:BH79) -> 0
AN80: Amort/mês | AO80: =AO79/12 -> 0 | AP80: =AP79/12 -> 0 | AQ80: =AQ79/12 -> 0 | AR80: =AR79/12 -> 0 | AS80: =AS79/12 -> 0 | AT80: =AT79/12 -> 0 | AU80: =AU79/12 -> 0 | AV80: =AV79/12 -> 0 | ... BH80: =BH79/12 -> 0
AH81: 21 | AI81: =H38 -> 0 | AJ81: =I38 -> 0 | AK81: =IF(AJ81=0,0,ROUNDUP(100/AJ81/100,2)) -> 0 | AL81: =IF(AND(AK81>=1,AK81<=4),1.5,IF(AND(AK81>4,AK81<=6),2,2.5)) -> 2.5 | AM81: =AJ81*AL81 -> 0 | AN81: Quota | AO81: =IF(AK81=0,"",AI81/AK81) | AP81: =IF($AK81-AP$20<0,"",($AI81-$AO82)/($AK81-AO$20)) | AQ81: =IF($AK81-AQ$20<0,"",($AI81-SUM($AO82:AP82))/($AK81-AP$20)) | AR81: =IF($AK81-AR$20<0,"",($AI81-SUM($AO82:AQ82))/($AK81-AQ$20)) | AS81: =IF($AK81-AS$20<0,"",($AI81-SUM($AO82:AR82))/($AK81-AR$20)) | AT81: =IF($AK81-AT$20<0,"",($AI81-SUM($AO82:AS82))/($AK81-AS$20)) | AU81: =IF($AK81-AU$20<0,"",($AI81-SUM($AO82:AT82))/($AK81-AT$20)) | AV81: =IF($AK81-AV$20<0,"",($AI81-SUM($AO82:AU82))/($AK81-AU$20)) | AW81: =IF($AK81-AW$20<0,"",($AI81-SUM($AO82:AV82))/($AK81-AV$20)) | AX81: =IF($AK81-AX$20<0,"",($AI81-SUM($AO82:AW82))/($AK81-AW$20)) | ... BH81: =IF($AK81-BH$20<0,"",($AI81-SUM($AO82:BG82))/($AK81-BG$20))
AN82: Amort/ano | AO82: =IF(AO$20<=$AK81,AI81*AM81,0) -> 0 | AP82: =IF(AP$20<=$AK81,IF(($AI81-$AO82)*$AM81<AP81,AP81,(AI81-AO82)*AM81),0) -> 0 | AQ82: =IF(AQ$20<=$AK81,IF(($AI81-SUM($AO82:AP82))*$AM81<AQ81,AQ81,(($AI81-SUM($AO82:AP82))*$AM81)),0) -> 0 | AR82: =IF(AR$20<=$AK81,IF(($AI81-SUM($AO82:AQ82))*$AM81<AR81,AR81,(($AI81-SUM($AO82:AQ82))*$AM81)),0) -> 0 | AS82: =IF(AS$20<=$AK81,IF(($AI81-SUM($AO82:AR82))*$AM81<AS81,AS81,(($AI81-SUM($AO82:AR82))*$AM81)),0) -> 0 | AT82: =IF(AT$20<=$AK81,IF(($AI81-SUM($AO82:AS82))*$AM81<AT81,AT81,(($AI81-SUM($AO82:AS82))*$AM81)),0) -> 0 | AU82: =IF(AU$20<=$AK81,IF(($AI81-SUM($AO82:AT82))*$AM81<AU81,AU81,(($AI81-SUM($AO82:AT82))*$AM81)),0) -> 0 | AV82: =IF(AV$20<=$AK81,IF(($AI81-SUM($AO82:AU82))*$AM81<AV81,AV81,(($AI81-SUM($AO82:AU82))*$AM81)),0) -> 0 | AW82: =IF(AW$20<=$AK81,IF(($AI81-SUM($AO82:AV82))*$AM81<AW81,AW81,(($AI81-SUM($AO82:AV82))*$AM81)),0) -> 0 | AX82: =IF(AX$20<=$AK81,IF(($AI81-SUM($AO82:AW82))*$AM81<AX81,AX81,(($AI81-SUM($AO82:AW82))*$AM81)),0) -> 0 | ... BH82: =IF(BH$20<=$AK81,IF(($AI81-SUM($AO82:BG82))*$AM81<BH81,BH81,(($AI81-SUM($AO82:BG82))*$AM81)),0) -> 0 | BI82: =SUM(AO82:BH82) -> 0
AN83: Amort/mês | AO83: =AO82/12 -> 0 | AP83: =AP82/12 -> 0 | AQ83: =AQ82/12 -> 0 | AR83: =AR82/12 -> 0 | AS83: =AS82/12 -> 0 | AT83: =AT82/12 -> 0 | AU83: =AU82/12 -> 0 | AV83: =AV82/12 -> 0 | ... BH83: =BH82/12 -> 0

Sheet BUDGET
B8: SACCT-Projetos de Investigação Científica e Desenvolvimento Tecnológico (IC&DT)
B10: Quadro de Investimentos Total (Orçamento)
F12: VALOR MÁXIMO DA CANDIDATURA | G12: =+RH_ETI_QUADROS!G45 -> 580219.2
F13: AUTOFINANCIAMENTO (pessoal Interno da UAlg) | G13: =+RH_ETI_QUADROS!G47 -> 145054.8
F14: Overheads para o projeto | G14: =+G12*0.2 -> 116043.84
F15: Bolsas+ Contratos (se aplicável) | G15: =G22+G23 -> 148027.8
F16: VALOR A DISTRIBUIR PELOS CUSTOS DIRETOS | G16: =+G12-G13-G14-G15 -> 171092.76 | H16: =+G31+G30+G29+G28+G27+G26+G25+G24 -> 171092.76
B18: Classificação das Despesas | C18: 2026 | D18: 2027 | E18: 2028 | F18: 2029 | G18: TOTAL
B20: Pessoal Técnico do Beneficiário | C20: =SUM(C21:C23) -> 1782 | D20: =SUM(D21:D23) -> 100899.12 | E20: =SUM(E21:E23) -> 127305.12 | F20: =SUM(F21:F23) -> 63096.36 | G20: =SUM(G21:G23) -> 293082.6
B21: Pessoal Interno UALG | C21: =+RH_ETI_QUADROS!C47 -> 1782 | D21: =+RH_ETI_QUADROS!D47 -> 41688 | E21: =+RH_ETI_QUADROS!E47 -> 68094 | F21: =+RH_ETI_QUADROS!F47 -> 33490.8 | G21: =F21+E21+D21+C21 -> 145054.8
B22: Bolsas | C22: =IF(RH_BOLSEIROS!$E$14="SIM",RH_BOLSEIROS!G24,0) -> 0 | D22: =IF(RH_BOLSEIROS!$E$14="SIM",RH_BOLSEIROS!K24,0) -> 59211.12 | E22: =IF(RH_BOLSEIROS!$E$14="SIM",RH_BOLSEIROS!O24,0) -> 59211.12 | F22: =IF(RH_BOLSEIROS!$E$14="SIM",RH_BOLSEIROS!S24,0) -> 29605.56 | G22: =F22+E22+D22+C22 -> 148027.8
B23: CONTRATOS | C23: =IF(RH_CONTRATOS!$E$14="SIM",RH_CONTRATOS!I24,"0") -> 0 | D23: =IF(RH_CONTRATOS!$E$14="SIM",RH_CONTRATOS!O24,"0") -> 0 | E23: =IF(RH_CONTRATOS!$E$14="SIM",RH_CONTRATOS!U24,"0") -> 0 | F23: =IF(RH_CONTRATOS!$E$14="SIM",RH_CONTRATOS!AA24,"0") -> 0 | G23: =F23+E23+D23+C23 -> 0
B24: Viagens e estadas no estrangeiro diretamente imputáveis ao projeto | C24: 2000 | D24: 5000 | E24: 10000 | F24: 9000 | G24: =F24+E24+D24+C24 -> 26000
B25: Matérias Primas e materiais consumíveis | C25: 4684.63 | D25: 12000 | E25: 7000 | F25: 0 | G25: =F25+E25+D25+C25 -> 23684.63
B26: Aquisição de serviços a terceiros | C26: 0 | D26: 21000 | E26: 20900 | F26: 1000 | G26: =F26+E26+D26+C26 -> 42900
B27: Aquisição de Instrumentos e equipamento cientifico e técnico | C27: =Equipamento!R39 -> 50508.13 | D27: =Equipamento!S39 -> 0 | E27: =Equipamento!T39 -> 0 | F27: =Equipamento!U39 -> 0 | G27: =F27+E27+D27+C27 -> 50508.13
B28: Aquisição de software específico do projeto | C28: 0 | D28: 2000 | E28: 4000 | F28: 0 | G28: =F28+E28+D28+C28 -> 6000
B29: Despesas com a promoção e divulgação de resultados | C29: 0 | D29: 0 | E29: 10000 | F29: 10000 | G29: =F29+E29+D29+C29 -> 20000
B30: Aquisição de patentes | C30: 0 | D30: 0 | E30: 0 | F30: 2000 | G30: =F30+E30+D30+C30 -> 2000
B31: Despesas com o processo de certificação so sistema de gestão da investigação | C31: 0 | D31: 0 | E31: 0 | F31: 0 | G31: =F31+E31+D31+C31 -> 0
B32: CUSTOS DIRETOS | C32: =+C27+C26+C25+C24+C20+C28+C29+C30+C31 -> 58974.76 | D32: =+D27+D26+D25+D24+D20+D28+D29+D30+D31 -> 140899.12 | E32: =+E27+E26+E25+E24+E20+E28+E29+E30+E31 -> 179205.12 | F32: =+F27+F26+F25+F24+F20+F28+F29+F30+F31 -> 85096.36 | G32: =G20+G24+G25+G26+G27+G28+G29+G30+G31 -> 464175.36
B33: Custos Indiretos (25%) | C33: =(C32)*0.25 -> 14743.69 | D33: =(D32)*0.25 -> 35224.78 | E33: =(E32)*0.25 -> 44801.28 | F33: =(F32)*0.25 -> 21274.09 | G33: =+G32*0.25 -> 116043.84
B34: CUSTO TOTAL | C34: =+C32+C33 -> 73718.45 | D34: =+D32+D33 -> 176123.9 | E34: =+E32+E33 -> 224006.4 | F34: =+F32+F33 -> 106370.45 | G34: =SUM(C34:F34) -> 580219.2
B36: TAXA DE COMPARTICIPAÇÂO | C36: 0.75
B37: Comparticipação | C37: =+C34*$C$36 -> 55288.837 | D37: =+D34*$C$36 -> 132092.92 | E37: =+E34*$C$36 -> 168004.8 | F37: =+F34*$C$36 -> 79777.837 | G37: =+C37+D37+E37+F37 -> 435164.4
B39: AUTOFINANCIAMENTO | G39: =+G34-G37 -> 145054.8
F41: Financiamento do projecto: | G41: =+G37 -> 435164.4
F42: Despesas Diretas do projeto | G42: =G22+G24+G25+G26+G27+G23+G28+G29+G30+G31 -> 319120.56
F43: Equipto não amortizado | G43: =Equipamento!P39 -> 5491.88
F44: Outras despesas não elegiveís
F45: Total das despesas efectivas do projecto: | G45: =SUM(G42:G44) -> 324612.44
F46: Financiamento do projecto-Total das despesas efectivas do projecto: | G46: =G41-G45 -> 110551.96
F47: TAXA DE OVERHEADS | G47: =+G46/G34 -> 0.19053482

Sheet Orçamento
B8: =+#REF! -> #REF!
B10: Ref.ª Candidatura:
B11: Titulo Candidatura:
B12: Tipologia de Projeto | C12: =+RESUMO!$E$21 -> Universidade do Algarve
B13: Investigador Responsável (IR):
B14: Data Inicio:
B15: N.º Meses:
B16: Quadro de Investimentos Total (Orçamento)
B18: Os Custos de Pessoal e Equipamento têm que ser preenchidos nas respetivas folhas (Calculo Bolsas e Contratação / Calculo Equipamento). Os calculos obtidos nessas folhas são apresentados automáticamente nas respetivas linhas do orçamento.
F19: VALOR MÁXIMO DA CANDIDATURA | G19: 250000
B20: Classificação das Despesas | C20: 2025 | D20: 2026 | E20: 2027 | F20: 2028 | G20: TOTAL
B22: Recursos Humanos | C22: =SUM(C23:C25) -> #REF! | D22: =SUM(D23:D25) -> #REF! | E22: =SUM(E23:E25) -> #REF! | F22: =SUM(F23:F25) -> #REF! | G22: =SUM(G23:G25) -> #REF!
B23: Pessoal Interno UALG | C23: =RH_EQUIPA!#REF! -> #REF! | D23: =RH_EQUIPA!#REF! -> #REF! | E23: =RH_EQUIPA!#REF! -> #REF! | F23: =RH_EQUIPA!#REF! -> #REF! | G23: =F23+E23+D23+C23 -> #REF!
B24: Bolsas | C24: =RH_EQUIPA!#REF! -> #REF! | D24: =RH_EQUIPA!#REF! -> #REF! | E24: =RH_EQUIPA!#REF! -> #REF! | F24: =RH_EQUIPA!#REF! -> #REF! | G24: =F24+E24+D24+C24 -> #REF!
B25: CONTRATOS | C25: =RH_EQUIPA!#REF! -> #REF! | D25: =RH_EQUIPA!#REF! -> #REF! | E25: =RH_EQUIPA!#REF! -> #REF! | F25: =RH_EQUIPA!#REF! -> #REF! | G25: =F25+E25+D25+C25 -> #REF!
B26: Missões | C26: 2000 | D26: 2500 | E26: 2500 | F26: 0 | G26: =F26+E26+D26+C26 -> 7000
B27: Aquisição de outros bens e serviços | C27: 25000 | D27: 15000 | E27: 15000 | F27: 0 | G27: =F27+E27+D27+C27 -> 55000
B28: Demonstração, promoção e divulgação | C28: 0 | D28: 3500 | E28: 3000 | F28: 0 | G28: =F28+E28+D28+C28 -> 6500
B29: Adaptação de edificios e instalações | C29: 0 | D29: 0 | E29: 0 | F29: 0 | G29: =F29+E29+D29+C29 -> 0
B30: Registo de patentes | C30: 0 | D30: 0 | E30: 0 | F30: 0 | G30: =F30+E30+D30+C30 -> 0
B31: Instrumentos e equipamento cientifico | C31: =+#REF! -> #REF! | D31: =+#REF! -> #REF! | E31: =+#REF! -> #REF! | F31: =+#REF! -> #REF! | G31: =F31+E31+D31+C31 -> #REF!
B32: Subcontratos | C32: 0 | D32: 0 | E32: 0 | F32: 0 | G32: =F32+E32+D32+C32 -> 0
B33: Custos Diretos | C33: =C32+C31+C30+C29+C28+C27+C26+C22 -> #REF! | D33: =D32+D31+D30+D29+D28+D27+D26+D22 -> #REF! | E33: =E32+E31+E30+E29+E28+E27+E26+E22 -> #REF! | F33: =F32+F31+F30+F29+F28+F27+F26+F22 -> #REF! | G33: =G32+G31+G30+G29+G28+G27+G26+G22 -> #REF!
B34: Custos Indiretos (25%) | C34: =(C22+C26+C27+C28+C29+C30+C31)*0.25 -> #REF! | D34: =(D22+D26+D27+D28+D29+D30+D31)*0.25 -> #REF! | E34: =(E22+E26+E27+E28+E29+E30+E31)*0.25 -> #REF! | F34: =(F22+F26+F27+F28+F29+F30+F31)*0.25 -> #REF! | G34: =(G22+G26+G27+G28+G29+G30+G31)*0.25 -> #REF!
B35: Financiamento | C35: =C37*C39 -> #REF! | D35: =D37*D39 -> #REF! | E35: =E37*E39 -> #REF! | F35: =F37 -> #REF! | G35: =SUM(C35:F35) -> #REF!
B36: Autofinanciamento | C36: =C37-C35 -> #REF! | D36: =D37-D35 -> #REF! | E36: =E37-E35 -> #REF! | F36: =F37-F35 -> #REF! | G36: =G37-G35 -> #REF!
B37: TOTAL | C37: =C34+C33 -> #REF! | D37: =D34+D33 -> #REF! | E37: =E34+E33 -> #REF! | F37: =F34+F33 -> #REF! | G37: =G34+G33 -> #REF! | I37: =IF(G37=#REF!,"Orçamento ditribuído Igual ao OCS","VERIFICAR NOVAMENTE") -> #REF!
B39: Comparticipação | C39: 0.8 | D39: 0.8 | E39: 0.8 | F39: 0.8 | G39: 0.8
F42: Financiamento do projecto: | G42: =G35 -> #REF!
B43: FEDER (40% de comparticipação) | C43: =+G37*0.4 -> #REF! | F43: Despesas Diretas do projeto | G43: =G24+G26+G27+G28+G29+G30+G31+G32 -> #REF!
B44: OE (60% de Comparticipação) | C44: =+G37*0.6 -> #REF! | F44: Equipto não amortizado | G44: =+#REF! -> #REF!
F45: Outras despesas não elegiveís | G45: =RH_EQUIPA!#REF! -> #REF!
F46: Total das despesas efectivas do projecto: | G46: =SUM(G43:G45) -> #REF!
F47: Financiamento do projecto-Total das despesas efectivas do projecto: | G47: =G42-G46 -> #REF!
F48: TAXA DE OVERHEADS | G48: =+G47/G42 -> #REF!

Sheet Valores bolsas e 57_2016
A1: Bolsas de investigação pós doutoral | B1: 1851
A2: Bolsas de Investigação (BI)- estudantes de doutoramento | B2: 1309.64
A3: Bolsas de Investigação (BI) - estudandes licenciados ou mestres | B3: 1040.98
A4: Bolsas de Iniciação à Investigação | B4: 651.12
A5: Sem bolsa | B5: 0
B6: EXC | C6: INTEGRAL | D6: FCT | E6: ABC-RI | F6: Sim
A7: Investigador Júnior | B7: 2351.53 | D7: FE | E7: CEAACP | F7: Não
A8: Investigador Auxiliar | B8: 3501.28 | D8: FCHS | E8: CEAD
A9: Investigador Principal/auxiliar Com Habilitação ou agregação | B9: 3950.17 | D9: FCBM | E9: CEFAGE
A10: Investigador Principal | B10: 4399.05 | D10: ISE | E10: CENSE
A11: Investigador Coordenador | B11: 5117.26 | D11: ESGHT | E11: CEOT
A12: Sem Contrato | B12: 0 | D12: ESEC | E12: CIAC
D13: ESSaúde | E13: CIMA
E14: CINTESIS
A15: Missões | E15: CinTurs
A16: Aquisição de outros bens e serviços | E16: CIP
A17: Demonstração, promoção e divulgação | E17: CITUR
A18: Adaptação de edificios e instalações | E18: ICARHEB
A19: Registo de patentes | E19: MED
A20: Instrumentos e equipamento cientifico
A21: Subcontratos
A22: Pessoal Interno UALG
A23: Bolsas
A24: CONTRATOS
A28: Contrato trabalho com o beneficiário
A29: Bolseiro de Investigação- a contratar
A30: Contrato de Investigador - DL.56-2016
A31: Acordo Escrito com a entidade
A34: Universidade do Algarve
A35: Entidade A
A36: Entidade B
... A41: EQUIPA
A42: =IF(RH_EQUIPA!B19>0,RH_EQUIPA!C19,"") -> Ana Cristina Coelho
A43: =IF(RH_EQUIPA!B20>0,RH_EQUIPA!C20,"") -> Ana Maria Costa
A44: =IF(RH_EQUIPA!B21>0,RH_EQUIPA!C21,"") -> Cristina Veiga-Pires
A45: =IF(RH_EQUIPA!B22>0,RH_EQUIPA!C22,"") -> Jorge Semião
A46: =IF(RH_EQUIPA!B23>0,RH_EQUIPA!C23,"") -> Jânio Monteiro
A47: =IF(RH_EQUIPA!B24>0,RH_EQUIPA!C24,"") -> Pedro cardoso
A48: =IF(RH_EQUIPA!B25>0,RH_EQUIPA!C25,"") -> Roberto Lam
A49: =IF(RH_EQUIPA!B26>0,RH_EQUIPA!C26,"") -> Cristiano Cabrita
A50: =IF(RH_EQUIPA!B27>0,RH_EQUIPA!C27,"") -> Jaime Martins
A51: =IF(RH_EQUIPA!B28>0,RH_EQUIPA!C28,"") -> Paulo Silva
A52: =IF(RH_EQUIPA!B29>0,RH_EQUIPA!C29,"") -> João Rodrigues
A53: =IF(RH_EQUIPA!B30>0,RH_EQUIPA!C30,"") -> Joana Lessa
... A56: =IF(RH_EQUIPA!B33>0,RH_EQUIPA!C33,"")
A57: =IF(RH_EQUIPA!B34>0,RH_EQUIPA!B34,"") -> B1
A58: =IF(RH_EQUIPA!B35>0,RH_EQUIPA!B35,"") -> B2
A59: =IF(RH_EQUIPA!B36>0,RH_EQUIPA!B36,"") -> B3
A60: =IF(RH_EQUIPA!B37>0,RH_EQUIPA!B37,"") -> B4
A61: =IF(RH_EQUIPA!B38>0,RH_EQUIPA!C38,"")
A62: =IF(RH_EQUIPA!B39>0,RH_EQUIPA!C39,"")
